Workbook
Name Contas: 'Plano de Contas'!$B$4:$B$52
Name Documentos: 'Plano de Contas'!$E$4:$E$9

Sheet Plano de Contas
A2: Plano de Contas
B4: Contas | C4: Descrição | E4: Documentos
B5: RECEITAS OPERACIONAIS | C5: Receitas derivadas da atividade principal da empresa | E5: Cartão de crédito
B6: Consultoria | C6: Receita advinda da atividade de consultoria em sistemas de informação | E6: Cobrança bancária
B7: Licença de software | C7: Receita de venda de sistemas e/ou licença de sistemas | E7: Cheque
B8: Manutenção de estrutura | C8: Receita advinda de contratos de manutenção em estrutura de tecnologia | E8: Deposito bancário
B9: Manutenção de Sistemas | C9: Receitas advindas das manutenções dos sistemas desenvolvidos pela empresa | E9: Dinheiro
B10: Outras receitas | C10: Outras receitas não especificadas
B11: DESPESAS FIXAS | C11: Despesas de natureza operacional e não relacionadas ao volume de atividade
B12: Água | C12: Despesas de água encanada e água mineral
B13: Aluguel | C13: Aluguel do prédio
B14: Cartório | C14: Despesas de cartório
B15: Combustível | C15: Despesas de combustível dos veículos
B16: Correios | C16: Despesas de envio de cartas, mala direta e sedex
B17: Encargos sociais | C17: Despesas de encargos sociais sobre a folha, seguro de vida e plano de saúde
B18: Energia | C18: Energia elétrica
B19: Fones / Comunicação | C19: Despesas de telefones fixo e móvel e internet
B20: Impostos/taxas diversas | C20: Impostos e taxas diversas, tais como IPTU, IPVA, CPMF, taxas de conselhos e sindicatos, taxas de concorrências públicas, etc.
B21: Manutenção equipamentos | C21: Manutenção de computadores, impressoras, TVs, circuito de TV, copiadora, etc.
... B52: Pgto. empréstimo (juros) | C52: Pagamento de empréstimos contraídos (juros)

Sheet Premissas
A2: Premissas
B4: Ano de avaliação | C4: =TEXT(TODAY(),"aaaa") -> 2020
B5: Saldo Inicial | C5: 0
B7: Faturamento Projetado
B8: Contas | C8: Jan | D8: Fev | E8: Mar | F8: Abr | G8: Mai | H8: Jun | I8: Jul | J8: Ago | K8: Set | L8: Out | M8: Nov | N8: Dez
B9: ='Plano de Contas'!B6 -> Consultoria | C9: 10253 | D9: 10041 | E9: 10342 | F9: 11842 | G9: 11449 | H9: 10189 | I9: 11481 | J9: 11464 | K9: 11205 | L9: 10930 | M9: 11763 | N9: 11251
B10: ='Plano de Contas'!B7 -> Licença de software | C10: 10358 | D10: 10263 | E10: 10055 | F10: 10745 | G10: 10725 | H10: 11887 | I10: 11547 | J10: 10194 | K10: 11618 | L10: 10717 | M10: 10787 | N10: 10904
B11: ='Plano de Contas'!B8 -> Manutenção de estrutura | C11: 5515 | D11: 5379 | E11: 5788 | F11: 4634 | G11: 5447 | H11: 4672 | I11: 5532 | J11: 5451 | K11: 4727 | L11: 5029 | M11: 4485 | N11: 4080
B12: ='Plano de Contas'!B9 -> Manutenção de Sistemas | C12: 1618 | D12: 1998 | E12: 1997 | F12: 1521 | G12: 1551 | H12: 1326 | I12: 1451 | J12: 1611 | K12: 1658 | L12: 1030 | M12: 1165 | N12: 1101
B13: ='Plano de Contas'!B10 -> Outras receitas | C13: 933 | D13: 965 | E13: 886 | F13: 930 | G13: 901 | H13: 897 | I13: 892 | J13: 987 | K13: 978 | L13: 890 | M13: 806 | N13: 922
B15: Total | C15: =SUM(C9:C13) -> 28677 | D15: =SUM(D9:D13) -> 28646 | E15: =SUM(E9:E13) -> 29068 | F15: =SUM(F9:F13) -> 29672 | G15: =SUM(G9:G13) -> 30073 | H15: =SUM(H9:H13) -> 28971 | I15: =SUM(I9:I13) -> 30903 | J15: =SUM(J9:J13) -> 29707 | ... N15: =SUM(N9:N13) -> 28258
B17: Despesas Fixas Mensais
B18: ='Plano de Contas'!B12 -> Água | C18: 90
B19: ='Plano de Contas'!B13 -> Aluguel | C19: 500
B20: ='Plano de Contas'!B14 -> Cartório | C20: 150
B21: ='Plano de Contas'!B15 -> Combustível | C21: 500
B22: ='Plano de Contas'!B16 -> Correios | C22: 150
B23: ='Plano de Contas'!B17 -> Encargos sociais | C23: 4000
B24: ='Plano de Contas'!B18 -> Energia | C24: 1200
B25: ='Plano de Contas'!B19 -> Fones / Comunicação | C25: 200
B26: ='Plano de Contas'!B20 -> Impostos/taxas diversas | C26: 1000
B27: ='Plano de Contas'!B21 -> Manutenção equipamentos | C27: 600
B28: ='Plano de Contas'!B22 -> Manutenção prédio | C28: 600
B29: ='Plano de Contas'!B23 -> Material escritório | C29: 246
... B38: ='Plano de Contas'!B32 -> Viagens | C38: 208
B40: Despesas Variáveis
B41: ='Plano de Contas'!B34 -> Comissões | C41: 0.05 | D41: Pago em M sobre o faturamento
B42: ='Plano de Contas'!B35 -> Impostos estaduais | C42: 0 | D42: Não tem comercialização de produtos
B43: ='Plano de Contas'!B36 -> Impostos federais | C43: 0.1133 | D43: Pago em M+1 sobre faturamento. PIS 0,65%, Confins 3%, Cont. Social 2,88%, IRPJ 4,8%
B44: ='Plano de Contas'!B37 -> Impostos municipais | C44: 0.05 | D44: Pago em M+1 sobre faturamento. ISS 5,00%
B45: ='Plano de Contas'!B38 -> Outras despesas variáveis | C45: 0

Sheet Receitas
A2: Receitas
C4: Regras de Faturamento
B5: Serviços | C5: À Vista | D5: 30 dias
B6: ='Plano de Contas'!B6 -> Consultoria | C6: 0.5 | D6: 0.5
B7: ='Plano de Contas'!B7 -> Licença de software | C7: 0.5 | D7: 0.5
B8: ='Plano de Contas'!B8 -> Manutenção de estrutura | C8: 0.25 | D8: 0.75
B9: ='Plano de Contas'!B9 -> Manutenção de Sistemas | D9: 1
B10: ='Plano de Contas'!B10 -> Outras receitas | D10: 1
B12: Faturamento Projetado
C13: =Premissas!C8 -> Jan | D13: =Premissas!D8 -> Fev | E13: =Premissas!E8 -> Mar | F13: =Premissas!F8 -> Abr | G13: =Premissas!G8 -> Mai | H13: =Premissas!H8 -> Jun | I13: =Premissas!I8 -> Jul | J13: =Premissas!J8 -> Ago | ... N13: =Premissas!N8 -> Dez
B14: =Premissas!B9 -> Consultoria | C14: =Premissas!C9 -> 10253 | D14: =Premissas!D9 -> 10041 | E14: =Premissas!E9 -> 10342 | F14: =Premissas!F9 -> 11842 | G14: =Premissas!G9 -> 11449 | H14: =Premissas!H9 -> 10189 | I14: =Premissas!I9 -> 11481 | ... N14: =Premissas!N9 -> 11251
B15: =Premissas!B10 -> Licença de software | C15: =Premissas!C10 -> 10358 | D15: =Premissas!D10 -> 10263 | E15: =Premissas!E10 -> 10055 | F15: =Premissas!F10 -> 10745 | G15: =Premissas!G10 -> 10725 | H15: =Premissas!H10 -> 11887 | I15: =Premissas!I10 -> 11547 | ... N15: =Premissas!N10 -> 10904
B16: =Premissas!B11 -> Manutenção de estrutura | C16: =Premissas!C11 -> 5515 | D16: =Premissas!D11 -> 5379 | E16: =Premissas!E11 -> 5788 | F16: =Premissas!F11 -> 4634 | G16: =Premissas!G11 -> 5447 | H16: =Premissas!H11 -> 4672 | I16: =Premissas!I11 -> 5532 | ... N16: =Premissas!N11 -> 4080
B17: =Premissas!B12 -> Manutenção de Sistemas | C17: =Premissas!C12 -> 1618 | D17: =Premissas!D12 -> 1998 | E17: =Premissas!E12 -> 1997 | F17: =Premissas!F12 -> 1521 | G17: =Premissas!G12 -> 1551 | H17: =Premissas!H12 -> 1326 | I17: =Premissas!I12 -> 1451 | ... N17: =Premissas!N12 -> 1101
B18: =Premissas!B13 -> Outras receitas | C18: =Premissas!C13 -> 933 | D18: =Premissas!D13 -> 965 | E18: =Premissas!E13 -> 886 | F18: =Premissas!F13 -> 930 | G18: =Premissas!G13 -> 901 | H18: =Premissas!H13 -> 897 | I18: =Premissas!I13 -> 892 | ... N18: =Premissas!N13 -> 922
B19: Total | C19: =SUM(C14:C18) -> 28677 | D19: =SUM(D14:D18) -> 28646 | E19: =SUM(E14:E18) -> 29068 | F19: =SUM(F14:F18) -> 29672 | G19: =SUM(G14:G18) -> 30073 | H19: =SUM(H14:H18) -> 28971 | I19: =SUM(I14:I18) -> 30903 | J19: =SUM(J14:J18) -> 29707 | ... N19: =SUM(N14:N18) -> 28258 | R19: =SUM(C19:Q19) -> 351763
B22: Receita Projetada
C23: =C13 -> Jan | D23: =D13 -> Fev | E23: =E13 -> Mar | F23: =F13 -> Abr | G23: =G13 -> Mai | H23: =H13 -> Jun | I23: =I13 -> Jul | J23: =J13 -> Ago | ... N23: =N13 -> Dez | O23: Jan
B24: =B14 -> Consultoria | C24: =C14*C6 -> 5126.5 | D24: =(D14*$C6)+(C14*$D6) -> 10147 | E24: =(E14*$C6)+(D14*$D6) -> 10191.5 | F24: =(F14*$C6)+(E14*$D6) -> 11092 | G24: =(G14*$C6)+(F14*$D6) -> 11645.5 | H24: =(H14*$C6)+(G14*$D6) -> 10819 | I24: =(I14*$C6)+(H14*$D6) -> 10835 | J24: =(J14*$C6)+(I14*$D6) -> 11472.5 | K24: =(K14*$C6)+(J14*$D6) -> 11334.5 | ... O24: =(O14*$C6)+(N14*$D6) -> 5625.5
B25: =B15 -> Licença de software | C25: =C15*C7 -> 5179 | D25: =(D15*$C7)+(C15*$D7) -> 10310.5 | E25: =(E15*$C7)+(D15*$D7) -> 10159 | F25: =(F15*$C7)+(E15*$D7) -> 10400 | G25: =(G15*$C7)+(F15*$D7) -> 10735 | H25: =(H15*$C7)+(G15*$D7) -> 11306 | I25: =(I15*$C7)+(H15*$D7) -> 11717 | J25: =(J15*$C7)+(I15*$D7) -> 10870.5 | K25: =(K15*$C7)+(J15*$D7) -> 10906 | ... O25: =(O15*$C7)+(N15*$D7) -> 5452
B26: =B16 -> Manutenção de estrutura | C26: =C16*C8 -> 1378.75 | D26: =(D16*$C8)+(C16*$D8) -> 5481 | E26: =(E16*$C8)+(D16*$D8) -> 5481.25 | F26: =(F16*$C8)+(E16*$D8) -> 5499.5 | G26: =(G16*$C8)+(F16*$D8) -> 4837.25 | H26: =(H16*$C8)+(G16*$D8) -> 5253.25 | I26: =(I16*$C8)+(H16*$D8) -> 4887 | J26: =(J16*$C8)+(I16*$D8) -> 5511.75 | K26: =(K16*$C8)+(J16*$D8) -> 5270 | ... O26: =(O16*$C8)+(N16*$D8) -> 3060
B27: =B17 -> Manutenção de Sistemas | C27: =C17*C9 -> 0 | D27: =(D17*$C9)+(C17*$D9) -> 1618 | E27: =(E17*$C9)+(D17*$D9) -> 1998 | F27: =(F17*$C9)+(E17*$D9) -> 1997 | G27: =(G17*$C9)+(F17*$D9) -> 1521 | H27: =(H17*$C9)+(G17*$D9) -> 1551 | I27: =(I17*$C9)+(H17*$D9) -> 1326 | J27: =(J17*$C9)+(I17*$D9) -> 1451 | K27: =(K17*$C9)+(J17*$D9) -> 1611 | ... O27: =(O17*$C9)+(N17*$D9) -> 1101
B28: =B18 -> Outras receitas | C28: =C18*C10 -> 0 | D28: =(D18*$C10)+(C18*$D10) -> 933 | E28: =(E18*$C10)+(D18*$D10) -> 965 | F28: =(F18*$C10)+(E18*$D10) -> 886 | G28: =(G18*$C10)+(F18*$D10) -> 930 | H28: =(H18*$C10)+(G18*$D10) -> 901 | I28: =(I18*$C10)+(H18*$D10) -> 897 | J28: =(J18*$C10)+(I18*$D10) -> 892 | K28: =(K18*$C10)+(J18*$D10) -> 987 | ... O28: =(O18*$C10)+(N18*$D10) -> 922
B29: Total | C29: =SUM(C24:C28) -> 11684.25 | D29: =SUM(D24:D28) -> 28489.5 | E29: =SUM(E24:E28) -> 28794.75 | F29: =SUM(F24:F28) -> 29874.5 | G29: =SUM(G24:G28) -> 29668.75 | H29: =SUM(H24:H28) -> 29830.25 | I29: =SUM(I24:I28) -> 29662 | J29: =SUM(J24:J28) -> 30197.75 | ... O29: =SUM(O24:O28) -> 16160.5 | R29: =SUM(C29:N29) -> 335602.5

Sheet Fluxo_Projetado
A2: ="Fluxo de Caixa Projetado - "&Premissas!C4 -> Fluxo de Caixa Projetado - 2020
B4: Contas | C4: Jan | D4: Fev | E4: Mar | F4: Abr | G4: Mai | H4: Jun | I4: Jul | J4: Ago | K4: Set | L4: Out | M4: Nov | N4: Dez | O4: Jan | P4: Total | Q4: Média
B5: ='Plano de Contas'!B5 -> RECEITAS OPERACIONAIS | C5: =SUM(C6:C10) -> 11684.25 | D5: =SUM(D6:D10) -> 28489.5 | E5: =SUM(E6:E10) -> 28794.75 | F5: =SUM(F6:F10) -> 29874.5 | G5: =SUM(G6:G10) -> 29668.75 | H5: =SUM(H6:H10) -> 29830.25 | I5: =SUM(I6:I10) -> 29662 | J5: =SUM(J6:J10) -> 30197.75 | ... O5: =SUM(O6:O10) -> 16160.5 | P5: =SUM(C5:O5) -> 351763 | Q5: =IF(P5=0,0,AVERAGE(C5:O5)) -> 27058.692
B6: ='Plano de Contas'!B6 -> Consultoria | C6: =Receitas!C24 -> 5126.5 | D6: =Receitas!D24 -> 10147 | E6: =Receitas!E24 -> 10191.5 | F6: =Receitas!F24 -> 11092 | G6: =Receitas!G24 -> 11645.5 | H6: =Receitas!H24 -> 10819 | I6: =Receitas!I24 -> 10835 | J6: =Receitas!J24 -> 11472.5 | ... O6: =Receitas!O24 -> 5625.5 | P6: =SUM(C6:O6) -> 132210 | Q6: =IF(P6=0,0,AVERAGE(C6:O6)) -> 10170
B7: ='Plano de Contas'!B7 -> Licença de software | C7: =Receitas!C25 -> 5179 | D7: =Receitas!D25 -> 10310.5 | E7: =Receitas!E25 -> 10159 | F7: =Receitas!F25 -> 10400 | G7: =Receitas!G25 -> 10735 | H7: =Receitas!H25 -> 11306 | I7: =Receitas!I25 -> 11717 | J7: =Receitas!J25 -> 10870.5 | ... O7: =Receitas!O25 -> 5452 | P7: =SUM(C7:O7) -> 129800 | Q7: =IF(P7=0,0,AVERAGE(C7:O7)) -> 9984.6154
B8: ='Plano de Contas'!B8 -> Manutenção de estrutura | C8: =Receitas!C26 -> 1378.75 | D8: =Receitas!D26 -> 5481 | E8: =Receitas!E26 -> 5481.25 | F8: =Receitas!F26 -> 5499.5 | G8: =Receitas!G26 -> 4837.25 | H8: =Receitas!H26 -> 5253.25 | I8: =Receitas!I26 -> 4887 | J8: =Receitas!J26 -> 5511.75 | ... O8: =Receitas!O26 -> 3060 | P8: =SUM(C8:O8) -> 60739 | Q8: =IF(P8=0,0,AVERAGE(C8:O8)) -> 4672.2308
B9: ='Plano de Contas'!B9 -> Manutenção de Sistemas | C9: =Receitas!C27 -> 0 | D9: =Receitas!D27 -> 1618 | E9: =Receitas!E27 -> 1998 | F9: =Receitas!F27 -> 1997 | G9: =Receitas!G27 -> 1521 | H9: =Receitas!H27 -> 1551 | I9: =Receitas!I27 -> 1326 | J9: =Receitas!J27 -> 1451 | ... O9: =Receitas!O27 -> 1101 | P9: =SUM(C9:O9) -> 18027 | Q9: =IF(P9=0,0,AVERAGE(C9:O9)) -> 1386.6923
B10: ='Plano de Contas'!B10 -> Outras receitas | C10: =Receitas!C28 -> 0 | D10: =Receitas!D28 -> 933 | E10: =Receitas!E28 -> 965 | F10: =Receitas!F28 -> 886 | G10: =Receitas!G28 -> 930 | H10: =Receitas!H28 -> 901 | I10: =Receitas!I28 -> 897 | J10: =Receitas!J28 -> 892 | ... O10: =Receitas!O28 -> 922 | P10: =SUM(C10:O10) -> 10987 | Q10: =IF(P10=0,0,AVERAGE(C10:O10)) -> 845.15385
B11: ='Plano de Contas'!B11 -> DESPESAS FIXAS | C11: =SUM(C12:C32) -> -11190 | D11: =SUM(D12:D32) -> -11190 | E11: =SUM(E12:E32) -> -11190 | F11: =SUM(F12:F32) -> -11190 | G11: =SUM(G12:G32) -> -11190 | H11: =SUM(H12:H32) -> -11190 | I11: =SUM(I12:I32) -> -11190 | J11: =SUM(J12:J32) -> -11190 | ... O11: =SUM(O12:O32) -> -11190 | P11: =SUM(C11:O11) -> -145470 | Q11: =IF(P11=0,0,AVERAGE(C11:O11)) -> -11190
B12: ='Plano de Contas'!B12 -> Água | C12: =-Premissas!$C18 -> -90 | D12: =-Premissas!$C18 -> -90 | E12: =-Premissas!$C18 -> -90 | F12: =-Premissas!$C18 -> -90 | G12: =-Premissas!$C18 -> -90 | H12: =-Premissas!$C18 -> -90 | I12: =-Premissas!$C18 -> -90 | J12: =-Premissas!$C18 -> -90 | ... O12: =-Premissas!$C18 -> -90 | P12: =SUM(C12:O12) -> -1170 | Q12: =IF(P12=0,0,AVERAGE(C12:O12)) -> -90
B13: ='Plano de Contas'!B13 -> Aluguel | C13: =-Premissas!$C19 -> -500 | D13: =-Premissas!$C19 -> -500 | E13: =-Premissas!$C19 -> -500 | F13: =-Premissas!$C19 -> -500 | G13: =-Premissas!$C19 -> -500 | H13: =-Premissas!$C19 -> -500 | I13: =-Premissas!$C19 -> -500 | J13: =-Premissas!$C19 -> -500 | ... O13: =-Premissas!$C19 -> -500 | P13: =SUM(C13:O13) -> -6500 | Q13: =IF(P13=0,0,AVERAGE(C13:O13)) -> -500
B14: ='Plano de Contas'!B14 -> Cartório | C14: =-Premissas!$C20 -> -150 | D14: =-Premissas!$C20 -> -150 | E14: =-Premissas!$C20 -> -150 | F14: =-Premissas!$C20 -> -150 | G14: =-Premissas!$C20 -> -150 | H14: =-Premissas!$C20 -> -150 | I14: =-Premissas!$C20 -> -150 | J14: =-Premissas!$C20 -> -150 | ... O14: =-Premissas!$C20 -> -150 | P14: =SUM(C14:O14) -> -1950 | Q14: =IF(P14=0,0,AVERAGE(C14:O14)) -> -150
B15: ='Plano de Contas'!B15 -> Combustível | C15: =-Premissas!$C21 -> -500 | D15: =-Premissas!$C21 -> -500 | E15: =-Premissas!$C21 -> -500 | F15: =-Premissas!$C21 -> -500 | G15: =-Premissas!$C21 -> -500 | H15: =-Premissas!$C21 -> -500 | I15: =-Premissas!$C21 -> -500 | J15: =-Premissas!$C21 -> -500 | ... O15: =-Premissas!$C21 -> -500 | P15: =SUM(C15:O15) -> -6500 | Q15: =IF(P15=0,0,AVERAGE(C15:O15)) -> -500
B16: ='Plano de Contas'!B16 -> Correios | C16: =-Premissas!$C22 -> -150 | D16: =-Premissas!$C22 -> -150 | E16: =-Premissas!$C22 -> -150 | F16: =-Premissas!$C22 -> -150 | G16: =-Premissas!$C22 -> -150 | H16: =-Premissas!$C22 -> -150 | I16: =-Premissas!$C22 -> -150 | J16: =-Premissas!$C22 -> -150 | ... O16: =-Premissas!$C22 -> -150 | P16: =SUM(C16:O16) -> -1950 | Q16: =IF(P16=0,0,AVERAGE(C16:O16)) -> -150
B17: ='Plano de Contas'!B17 -> Encargos sociais | C17: =-Premissas!$C23 -> -4000 | D17: =-Premissas!$C23 -> -4000 | E17: =-Premissas!$C23 -> -4000 | F17: =-Premissas!$C23 -> -4000 | G17: =-Premissas!$C23 -> -4000 | H17: =-Premissas!$C23 -> -4000 | I17: =-Premissas!$C23 -> -4000 | J17: =-Premissas!$C23 -> -4000 | ... O17: =-Premissas!$C23 -> -4000 | P17: =SUM(C17:O17) -> -52000 | Q17: =IF(P17=0,0,AVERAGE(C17:O17)) -> -4000
B18: ='Plano de Contas'!B18 -> Energia | C18: =-Premissas!$C24 -> -1200 | D18: =-Premissas!$C24 -> -1200 | E18: =-Premissas!$C24 -> -1200 | F18: =-Premissas!$C24 -> -1200 | G18: =-Premissas!$C24 -> -1200 | H18: =-Premissas!$C24 -> -1200 | I18: =-Premissas!$C24 -> -1200 | J18: =-Premissas!$C24 -> -1200 | ... O18: =-Premissas!$C24 -> -1200 | P18: =SUM(C18:O18) -> -15600 | Q18: =IF(P18=0,0,AVERAGE(C18:O18)) -> -1200
B19: ='Plano de Contas'!B19 -> Fones / Comunicação | C19: =-Premissas!$C25 -> -200 | D19: =-Premissas!$C25 -> -200 | E19: =-Premissas!$C25 -> -200 | F19: =-Premissas!$C25 -> -200 | G19: =-Premissas!$C25 -> -200 | H19: =-Premissas!$C25 -> -200 | I19: =-Premissas!$C25 -> -200 | J19: =-Premissas!$C25 -> -200 | ... O19: =-Premissas!$C25 -> -200 | P19: =SUM(C19:O19) -> -2600 | Q19: =IF(P19=0,0,AVERAGE(C19:O19)) -> -200
B20: ='Plano de Contas'!B20 -> Impostos/taxas diversas | C20: =-Premissas!$C26 -> -1000 | D20: =-Premissas!$C26 -> -1000 | E20: =-Premissas!$C26 -> -1000 | F20: =-Premissas!$C26 -> -1000 | G20: =-Premissas!$C26 -> -1000 | H20: =-Premissas!$C26 -> -1000 | I20: =-Premissas!$C26 -> -1000 | J20: =-Premissas!$C26 -> -1000 | ... O20: =-Premissas!$C26 -> -1000 | P20: =SUM(C20:O20) -> -13000 | Q20: =IF(P20=0,0,AVERAGE(C20:O20)) -> -1000
B21: ='Plano de Contas'!B21 -> Manutenção equipamentos | C21: =-Premissas!$C27 -> -600 | D21: =-Premissas!$C27 -> -600 | E21: =-Premissas!$C27 -> -600 | F21: =-Premissas!$C27 -> -600 | G21: =-Premissas!$C27 -> -600 | H21: =-Premissas!$C27 -> -600 | I21: =-Premissas!$C27 -> -600 | J21: =-Premissas!$C27 -> -600 | ... O21: =-Premissas!$C27 -> -600 | P21: =SUM(C21:O21) -> -7800 | Q21: =IF(P21=0,0,AVERAGE(C21:O21)) -> -600
B22: ='Plano de Contas'!B22 -> Manutenção prédio | C22: =-Premissas!$C28 -> -600 | D22: =-Premissas!$C28 -> -600 | E22: =-Premissas!$C28 -> -600 | F22: =-Premissas!$C28 -> -600 | G22: =-Premissas!$C28 -> -600 | H22: =-Premissas!$C28 -> -600 | I22: =-Premissas!$C28 -> -600 | J22: =-Premissas!$C28 -> -600 | ... O22: =-Premissas!$C28 -> -600 | P22: =SUM(C22:O22) -> -7800 | Q22: =IF(P22=0,0,AVERAGE(C22:O22)) -> -600
B23: ='Plano de Contas'!B23 -> Material escritório | C23: =-Premissas!$C29 -> -246 | D23: =-Premissas!$C29 -> -246 | E23: =-Premissas!$C29 -> -246 | F23: =-Premissas!$C29 -> -246 | G23: =-Premissas!$C29 -> -246 | H23: =-Premissas!$C29 -> -246 | I23: =-Premissas!$C29 -> -246 | J23: =-Premissas!$C29 -> -246 | ... O23: =-Premissas!$C29 -> -246 | P23: =SUM(C23:O23) -> -3198 | Q23: =IF(P23=0,0,AVERAGE(C23:O23)) -> -246
... B32: ='Plano de Contas'!B32 -> Viagens | C32: =-Premissas!$C38 -> -208 | D32: =-Premissas!$C38 -> -208 | E32: =-Premissas!$C38 -> -208 | F32: =-Premissas!$C38 -> -208 | G32: =-Premissas!$C38 -> -208 | H32: =-Premissas!$C38 -> -208 | I32: =-Premissas!$C38 -> -208 | J32: =-Premissas!$C38 -> -208 | ... O32: =-Premissas!$C38 -> -208 | P32: =SUM(C32:O32) -> -2704 | Q32: =IF(P32=0,0,AVERAGE(C32:O32)) -> -208
B33: ='Plano de Contas'!B33 -> DESPESAS VARIÁVEIS | C33: =SUM(C34:C38) -> -1433.85 | D33: =SUM(D34:D38) -> -6115.2541 | E33: =SUM(E34:E38) -> -6131.2918 | F33: =SUM(F34:F38) -> -6230.4044 | G33: =SUM(G34:G38) -> -6349.0876 | H33: =SUM(H34:H38) -> -6359.4709 | I33: =SUM(I34:I38) -> -6276.1143 | J33: =SUM(J34:J38) -> -6531.8099 | ... O33: =SUM(O34:O38) -> -4614.5314 | P33: =SUM(C33:O33) -> -75031.048 | Q33: =IF(P33=0,0,AVERAGE(C33:O33)) -> -5771.6191
B34: ='Plano de Contas'!B34 -> Comissões | C34: =-Premissas!$C$41*Premissas!C15 -> -1433.85 | D34: =-Premissas!$C$41*Premissas!D15 -> -1432.3 | E34: =-Premissas!$C$41*Premissas!E15 -> -1453.4 | F34: =-Premissas!$C$41*Premissas!F15 -> -1483.6 | G34: =-Premissas!$C$41*Premissas!G15 -> -1503.65 | H34: =-Premissas!$C$41*Premissas!H15 -> -1448.55 | I34: =-Premissas!$C$41*Premissas!I15 -> -1545.15 | J34: =-Premissas!$C$41*Premissas!J15 -> -1485.35 | ... O34: =-Premissas!$C$41*Premissas!O15 -> 0 | P34: =SUM(C34:O34) -> -17588.15 | Q34: =IF(P34=0,0,AVERAGE(C34:O34)) -> -1352.9346
B35: ='Plano de Contas'!B35 -> Impostos estaduais | C35: 0 | D35: 0 | E35: 0 | F35: 0 | G35: 0 | H35: 0 | I35: 0 | J35: 0 | K35: 0 | L35: 0 | M35: 0 | N35: 0 | O35: 0 | P35: =SUM(C35:O35) -> 0 | Q35: =IF(P35=0,0,AVERAGE(C35:O35)) -> 0
B36: ='Plano de Contas'!B36 -> Impostos federais | C36: 0 | D36: =-Premissas!$C$43*Premissas!C15 -> -3249.1041 | E36: =-Premissas!$C$43*Premissas!D15 -> -3245.5918 | F36: =-Premissas!$C$43*Premissas!E15 -> -3293.4044 | G36: =-Premissas!$C$43*Premissas!F15 -> -3361.8376 | H36: =-Premissas!$C$43*Premissas!G15 -> -3407.2709 | I36: =-Premissas!$C$43*Premissas!H15 -> -3282.4143 | J36: =-Premissas!$C$43*Premissas!I15 -> -3501.3099 | K36: =-Premissas!$C$43*Premissas!J15 -> -3365.8031 | ... O36: =-Premissas!$C$43*Premissas!N15 -> -3201.6314 | P36: =SUM(C36:O36) -> -39854.748 | Q36: =IF(P36=0,0,AVERAGE(C36:O36)) -> -3065.7498
B37: ='Plano de Contas'!B37 -> Impostos municipais | C37: 0 | D37: =-Premissas!$C$44*Premissas!C15 -> -1433.85 | E37: =-Premissas!$C$44*Premissas!D15 -> -1432.3 | F37: =-Premissas!$C$44*Premissas!E15 -> -1453.4 | G37: =-Premissas!$C$44*Premissas!F15 -> -1483.6 | H37: =-Premissas!$C$44*Premissas!G15 -> -1503.65 | I37: =-Premissas!$C$44*Premissas!H15 -> -1448.55 | J37: =-Premissas!$C$44*Premissas!I15 -> -1545.15 | K37: =-Premissas!$C$44*Premissas!J15 -> -1485.35 | ... O37: =-Premissas!$C$44*Premissas!N15 -> -1412.9 | P37: =SUM(C37:O37) -> -17588.15 | Q37: =IF(P37=0,0,AVERAGE(C37:O37)) -> -1352.9346
B38: ='Plano de Contas'!B38 -> Outras despesas variáveis | C38: =-Premissas!$C$45*Premissas!C15 -> 0 | D38: =-Premissas!$C$45*Premissas!D15 -> 0 | E38: =-Premissas!$C$45*Premissas!E15 -> 0 | F38: =-Premissas!$C$45*Premissas!F15 -> 0 | G38: =-Premissas!$C$45*Premissas!G15 -> 0 | H38: =-Premissas!$C$45*Premissas!H15 -> 0 | I38: =-Premissas!$C$45*Premissas!I15 -> 0 | J38: =-Premissas!$C$45*Premissas!J15 -> 0 | ... O38: =-Premissas!$C$45*Premissas!O15 -> 0 | P38: =SUM(C38:O38) -> 0 | Q38: =IF(P38=0,0,AVERAGE(C38:O38)) -> 0
B39: ='Plano de Contas'!B39 -> ENTRADA FL. INVESTIMENTO | C39: =SUM(C40:C41) -> 0 | D39: =SUM(D40:D41) -> 0 | E39: =SUM(E40:E41) -> 0 | F39: =SUM(F40:F41) -> 0 | G39: =SUM(G40:G41) -> 0 | H39: =SUM(H40:H41) -> 0 | I39: =SUM(I40:I41) -> 0 | J39: =SUM(J40:J41) -> 0 | ... O39: =SUM(O40:O41) -> 0 | P39: =SUM(C39:O39) -> 0 | Q39: =IF(P39=0,0,AVERAGE(C39:O39)) -> 0
B40: ='Plano de Contas'!B40 -> Resgate Aplicações Financeiras | P40: =SUM(C40:O40) -> 0 | Q40: =IF(P40=0,0,AVERAGE(C40:O40)) -> 0
B41: ='Plano de Contas'!B41 -> Venda Ativo | P41: =SUM(C41:O41) -> 0 | Q41: =IF(P41=0,0,AVERAGE(C41:O41)) -> 0
B42: ='Plano de Contas'!B42 -> SAÍDA FL. INVESTIMENTO | C42: =SUM(C43:C45) -> 0 | D42: =SUM(D43:D45) -> 0 | E42: =SUM(E43:E45) -> 0 | F42: =SUM(F43:F45) -> 0 | G42: =SUM(G43:G45) -> 0 | H42: =SUM(H43:H45) -> 0 | I42: =SUM(I43:I45) -> 0 | J42: =SUM(J43:J45) -> 0 | ... O42: =SUM(O43:O45) -> 0 | P42: =SUM(C42:O42) -> 0 | Q42: =IF(P42=0,0,AVERAGE(C42:O42)) -> 0
B43: ='Plano de Contas'!B43 -> Aplicação financeira | P43: =SUM(C43:O43) -> 0 | Q43: =IF(P43=0,0,AVERAGE(C43:O43)) -> 0
B44: ='Plano de Contas'!B44 -> Ativo imobilizado | P44: =SUM(C44:O44) -> 0 | Q44: =IF(P44=0,0,AVERAGE(C44:O44)) -> 0
B45: ='Plano de Contas'!B45 -> Treinamento | P45: =SUM(C45:O45) -> 0 | Q45: =IF(P45=0,0,AVERAGE(C45:O45)) -> 0
B46: ='Plano de Contas'!B46 -> ENTRADA FL. FINANCIAMENTO | C46: =SUM(C47:C48) -> 939.6 | D46: =SUM(D47:D48) -> 0 | E46: =SUM(E47:E48) -> 0 | F46: =SUM(F47:F48) -> 0 | G46: =SUM(G47:G48) -> 0 | H46: =SUM(H47:H48) -> 0 | I46: =SUM(I47:I48) -> 0 | J46: =SUM(J47:J48) -> 0 | ... O46: =SUM(O47:O48) -> 0 | P46: =SUM(C46:O46) -> 939.6 | Q46: =IF(P46=0,0,AVERAGE(C46:O46)) -> 72.276923
B47: ='Plano de Contas'!B47 -> Aporte Sócios | P47: =SUM(C47:O47) -> 0 | Q47: =IF(P47=0,0,AVERAGE(C47:O47)) -> 0
B48: ='Plano de Contas'!B48 -> Recebimento de Empréstimo | C48: =IF(SUM(C54,C64,C65,C49)<0,-1*SUM(C54,C64,C65,C49),0) -> 939.6 | D48: =IF(SUM(D54,D64,D65,D49)<0,-1*SUM(D54,D64,D65,D49),0) -> 0 | E48: =IF(SUM(E54,E64,E65,E49)<0,-1*SUM(E54,E64,E65,E49),0) -> 0 | F48: =IF(SUM(F54,F64,F65,F49)<0,-1*SUM(F54,F64,F65,F49),0) -> 0 | G48: =IF(SUM(G54,G64,G65,G49)<0,-1*SUM(G54,G64,G65,G49),0) -> 0 | H48: =IF(SUM(H54,H64,H65,H49)<0,-1*SUM(H54,H64,H65,H49),0) -> 0 | I48: =IF(SUM(I54,I64,I65,I49)<0,-1*SUM(I54,I64,I65,I49),0) -> 0 | J48: =IF(SUM(J54,J64,J65,J49)<0,-1*SUM(J54,J64,J65,J49),0) -> 0 | ... N48: =IF(SUM(N54,N64,N65,N49)<0,-1*SUM(N54,N64,N65,N49),0) -> 0 | P48: =SUM(C48:O48) -> 939.6 | Q48: =IF(P48=0,0,AVERAGE(C48:O48)) -> 78.3
B49: ='Plano de Contas'!B49 -> SAÍDA FL. FINANCIAMENTO | C49: =SUM(C50:C52) -> 0 | D49: =SUM(D50:D52) -> -5432.0904 | E49: =SUM(E50:E52) -> -4589.3833 | F49: =SUM(F50:F52) -> -4981.6382 | G49: =SUM(G50:G52) -> -4851.865 | H49: =SUM(H50:H52) -> -4912.3116 | I49: =SUM(I50:I52) -> -4878.3543 | J49: =SUM(J50:J52) -> -4990.376 | ... O49: =SUM(O50:O52) -> -142.38744 | P49: =SUM(C49:O49) -> -53839.013 | Q49: =IF(P49=0,0,AVERAGE(C49:O49)) -> -4141.4625
B50: ='Plano de Contas'!B50 -> Distribuição de Lucros | C50: =IF(C66>0,-40%*C66,0) -> 0 | D50: =IF(D66>0,-40%*D66,0) -> -4473.6984 | E50: =IF(E66>0,-40%*E66,0) -> -4589.3833 | F50: =IF(F66>0,-40%*F66,0) -> -4981.6382 | G50: =IF(G66>0,-40%*G66,0) -> -4851.865 | H50: =IF(H66>0,-40%*H66,0) -> -4912.3116 | I50: =IF(I66>0,-40%*I66,0) -> -4878.3543 | J50: =IF(J66>0,-40%*J66,0) -> -4990.376 | ... O50: =IF(O66>0,-40%*O66,0) -> -142.38744 | P50: =SUM(C50:O50) -> -52880.621 | Q50: =IF(P50=0,0,AVERAGE(C50:O50)) -> -4067.7401
B51: ='Plano de Contas'!B51 -> Pgto. empréstimo (principal) | D51: =IF(C48=0,0,-C48) -> -939.6 | E51: =IF(D48=0,0,-D48) -> 0 | F51: =IF(E48=0,0,-E48) -> 0 | G51: =IF(F48=0,0,-F48) -> 0 | H51: =IF(G48=0,0,-G48) -> 0 | I51: =IF(H48=0,0,-H48) -> 0 | J51: =IF(I48=0,0,-I48) -> 0 | K51: =IF(J48=0,0,-J48) -> 0 | ... O51: =IF(N48=0,0,-N48) -> 0 | P51: =SUM(C51:O51) -> -939.6 | Q51: =IF(P51=0,0,AVERAGE(C51:O51)) -> -78.3
B52: ='Plano de Contas'!B52 -> Pgto. empréstimo (juros) | D52: =IF(D51=0,0,2%*D51) -> -18.792 | E52: =IF(E51=0,0,2%*E51) -> 0 | F52: =IF(F51=0,0,2%*F51) -> 0 | G52: =IF(G51=0,0,2%*G51) -> 0 | H52: =IF(H51=0,0,2%*H51) -> 0 | I52: =IF(I51=0,0,2%*I51) -> 0 | J52: =IF(J51=0,0,2%*J51) -> 0 | K52: =IF(K51=0,0,2%*K51) -> 0 | ... O52: =IF(O51=0,0,2%*O51) -> 0 | P52: =SUM(C52:O52) -> -18.792 | Q52: =IF(P52=0,0,AVERAGE(C52:O52)) -> -1.566
B54: Saldos Iniciais | C54: =Premissas!C5 -> 0 | D54: =C62 -> 0 | E54: =D62 -> 5752.1555 | F54: =E62 -> 12636.23 | G54: =F62 -> 20108.688 | H54: =G62 -> 27386.485 | I54: =H62 -> 34754.953 | J54: =I62 -> 42072.484 | K54: =J62 -> 49558.048 | ... O54: =N62 -> 78148.958 | P54: =SUM(C54:O54) -> 463206.71 | Q54: =IF(P54=0,0,AVERAGE(C54:O54)) -> 35631.285
B55: =B5 -> RECEITAS OPERACIONAIS | C55: =C5 -> 11684.25 | D55: =D5 -> 28489.5 | E55: =E5 -> 28794.75 | F55: =F5 -> 29874.5 | G55: =G5 -> 29668.75 | H55: =H5 -> 29830.25 | I55: =I5 -> 29662 | ... O55: =O5 -> 16160.5 | P55: =SUM(C55:O55) -> 351763 | Q55: =IF(P55=0,0,AVERAGE(C55:O55)) -> 27058.692
B56: =B11 -> DESPESAS FIXAS | C56: =C11 -> -11190 | D56: =D11 -> -11190 | E56: =E11 -> -11190 | F56: =F11 -> -11190 | G56: =G11 -> -11190 | H56: =H11 -> -11190 | I56: =I11 -> -11190 | ... O56: =O11 -> -11190 | P56: =SUM(C56:O56) -> -145470 | Q56: =IF(P56=0,0,AVERAGE(C56:O56)) -> -11190
B57: =B33 -> DESPESAS VARIÁVEIS | C57: =C33 -> -1433.85 | D57: =D33 -> -6115.2541 | E57: =E33 -> -6131.2918 | F57: =F33 -> -6230.4044 | G57: =G33 -> -6349.0876 | H57: =H33 -> -6359.4709 | I57: =I33 -> -6276.1143 | ... O57: =O33 -> -4614.5314 | P57: =SUM(C57:O57) -> -75031.048 | Q57: =IF(P57=0,0,AVERAGE(C57:O57)) -> -5771.6191
B58: =B39 -> ENTRADA FL. INVESTIMENTO | C58: =C39 -> 0 | D58: =D39 -> 0 | E58: =E39 -> 0 | F58: =F39 -> 0 | G58: =G39 -> 0 | H58: =H39 -> 0 | I58: =I39 -> 0 | ... O58: =O39 -> 0 | P58: =SUM(C58:O58) -> 0 | Q58: =IF(P58=0,0,AVERAGE(C58:O58)) -> 0
B59: =B42 -> SAÍDA FL. INVESTIMENTO | C59: =C42 -> 0 | D59: =D42 -> 0 | E59: =E42 -> 0 | F59: =F42 -> 0 | G59: =G42 -> 0 | H59: =H42 -> 0 | I59: =I42 -> 0 | ... O59: =O42 -> 0 | P59: =SUM(C59:O59) -> 0 | Q59: =IF(P59=0,0,AVERAGE(C59:O59)) -> 0
B60: =B46 -> ENTRADA FL. FINANCIAMENTO | C60: =C46 -> 939.6 | D60: =D46 -> 0 | E60: =E46 -> 0 | F60: =F46 -> 0 | G60: =G46 -> 0 | H60: =H46 -> 0 | I60: =I46 -> 0 | ... O60: =O46 -> 0 | P60: =SUM(C60:O60) -> 939.6 | Q60: =IF(P60=0,0,AVERAGE(C60:O60)) -> 72.276923
B61: =B49 -> SAÍDA FL. FINANCIAMENTO | C61: =C49 -> 0 | D61: =D49 -> -5432.0904 | E61: =E49 -> -4589.3833 | F61: =F49 -> -4981.6382 | G61: =G49 -> -4851.865 | H61: =H49 -> -4912.3116 | I61: =I49 -> -4878.3543 | ... O61: =O49 -> -142.38744 | P61: =SUM(C61:O61) -> -53839.013 | Q61: =IF(P61=0,0,AVERAGE(C61:O61)) -> -4141.4625
B62: Saldos Finais | C62: =SUM(C54:C61) -> 0 | D62: =SUM(D54:D61) -> 5752.1555 | E62: =SUM(E54:E61) -> 12636.23 | F62: =SUM(F54:F61) -> 20108.688 | G62: =SUM(G54:G61) -> 27386.485 | H62: =SUM(H54:H61) -> 34754.953 | I62: =SUM(I54:I61) -> 42072.484 | J62: =SUM(J54:J61) -> 49558.048 | ... O62: =SUM(O54:O61) -> 78362.539 | P62: =SUM(C62:O62) -> 541569.25 | Q62: =IF(P62=0,0,AVERAGE(C62:O62)) -> 41659.173
B64: Fluxo Operacional | C64: =SUM(C55:C57) -> -939.6 | D64: =SUM(D55:D57) -> 11184.246 | E64: =SUM(E55:E57) -> 11473.458 | F64: =SUM(F55:F57) -> 12454.096 | G64: =SUM(G55:G57) -> 12129.662 | H64: =SUM(H55:H57) -> 12280.779 | I64: =SUM(I55:I57) -> 12195.886 | J64: =SUM(J55:J57) -> 12475.94 | ... Q64: =SUM(Q55:Q57) -> 10097.073
B65: Fluxo de Investimento | C65: =SUM(C58:C59) -> 0 | D65: =SUM(D58:D59) -> 0 | E65: =SUM(E58:E59) -> 0 | F65: =SUM(F58:F59) -> 0 | G65: =SUM(G58:G59) -> 0 | H65: =SUM(H58:H59) -> 0 | I65: =SUM(I58:I59) -> 0 | J65: =SUM(J58:J59) -> 0 | ... Q65: =SUM(Q58:Q59) -> 0
B66: Fluxo de Caixa Livre | C66: =SUM(C64:C65) -> -939.6 | D66: =SUM(D64:D65) -> 11184.246 | E66: =SUM(E64:E65) -> 11473.458 | F66: =SUM(F64:F65) -> 12454.096 | G66: =SUM(G64:G65) -> 12129.662 | H66: =SUM(H64:H65) -> 12280.779 | I66: =SUM(I64:I65) -> 12195.886 | J66: =SUM(J64:J65) -> 12475.94 | ... Q66: =SUM(Q64:Q65) -> 10097.073
B67: Fluxo de Financiamento | C67: =SUM(C60:C61) -> 939.6 | D67: =SUM(D60:D61) -> -5432.0904 | E67: =SUM(E60:E61) -> -4589.3833 | F67: =SUM(F60:F61) -> -4981.6382 | G67: =SUM(G60:G61) -> -4851.865 | H67: =SUM(H60:H61) -> -4912.3116 | I67: =SUM(I60:I61) -> -4878.3543 | J67: =SUM(J60:J61) -> -4990.376 | ... Q67: =SUM(Q60:Q61) -> -4069.1856
B68: Despesa Fixa / Receita Operacional | C68: =-C56/C55 -> 0.95769947 | D68: =-D56/D55 -> 0.39277629 | E68: =-E56/E55 -> 0.38861251 | F68: =-F56/F55 -> 0.37456694 | G68: =-G56/G55 -> 0.37716452 | H68: =-H56/H55 -> 0.37512257 | I68: =-I56/I55 -> 0.37725035 | J68: =-J56/J55 -> 0.37055741 | ... O68: =-O56/O55 -> 0.69242907
B69: Despesa Variável / Receita Operacional | C69: =-C57/C55 -> 0.12271648 | D69: =-D57/D55 -> 0.2146494 | E69: =-E57/E55 -> 0.21293089 | F69: =-F57/F55 -> 0.20855259 | G69: =-G57/G55 -> 0.21399916 | H69: =-H57/H55 -> 0.21318866 | I69: =-I57/I55 -> 0.2115877 | J69: =-J57/J55 -> 0.21630121 | ... O69: =-O57/O55 -> 0.28554385
B70: Margem de Contribuição | C70: =1-C69 -> 0.87728352 | D70: =1-D69 -> 0.7853506 | E70: =1-E69 -> 0.78706911 | F70: =1-F69 -> 0.79144741 | G70: =1-G69 -> 0.78600084 | H70: =1-H69 -> 0.78681134 | I70: =1-I69 -> 0.7884123 | J70: =1-J69 -> 0.78369879 | ... O70: =1-O69 -> 0.71445615
B71: Margem de Lucro | C71: =1-C70 -> 0.12271648 | D71: =1-D70 -> 0.2146494 | E71: =1-E70 -> 0.21293089 | F71: =1-F70 -> 0.20855259 | G71: =1-G70 -> 0.21399916 | H71: =1-H70 -> 0.21318866 | I71: =1-I70 -> 0.2115877 | J71: =1-J70 -> 0.21630121 | ... O71: =1-O70 -> 0.28554385
B72: Ponto de Equilíbrio | C72: =-C56/C70 -> 12755.283 | D72: =-D56/D70 -> 14248.413 | E72: =-E56/E70 -> 14217.303 | F72: =-F56/F70 -> 14138.653 | G72: =-G56/G70 -> 14236.626 | H72: =-H56/H70 -> 14221.961 | I72: =-I56/I70 -> 14193.081 | J72: =-J56/J70 -> 14278.445 | ... O72: =-O56/O70 -> 15662.263

Sheet Fluxo_Diário
A2: ="Fluxo de Caixa Diário - "&Premissas!C4 -> Fluxo de Caixa Diário - 2020
B4: Ref. | C4: Caixa | D4: Entradas | E4: Saídas | F4: Saldo | M4: Entradas | O4: =SUMIF(O$9:O$1048576,">0",O$9:O$1048576) -> 56325 | P4: =SUMIF(P$9:P$1048576,">0",P$9:P$1048576) -> 19889 | Q4: =SUMIF(Q$9:Q$1048576,">0",Q$9:Q$1048576) -> 62947 | R4: =SUMIF(R$9:R$1048576,">0",R$9:R$1048576) -> 31838 | S4: =SUMIF(S$9:S$1048576,">0",S$9:S$1048576) -> 53566 | T4: =SUMIF(T$9:T$1048576,">0",T$9:T$1048576) -> 91372 | U4: =SUMIF(U$9:U$1048576,">0",U$9:U$1048576) -> 77493 | V4: =SUMIF(V$9:V$1048576,">0",V$9:V$1048576) -> 0 | ... Z4: =SUMIF(Z$9:Z$1048576,">0",Z$9:Z$1048576) -> 0
B5: Jan | C5: Previsão | D5: =SUMIFS(E$9:E$1048576,E$9:E$1048576,">0",A$9:A$1048576,B5) -> 7500 | E5: =SUMIFS(E$9:E$1048576,E$9:E$1048576,"<0",A$9:A$1048576,B5) -> -2575 | F5: =SUM(D5:E5) -> 4925 | M5: Saídas | O5: =SUMIF(O$9:O$1048576,"<0",O$9:O$1048576) -> -17533 | P5: =SUMIF(P$9:P$1048576,"<0",P$9:P$1048576) -> -18498 | Q5: =SUMIF(Q$9:Q$1048576,"<0",Q$9:Q$1048576) -> -13538 | R5: =SUMIF(R$9:R$1048576,"<0",R$9:R$1048576) -> -18686 | S5: =SUMIF(S$9:S$1048576,"<0",S$9:S$1048576) -> -14023 | T5: =SUMIF(T$9:T$1048576,"<0",T$9:T$1048576) -> -9541 | U5: =SUMIF(U$9:U$1048576,"<0",U$9:U$1048576) -> -6506 | V5: =SUMIF(V$9:V$1048576,"<0",V$9:V$1048576) -> -1355 | ... Z5: =SUMIF(Z$9:Z$1048576,"<0",Z$9:Z$1048576) -> 0
B6: =TODAY() -> 44037 | C6: Efetivo | D6: =SUMIFS(Fluxo_Diário_DB!G:G,Fluxo_Diário_DB!G:G,">0",Fluxo_Diário_DB!F:F,"<="&B6) -> 378827 | E6: =SUMIFS(Fluxo_Diário_DB!G:G,Fluxo_Diário_DB!G:G,"<0",Fluxo_Diário_DB!F:F,"<="&B6) -> -93143 | F6: =SUM(D6:E6) -> 285684 | M6: Saldo | O6: =SUM(O4:O5) -> 38792 | P6: =SUM(P4:P5) -> 1391 | Q6: =SUM(Q4:Q5) -> 49409 | R6: =SUM(R4:R5) -> 13152 | S6: =SUM(S4:S5) -> 39543 | T6: =SUM(T4:T5) -> 81831 | U6: =SUM(U4:U5) -> 70987 | V6: =SUM(V4:V5) -> -1355 | ... Z6: =SUM(Z4:Z5) -> 0
G7: Saída | H7: Entrada | O7: 1 | P7: 2 | Q7: 3 | R7: 4 | S7: 5 | T7: 6 | U7: 7 | V7: 8 | W7: 9 | X7: 10 | Y7: 11 | Z7: 12
B8: Data de Reg. | C8: Valor | D8: Data Efet. | E8: Valor | F8: Doc. Pgto. | G8: Nº Doc | H8: Doc. Fiscal | I8: Categoria | J8: Histórico | L8: Saldo Prev. | M8: Saldo Real. | O8: Jan | P8: Fev | Q8: Mar | R8: Abr | S8: Mai | T8: Jun | U8: Jul | V8: Ago | W8: Set | X8: Out | Y8: Nov | Z8: Dez
A9: =IF(D9="","",TEXT(D9,"mmm")) -> dez | B9: 43830 | C9: 0 | D9: 43830 | E9: 0 | J9: Saldo Inicial | L9: =C9 -> 0 | M9: =E9 -> 0
A10: =IF(D10="","",TEXT(D10,"mmm")) -> jan | B10: 43833 | C10: 1200 | D10: 43834 | E10: 1200 | F10: Deposito bancário | H10: 905006 | I10: Consultoria | J10: Cliente ABC | L10: =C10+L9 -> 1200 | M10: =E10+M9 -> 1200 | O10: =IF($D10="","",IF(MONTH($D10)=O$7,$E10,0)) -> 1200 | P10: =IF($D10="","",IF(MONTH($D10)=P$7,$E10,0)) -> 0 | Q10: =IF($D10="","",IF(MONTH($D10)=Q$7,$E10,0)) -> 0 | R10: =IF($D10="","",IF(MONTH($D10)=R$7,$E10,0)) -> 0 | S10: =IF($D10="","",IF(MONTH($D10)=S$7,$E10,0)) -> 0 | T10: =IF($D10="","",IF(MONTH($D10)=T$7,$E10,0)) -> 0 | U10: =IF($D10="","",IF(MONTH($D10)=U$7,$E10,0)) -> 0 | V10: =IF($D10="","",IF(MONTH($D10)=V$7,$E10,0)) -> 0 | ... Z10: =IF($D10="","",IF(MONTH($D10)=Z$7,$E10,0)) -> 0
A11: =IF(D11="","",TEXT(D11,"mmm")) -> jan | B11: 43833 | C11: -50 | D11: 43833 | E11: -50 | F11: Cobrança bancária | G11: 5455512 | I11: Manutenção prédio | J11: Serviço de Manutenção Predial | L11: =C11+L10 -> 1150 | M11: =E11+M10 -> 1150 | O11: =IF($D11="","",IF(MONTH($D11)=O$7,$E11,0)) -> -50 | P11: =IF($D11="","",IF(MONTH($D11)=P$7,$E11,0)) -> 0 | Q11: =IF($D11="","",IF(MONTH($D11)=Q$7,$E11,0)) -> 0 | R11: =IF($D11="","",IF(MONTH($D11)=R$7,$E11,0)) -> 0 | S11: =IF($D11="","",IF(MONTH($D11)=S$7,$E11,0)) -> 0 | T11: =IF($D11="","",IF(MONTH($D11)=T$7,$E11,0)) -> 0 | U11: =IF($D11="","",IF(MONTH($D11)=U$7,$E11,0)) -> 0 | V11: =IF($D11="","",IF(MONTH($D11)=V$7,$E11,0)) -> 0 | ... Z11: =IF($D11="","",IF(MONTH($D11)=Z$7,$E11,0)) -> 0
A12: =IF(D12="","",TEXT(D12,"mmm")) -> jan | B12: 43834 | C12: -20 | D12: 43834 | E12: -20 | F12: Dinheiro | G12: 5645645 | I12: Cartório | J12: Reconhecimento de Firma | L12: =C12+L11 -> 1130 | M12: =E12+M11 -> 1130 | O12: =IF($D12="","",IF(MONTH($D12)=O$7,$E12,0)) -> -20 | P12: =IF($D12="","",IF(MONTH($D12)=P$7,$E12,0)) -> 0 | Q12: =IF($D12="","",IF(MONTH($D12)=Q$7,$E12,0)) -> 0 | R12: =IF($D12="","",IF(MONTH($D12)=R$7,$E12,0)) -> 0 | S12: =IF($D12="","",IF(MONTH($D12)=S$7,$E12,0)) -> 0 | T12: =IF($D12="","",IF(MONTH($D12)=T$7,$E12,0)) -> 0 | U12: =IF($D12="","",IF(MONTH($D12)=U$7,$E12,0)) -> 0 | V12: =IF($D12="","",IF(MONTH($D12)=V$7,$E12,0)) -> 0 | ... Z12: =IF($D12="","",IF(MONTH($D12)=Z$7,$E12,0)) -> 0
A13: =IF(D13="","",TEXT(D13,"mmm")) -> jan | B13: 43835 | C13: 500 | D13: 43840 | E13: 500 | F13: Deposito bancário | H13: 403518 | I13: Licença de software | J13: Cliente XYZ | L13: =C13+L12 -> 1630 | M13: =E13+M12 -> 1630 | O13: =IF($D13="","",IF(MONTH($D13)=O$7,$E13,0)) -> 500 | P13: =IF($D13="","",IF(MONTH($D13)=P$7,$E13,0)) -> 0 | Q13: =IF($D13="","",IF(MONTH($D13)=Q$7,$E13,0)) -> 0 | R13: =IF($D13="","",IF(MONTH($D13)=R$7,$E13,0)) -> 0 | S13: =IF($D13="","",IF(MONTH($D13)=S$7,$E13,0)) -> 0 | T13: =IF($D13="","",IF(MONTH($D13)=T$7,$E13,0)) -> 0 | U13: =IF($D13="","",IF(MONTH($D13)=U$7,$E13,0)) -> 0 | V13: =IF($D13="","",IF(MONTH($D13)=V$7,$E13,0)) -> 0 | ... Z13: =IF($D13="","",IF(MONTH($D13)=Z$7,$E13,0)) -> 0
A14: =IF(D14="","",TEXT(D14,"mmm")) -> jan | B14: 43835 | C14: 800 | D14: 43840 | E14: 800 | F14: Deposito bancário | H14: 868641 | I14: Manutenção de Sistemas | J14: Cliente XYZ | L14: =C14+L13 -> 2430 | M14: =E14+M13 -> 2430 | O14: =IF($D14="","",IF(MONTH($D14)=O$7,$E14,0)) -> 800 | P14: =IF($D14="","",IF(MONTH($D14)=P$7,$E14,0)) -> 0 | Q14: =IF($D14="","",IF(MONTH($D14)=Q$7,$E14,0)) -> 0 | R14: =IF($D14="","",IF(MONTH($D14)=R$7,$E14,0)) -> 0 | S14: =IF($D14="","",IF(MONTH($D14)=S$7,$E14,0)) -> 0 | T14: =IF($D14="","",IF(MONTH($D14)=T$7,$E14,0)) -> 0 | U14: =IF($D14="","",IF(MONTH($D14)=U$7,$E14,0)) -> 0 | V14: =IF($D14="","",IF(MONTH($D14)=V$7,$E14,0)) -> 0 | ... Z14: =IF($D14="","",IF(MONTH($D14)=Z$7,$E14,0)) -> 0
A15: =IF(D15="","",TEXT(D15,"mmm")) -> jan | B15: 43835 | C15: 5000 | D15: 43840 | E15: 5000 | F15: Deposito bancário | H15: 615347 | I15: Consultoria | J15: Cliente XYZ | L15: =C15+L14 -> 7430 | M15: =E15+M14 -> 7430 | O15: =IF($D15="","",IF(MONTH($D15)=O$7,$E15,0)) -> 5000 | P15: =IF($D15="","",IF(MONTH($D15)=P$7,$E15,0)) -> 0 | Q15: =IF($D15="","",IF(MONTH($D15)=Q$7,$E15,0)) -> 0 | R15: =IF($D15="","",IF(MONTH($D15)=R$7,$E15,0)) -> 0 | S15: =IF($D15="","",IF(MONTH($D15)=S$7,$E15,0)) -> 0 | T15: =IF($D15="","",IF(MONTH($D15)=T$7,$E15,0)) -> 0 | U15: =IF($D15="","",IF(MONTH($D15)=U$7,$E15,0)) -> 0 | V15: =IF($D15="","",IF(MONTH($D15)=V$7,$E15,0)) -> 0 | ... Z15: =IF($D15="","",IF(MONTH($D15)=Z$7,$E15,0)) -> 0
A16: =IF(D16="","",TEXT(D16,"mmm")) -> jan | B16: 43837 | C16: -30 | D16: 43837 | E16: -30 | F16: Deposito bancário | G16: 5455512 | I16: Material escritório | J16: Resma | L16: =C16+L15 -> 7400 | M16: =E16+M15 -> 7400 | O16: =IF($D16="","",IF(MONTH($D16)=O$7,$E16,0)) -> -30 | P16: =IF($D16="","",IF(MONTH($D16)=P$7,$E16,0)) -> 0 | Q16: =IF($D16="","",IF(MONTH($D16)=Q$7,$E16,0)) -> 0 | R16: =IF($D16="","",IF(MONTH($D16)=R$7,$E16,0)) -> 0 | S16: =IF($D16="","",IF(MONTH($D16)=S$7,$E16,0)) -> 0 | T16: =IF($D16="","",IF(MONTH($D16)=T$7,$E16,0)) -> 0 | U16: =IF($D16="","",IF(MONTH($D16)=U$7,$E16,0)) -> 0 | V16: =IF($D16="","",IF(MONTH($D16)=V$7,$E16,0)) -> 0 | ... Z16: =IF($D16="","",IF(MONTH($D16)=Z$7,$E16,0)) -> 0
A17: =IF(D17="","",TEXT(D17,"mmm")) -> jan | B17: 43837 | C17: -100 | D17: 43837 | E17: -100 | F17: Deposito bancário | G17: 5645645 | I17: Água | J17: Água do estacionamento | L17: =C17+L16 -> 7300 | M17: =E17+M16 -> 7300 | O17: =IF($D17="","",IF(MONTH($D17)=O$7,$E17,0)) -> -100 | P17: =IF($D17="","",IF(MONTH($D17)=P$7,$E17,0)) -> 0 | Q17: =IF($D17="","",IF(MONTH($D17)=Q$7,$E17,0)) -> 0 | R17: =IF($D17="","",IF(MONTH($D17)=R$7,$E17,0)) -> 0 | S17: =IF($D17="","",IF(MONTH($D17)=S$7,$E17,0)) -> 0 | T17: =IF($D17="","",IF(MONTH($D17)=T$7,$E17,0)) -> 0 | U17: =IF($D17="","",IF(MONTH($D17)=U$7,$E17,0)) -> 0 | V17: =IF($D17="","",IF(MONTH($D17)=V$7,$E17,0)) -> 0 | ... Z17: =IF($D17="","",IF(MONTH($D17)=Z$7,$E17,0)) -> 0
A18: =IF(D18="","",TEXT(D18,"mmm")) -> jan | B18: 43837 | C18: -45 | D18: 43837 | E18: -45 | F18: Deposito bancário | G18: 5835778 | I18: Correios | J18: Envio de Sedex | L18: =C18+L17 -> 7255 | M18: =E18+M17 -> 7255 | O18: =IF($D18="","",IF(MONTH($D18)=O$7,$E18,0)) -> -45 | P18: =IF($D18="","",IF(MONTH($D18)=P$7,$E18,0)) -> 0 | Q18: =IF($D18="","",IF(MONTH($D18)=Q$7,$E18,0)) -> 0 | R18: =IF($D18="","",IF(MONTH($D18)=R$7,$E18,0)) -> 0 | S18: =IF($D18="","",IF(MONTH($D18)=S$7,$E18,0)) -> 0 | T18: =IF($D18="","",IF(MONTH($D18)=T$7,$E18,0)) -> 0 | U18: =IF($D18="","",IF(MONTH($D18)=U$7,$E18,0)) -> 0 | V18: =IF($D18="","",IF(MONTH($D18)=V$7,$E18,0)) -> 0 | ... Z18: =IF($D18="","",IF(MONTH($D18)=Z$7,$E18,0)) -> 0
A19: =IF(D19="","",TEXT(D19,"mmm")) -> jan | B19: 43837 | C19: -500 | D19: 43837 | E19: -500 | F19: Deposito bancário | G19: 6025911 | I19: Material limpeza | J19: Complementar | L19: =C19+L18 -> 6755 | M19: =E19+M18 -> 6755 | O19: =IF($D19="","",IF(MONTH($D19)=O$7,$E19,0)) -> -500 | P19: =IF($D19="","",IF(MONTH($D19)=P$7,$E19,0)) -> 0 | Q19: =IF($D19="","",IF(MONTH($D19)=Q$7,$E19,0)) -> 0 | R19: =IF($D19="","",IF(MONTH($D19)=R$7,$E19,0)) -> 0 | S19: =IF($D19="","",IF(MONTH($D19)=S$7,$E19,0)) -> 0 | T19: =IF($D19="","",IF(MONTH($D19)=T$7,$E19,0)) -> 0 | U19: =IF($D19="","",IF(MONTH($D19)=U$7,$E19,0)) -> 0 | V19: =IF($D19="","",IF(MONTH($D19)=V$7,$E19,0)) -> 0 | ... Z19: =IF($D19="","",IF(MONTH($D19)=Z$7,$E19,0)) -> 0
A20: =IF(D20="","",TEXT(D20,"mmm")) -> jan | B20: 43837 | C20: -1000 | D20: 43837 | E20: -1000 | F20: Deposito bancário | G20: 6216044 | I20: Manutenção equipamentos | J20: Manutenção na impressora | L20: =C20+L19 -> 5755 | M20: =E20+M19 -> 5755 | O20: =IF($D20="","",IF(MONTH($D20)=O$7,$E20,0)) -> -1000 | P20: =IF($D20="","",IF(MONTH($D20)=P$7,$E20,0)) -> 0 | Q20: =IF($D20="","",IF(MONTH($D20)=Q$7,$E20,0)) -> 0 | R20: =IF($D20="","",IF(MONTH($D20)=R$7,$E20,0)) -> 0 | S20: =IF($D20="","",IF(MONTH($D20)=S$7,$E20,0)) -> 0 | T20: =IF($D20="","",IF(MONTH($D20)=T$7,$E20,0)) -> 0 | U20: =IF($D20="","",IF(MONTH($D20)=U$7,$E20,0)) -> 0 | V20: =IF($D20="","",IF(MONTH($D20)=V$7,$E20,0)) -> 0 | ... Z20: =IF($D20="","",IF(MONTH($D20)=Z$7,$E20,0)) -> 0
A21: =IF(D21="","",TEXT(D21,"mmm")) -> jan | B21: 43837 | C21: -800 | D21: 43837 | E21: -800 | F21: Deposito bancário | G21: 6406177 | I21: Terceirizados | J21: Encanador | L21: =C21+L20 -> 4955 | M21: =E21+M20 -> 4955 | O21: =IF($D21="","",IF(MONTH($D21)=O$7,$E21,0)) -> -800 | P21: =IF($D21="","",IF(MONTH($D21)=P$7,$E21,0)) -> 0 | Q21: =IF($D21="","",IF(MONTH($D21)=Q$7,$E21,0)) -> 0 | R21: =IF($D21="","",IF(MONTH($D21)=R$7,$E21,0)) -> 0 | S21: =IF($D21="","",IF(MONTH($D21)=S$7,$E21,0)) -> 0 | T21: =IF($D21="","",IF(MONTH($D21)=T$7,$E21,0)) -> 0 | U21: =IF($D21="","",IF(MONTH($D21)=U$7,$E21,0)) -> 0 | V21: =IF($D21="","",IF(MONTH($D21)=V$7,$E21,0)) -> 0 | ... Z21: =IF($D21="","",IF(MONTH($D21)=Z$7,$E21,0)) -> 0
A22: =IF(D22="","",TEXT(D22,"mmm")) -> jan | B22: 43837 | C22: -10 | D22: 43837 | E22: -10 | F22: Dinheiro | G22: 6596310 | I22: Correios | J22: Envio de Sedex | L22: =C22+L21 -> 4945 | M22: =E22+M21 -> 4945 | O22: =IF($D22="","",IF(MONTH($D22)=O$7,$E22,0)) -> -10 | P22: =IF($D22="","",IF(MONTH($D22)=P$7,$E22,0)) -> 0 | Q22: =IF($D22="","",IF(MONTH($D22)=Q$7,$E22,0)) -> 0 | R22: =IF($D22="","",IF(MONTH($D22)=R$7,$E22,0)) -> 0 | S22: =IF($D22="","",IF(MONTH($D22)=S$7,$E22,0)) -> 0 | T22: =IF($D22="","",IF(MONTH($D22)=T$7,$E22,0)) -> 0 | U22: =IF($D22="","",IF(MONTH($D22)=U$7,$E22,0)) -> 0 | V22: =IF($D22="","",IF(MONTH($D22)=V$7,$E22,0)) -> 0 | ... Z22: =IF($D22="","",IF(MONTH($D22)=Z$7,$E22,0)) -> 0
A23: =IF(D23="","",TEXT(D23,"mmm")) -> jan | B23: 43837 | C23: -10 | D23: 43837 | E23: -10 | F23: Dinheiro | G23: 6786443 | I23: Correios | J23: Envio de Sedex | L23: =C23+L22 -> 4935 | M23: =E23+M22 -> 4935 | O23: =IF($D23="","",IF(MONTH($D23)=O$7,$E23,0)) -> -10 | P23: =IF($D23="","",IF(MONTH($D23)=P$7,$E23,0)) -> 0 | Q23: =IF($D23="","",IF(MONTH($D23)=Q$7,$E23,0)) -> 0 | R23: =IF($D23="","",IF(MONTH($D23)=R$7,$E23,0)) -> 0 | S23: =IF($D23="","",IF(MONTH($D23)=S$7,$E23,0)) -> 0 | T23: =IF($D23="","",IF(MONTH($D23)=T$7,$E23,0)) -> 0 | U23: =IF($D23="","",IF(MONTH($D23)=U$7,$E23,0)) -> 0 | V23: =IF($D23="","",IF(MONTH($D23)=V$7,$E23,0)) -> 0 | ... Z23: =IF($D23="","",IF(MONTH($D23)=Z$7,$E23,0)) -> 0
A24: =IF(D24="","",TEXT(D24,"mmm")) -> jan | B24: 43837 | C24: -10 | D24: 43837 | E24: -10 | F24: Dinheiro | G24: 6976576 | I24: Correios | J24: Envio de Sedex | L24: =C24+L23 -> 4925 | M24: =E24+M23 -> 4925 | O24: =IF($D24="","",IF(MONTH($D24)=O$7,$E24,0)) -> -10 | P24: =IF($D24="","",IF(MONTH($D24)=P$7,$E24,0)) -> 0 | Q24: =IF($D24="","",IF(MONTH($D24)=Q$7,$E24,0)) -> 0 | R24: =IF($D24="","",IF(MONTH($D24)=R$7,$E24,0)) -> 0 | S24: =IF($D24="","",IF(MONTH($D24)=S$7,$E24,0)) -> 0 | T24: =IF($D24="","",IF(MONTH($D24)=T$7,$E24,0)) -> 0 | U24: =IF($D24="","",IF(MONTH($D24)=U$7,$E24,0)) -> 0 | V24: =IF($D24="","",IF(MONTH($D24)=V$7,$E24,0)) -> 0 | ... Z24: =IF($D24="","",IF(MONTH($D24)=Z$7,$E24,0)) -> 0
A25: =IF(D25="","",TEXT(D25,"mmm")) -> fev | B25: 43838 | C25: -4000 | D25: 43871 | E25: -4000 | F25: Deposito bancário | G25: 6976576 | I25: Segurança | J25: Segurança Predial | L25: =C25+L24 -> 925 | M25: =E25+M24 -> 925 | O25: =IF($D25="","",IF(MONTH($D25)=O$7,$E25,0)) -> 0 | P25: =IF($D25="","",IF(MONTH($D25)=P$7,$E25,0)) -> -4000 | Q25: =IF($D25="","",IF(MONTH($D25)=Q$7,$E25,0)) -> 0 | R25: =IF($D25="","",IF(MONTH($D25)=R$7,$E25,0)) -> 0 | S25: =IF($D25="","",IF(MONTH($D25)=S$7,$E25,0)) -> 0 | T25: =IF($D25="","",IF(MONTH($D25)=T$7,$E25,0)) -> 0 | U25: =IF($D25="","",IF(MONTH($D25)=U$7,$E25,0)) -> 0 | V25: =IF($D25="","",IF(MONTH($D25)=V$7,$E25,0)) -> 0 | ... Z25: =IF($D25="","",IF(MONTH($D25)=Z$7,$E25,0)) -> 0
A26: =IF(D26="","",TEXT(D26,"mmm")) -> fev | B26: 43838 | C26: 3500 | D26: 43876 | E26: 3500 | F26: Cobrança bancária | H26: 753492 | I26: Consultoria | J26: Cliente ABC | L26: =C26+L25 -> 4425 | M26: =E26+M25 -> 4425 | O26: =IF($D26="","",IF(MONTH($D26)=O$7,$E26,0)) -> 0 | P26: =IF($D26="","",IF(MONTH($D26)=P$7,$E26,0)) -> 3500 | Q26: =IF($D26="","",IF(MONTH($D26)=Q$7,$E26,0)) -> 0 | R26: =IF($D26="","",IF(MONTH($D26)=R$7,$E26,0)) -> 0 | S26: =IF($D26="","",IF(MONTH($D26)=S$7,$E26,0)) -> 0 | T26: =IF($D26="","",IF(MONTH($D26)=T$7,$E26,0)) -> 0 | U26: =IF($D26="","",IF(MONTH($D26)=U$7,$E26,0)) -> 0 | V26: =IF($D26="","",IF(MONTH($D26)=V$7,$E26,0)) -> 0 | ... Z26: =IF($D26="","",IF(MONTH($D26)=Z$7,$E26,0)) -> 0
B27: =B26+2 -> 43840 | C27: -2209 | D27: 43841 | E27: -2209 | F27: Cobrança bancária | G27: 5455512 | I27: Correios | L27: =C27+L26 -> 2216 | M27: =E27+M26 -> 2216 | O27: =IF($D27="","",IF(MONTH($D27)=O$7,$E27,0)) -> -2209 | P27: =IF($D27="","",IF(MONTH($D27)=P$7,$E27,0)) -> 0 | Q27: =IF($D27="","",IF(MONTH($D27)=Q$7,$E27,0)) -> 0 | R27: =IF($D27="","",IF(MONTH($D27)=R$7,$E27,0)) -> 0 | S27: =IF($D27="","",IF(MONTH($D27)=S$7,$E27,0)) -> 0 | T27: =IF($D27="","",IF(MONTH($D27)=T$7,$E27,0)) -> 0 | U27: =IF($D27="","",IF(MONTH($D27)=U$7,$E27,0)) -> 0 | V27: =IF($D27="","",IF(MONTH($D27)=V$7,$E27,0)) -> 0 | ... Z27: =IF($D27="","",IF(MONTH($D27)=Z$7,$E27,0)) -> 0
B28: =B27+2 -> 43842 | C28: -2713 | D28: 43845 | E28: -2713 | F28: Dinheiro | G28: 5645645 | I28: Impostos municipais | L28: =C28+L27 -> -497 | M28: =E28+M27 -> -497 | O28: =IF($D28="","",IF(MONTH($D28)=O$7,$E28,0)) -> -2713 | P28: =IF($D28="","",IF(MONTH($D28)=P$7,$E28,0)) -> 0 | Q28: =IF($D28="","",IF(MONTH($D28)=Q$7,$E28,0)) -> 0 | R28: =IF($D28="","",IF(MONTH($D28)=R$7,$E28,0)) -> 0 | S28: =IF($D28="","",IF(MONTH($D28)=S$7,$E28,0)) -> 0 | T28: =IF($D28="","",IF(MONTH($D28)=T$7,$E28,0)) -> 0 | U28: =IF($D28="","",IF(MONTH($D28)=U$7,$E28,0)) -> 0 | V28: =IF($D28="","",IF(MONTH($D28)=V$7,$E28,0)) -> 0 | ... Z28: =IF($D28="","",IF(MONTH($D28)=Z$7,$E28,0)) -> 0
B29: =B28+2 -> 43844 | C29: -2946 | D29: 43845 | E29: -2946 | F29: Deposito bancário | G29: 5455512 | I29: Energia | L29: =C29+L28 -> -3443 | M29: =E29+M28 -> -3443 | O29: =IF($D29="","",IF(MONTH($D29)=O$7,$E29,0)) -> -2946 | P29: =IF($D29="","",IF(MONTH($D29)=P$7,$E29,0)) -> 0 | Q29: =IF($D29="","",IF(MONTH($D29)=Q$7,$E29,0)) -> 0 | R29: =IF($D29="","",IF(MONTH($D29)=R$7,$E29,0)) -> 0 | S29: =IF($D29="","",IF(MONTH($D29)=S$7,$E29,0)) -> 0 | T29: =IF($D29="","",IF(MONTH($D29)=T$7,$E29,0)) -> 0 | U29: =IF($D29="","",IF(MONTH($D29)=U$7,$E29,0)) -> 0 | V29: =IF($D29="","",IF(MONTH($D29)=V$7,$E29,0)) -> 0 | ... Z29: =IF($D29="","",IF(MONTH($D29)=Z$7,$E29,0)) -> 0
B30: =B29+2 -> 43846 | C30: -3164 | D30: 43849 | E30: -3164 | F30: Deposito bancário | G30: 5645645 | I30: Fones / Comunicação | L30: =C30+L29 -> -6607 | M30: =E30+M29 -> -6607 | O30: =IF($D30="","",IF(MONTH($D30)=O$7,$E30,0)) -> -3164 | P30: =IF($D30="","",IF(MONTH($D30)=P$7,$E30,0)) -> 0 | Q30: =IF($D30="","",IF(MONTH($D30)=Q$7,$E30,0)) -> 0 | R30: =IF($D30="","",IF(MONTH($D30)=R$7,$E30,0)) -> 0 | S30: =IF($D30="","",IF(MONTH($D30)=S$7,$E30,0)) -> 0 | T30: =IF($D30="","",IF(MONTH($D30)=T$7,$E30,0)) -> 0 | U30: =IF($D30="","",IF(MONTH($D30)=U$7,$E30,0)) -> 0 | V30: =IF($D30="","",IF(MONTH($D30)=V$7,$E30,0)) -> 0 | ... Z30: =IF($D30="","",IF(MONTH($D30)=Z$7,$E30,0)) -> 0
B31: =B30+2 -> 43848 | C31: -2037 | D31: 43849 | E31: -2037 | F31: Deposito bancário | G31: 5835778 | I31: Impostos/taxas diversas | L31: =C31+L30 -> -8644 | M31: =E31+M30 -> -8644 | O31: =IF($D31="","",IF(MONTH($D31)=O$7,$E31,0)) -> -2037 | P31: =IF($D31="","",IF(MONTH($D31)=P$7,$E31,0)) -> 0 | Q31: =IF($D31="","",IF(MONTH($D31)=Q$7,$E31,0)) -> 0 | R31: =IF($D31="","",IF(MONTH($D31)=R$7,$E31,0)) -> 0 | S31: =IF($D31="","",IF(MONTH($D31)=S$7,$E31,0)) -> 0 | T31: =IF($D31="","",IF(MONTH($D31)=T$7,$E31,0)) -> 0 | U31: =IF($D31="","",IF(MONTH($D31)=U$7,$E31,0)) -> 0 | V31: =IF($D31="","",IF(MONTH($D31)=V$7,$E31,0)) -> 0 | ... Z31: =IF($D31="","",IF(MONTH($D31)=Z$7,$E31,0)) -> 0
B32: =B31+2 -> 43850 | C32: 14762 | D32: 43853 | E32: 14762 | F32: Deposito bancário | H32: 446501 | I32: Consultoria | J32: Cliente ABC | L32: =C32+L31 -> 6118 | M32: =E32+M31 -> 6118 | O32: =IF($D32="","",IF(MONTH($D32)=O$7,$E32,0)) -> 14762 | P32: =IF($D32="","",IF(MONTH($D32)=P$7,$E32,0)) -> 0 | Q32: =IF($D32="","",IF(MONTH($D32)=Q$7,$E32,0)) -> 0 | R32: =IF($D32="","",IF(MONTH($D32)=R$7,$E32,0)) -> 0 | S32: =IF($D32="","",IF(MONTH($D32)=S$7,$E32,0)) -> 0 | T32: =IF($D32="","",IF(MONTH($D32)=T$7,$E32,0)) -> 0 | U32: =IF($D32="","",IF(MONTH($D32)=U$7,$E32,0)) -> 0 | V32: =IF($D32="","",IF(MONTH($D32)=V$7,$E32,0)) -> 0 | ... Z32: =IF($D32="","",IF(MONTH($D32)=Z$7,$E32,0)) -> 0
B33: =B32+2 -> 43852 | C33: 11949 | D33: 43853 | E33: 11949 | F33: Deposito bancário | H33: 436442 | I33: Licença de software | J33: Cliente XYZ | L33: =C33+L32 -> 18067 | M33: =E33+M32 -> 18067 | O33: =IF($D33="","",IF(MONTH($D33)=O$7,$E33,0)) -> 11949 | P33: =IF($D33="","",IF(MONTH($D33)=P$7,$E33,0)) -> 0 | Q33: =IF($D33="","",IF(MONTH($D33)=Q$7,$E33,0)) -> 0 | R33: =IF($D33="","",IF(MONTH($D33)=R$7,$E33,0)) -> 0 | S33: =IF($D33="","",IF(MONTH($D33)=S$7,$E33,0)) -> 0 | T33: =IF($D33="","",IF(MONTH($D33)=T$7,$E33,0)) -> 0 | U33: =IF($D33="","",IF(MONTH($D33)=U$7,$E33,0)) -> 0 | V33: =IF($D33="","",IF(MONTH($D33)=V$7,$E33,0)) -> 0 | ... Z33: =IF($D33="","",IF(MONTH($D33)=Z$7,$E33,0)) -> 0
B34: =B33+2 -> 43854 | C34: 14655 | D34: 43857 | E34: 14655 | F34: Dinheiro | H34: 526689 | I34: Manutenção de Sistemas | J34: Cliente XYZ | L34: =C34+L33 -> 32722 | M34: =E34+M33 -> 32722 | O34: =IF($D34="","",IF(MONTH($D34)=O$7,$E34,0)) -> 14655 | P34: =IF($D34="","",IF(MONTH($D34)=P$7,$E34,0)) -> 0 | Q34: =IF($D34="","",IF(MONTH($D34)=Q$7,$E34,0)) -> 0 | R34: =IF($D34="","",IF(MONTH($D34)=R$7,$E34,0)) -> 0 | S34: =IF($D34="","",IF(MONTH($D34)=S$7,$E34,0)) -> 0 | T34: =IF($D34="","",IF(MONTH($D34)=T$7,$E34,0)) -> 0 | U34: =IF($D34="","",IF(MONTH($D34)=U$7,$E34,0)) -> 0 | V34: =IF($D34="","",IF(MONTH($D34)=V$7,$E34,0)) -> 0 | ... Z34: =IF($D34="","",IF(MONTH($D34)=Z$7,$E34,0)) -> 0
B35: =B34+2 -> 43856 | C35: 7459 | D35: 43858 | E35: 7459 | F35: Dinheiro | H35: 718362 | I35: Consultoria | J35: Cliente ABC | L35: =C35+L34 -> 40181 | M35: =E35+M34 -> 40181 | O35: =IF($D35="","",IF(MONTH($D35)=O$7,$E35,0)) -> 7459 | P35: =IF($D35="","",IF(MONTH($D35)=P$7,$E35,0)) -> 0 | Q35: =IF($D35="","",IF(MONTH($D35)=Q$7,$E35,0)) -> 0 | R35: =IF($D35="","",IF(MONTH($D35)=R$7,$E35,0)) -> 0 | S35: =IF($D35="","",IF(MONTH($D35)=S$7,$E35,0)) -> 0 | T35: =IF($D35="","",IF(MONTH($D35)=T$7,$E35,0)) -> 0 | U35: =IF($D35="","",IF(MONTH($D35)=U$7,$E35,0)) -> 0 | V35: =IF($D35="","",IF(MONTH($D35)=V$7,$E35,0)) -> 0 | ... Z35: =IF($D35="","",IF(MONTH($D35)=Z$7,$E35,0)) -> 0
B36: =B35+2 -> 43858 | C36: -1889 | D36: 43861 | E36: -1889 | F36: Cartão de crédito | G36: 5835778 | I36: Energia | L36: =C36+L35 -> 38292 | M36: =E36+M35 -> 38292 | O36: =IF($D36="","",IF(MONTH($D36)=O$7,$E36,0)) -> -1889 | P36: =IF($D36="","",IF(MONTH($D36)=P$7,$E36,0)) -> 0 | Q36: =IF($D36="","",IF(MONTH($D36)=Q$7,$E36,0)) -> 0 | R36: =IF($D36="","",IF(MONTH($D36)=R$7,$E36,0)) -> 0 | S36: =IF($D36="","",IF(MONTH($D36)=S$7,$E36,0)) -> 0 | T36: =IF($D36="","",IF(MONTH($D36)=T$7,$E36,0)) -> 0 | U36: =IF($D36="","",IF(MONTH($D36)=U$7,$E36,0)) -> 0 | V36: =IF($D36="","",IF(MONTH($D36)=V$7,$E36,0)) -> 0 | ... Z36: =IF($D36="","",IF(MONTH($D36)=Z$7,$E36,0)) -> 0
B37: =B36+2 -> 43860 | C37: -3004 | D37: 43862 | E37: -3004 | F37: Cobrança bancária | G37: 5911831.2 | I37: Impostos federais | L37: =C37+L36 -> 35288 | M37: =E37+M36 -> 35288 | O37: =IF($D37="","",IF(MONTH($D37)=O$7,$E37,0)) -> 0 | P37: =IF($D37="","",IF(MONTH($D37)=P$7,$E37,0)) -> -3004 | Q37: =IF($D37="","",IF(MONTH($D37)=Q$7,$E37,0)) -> 0 | R37: =IF($D37="","",IF(MONTH($D37)=R$7,$E37,0)) -> 0 | S37: =IF($D37="","",IF(MONTH($D37)=S$7,$E37,0)) -> 0 | T37: =IF($D37="","",IF(MONTH($D37)=T$7,$E37,0)) -> 0 | U37: =IF($D37="","",IF(MONTH($D37)=U$7,$E37,0)) -> 0 | V37: =IF($D37="","",IF(MONTH($D37)=V$7,$E37,0)) -> 0 | ... Z37: =IF($D37="","",IF(MONTH($D37)=Z$7,$E37,0)) -> 0
B38: =B37+2 -> 43862 | C38: -1619 | D38: 43863 | E38: -1619 | F38: Cheque | G38: 5987884.4 | I38: Terceirizados | L38: =C38+L37 -> 33669 | M38: =E38+M37 -> 33669 | O38: =IF($D38="","",IF(MONTH($D38)=O$7,$E38,0)) -> 0 | P38: =IF($D38="","",IF(MONTH($D38)=P$7,$E38,0)) -> -1619 | Q38: =IF($D38="","",IF(MONTH($D38)=Q$7,$E38,0)) -> 0 | R38: =IF($D38="","",IF(MONTH($D38)=R$7,$E38,0)) -> 0 | S38: =IF($D38="","",IF(MONTH($D38)=S$7,$E38,0)) -> 0 | T38: =IF($D38="","",IF(MONTH($D38)=T$7,$E38,0)) -> 0 | U38: =IF($D38="","",IF(MONTH($D38)=U$7,$E38,0)) -> 0 | V38: =IF($D38="","",IF(MONTH($D38)=V$7,$E38,0)) -> 0 | ... Z38: =IF($D38="","",IF(MONTH($D38)=Z$7,$E38,0)) -> 0
B39: =B38+2 -> 43864 | C39: -2306 | D39: 43866 | E39: -2306 | F39: Deposito bancário | G39: 6063937.6 | I39: Comissões | L39: =C39+L38 -> 31363 | M39: =E39+M38 -> 31363 | O39: =IF($D39="","",IF(MONTH($D39)=O$7,$E39,0)) -> 0 | P39: =IF($D39="","",IF(MONTH($D39)=P$7,$E39,0)) -> -2306 | Q39: =IF($D39="","",IF(MONTH($D39)=Q$7,$E39,0)) -> 0 | R39: =IF($D39="","",IF(MONTH($D39)=R$7,$E39,0)) -> 0 | S39: =IF($D39="","",IF(MONTH($D39)=S$7,$E39,0)) -> 0 | T39: =IF($D39="","",IF(MONTH($D39)=T$7,$E39,0)) -> 0 | U39: =IF($D39="","",IF(MONTH($D39)=U$7,$E39,0)) -> 0 | V39: =IF($D39="","",IF(MONTH($D39)=V$7,$E39,0)) -> 0 | ... Z39: =IF($D39="","",IF(MONTH($D39)=Z$7,$E39,0)) -> 0
B40: =B39+2 -> 43866 | C40: -474 | D40: 43868 | E40: -474 | F40: Dinheiro | G40: 6139990.8 | I40: Correios | L40: =C40+L39 -> 30889 | M40: =E40+M39 -> 30889 | O40: =IF($D40="","",IF(MONTH($D40)=O$7,$E40,0)) -> 0 | P40: =IF($D40="","",IF(MONTH($D40)=P$7,$E40,0)) -> -474 | Q40: =IF($D40="","",IF(MONTH($D40)=Q$7,$E40,0)) -> 0 | R40: =IF($D40="","",IF(MONTH($D40)=R$7,$E40,0)) -> 0 | S40: =IF($D40="","",IF(MONTH($D40)=S$7,$E40,0)) -> 0 | T40: =IF($D40="","",IF(MONTH($D40)=T$7,$E40,0)) -> 0 | U40: =IF($D40="","",IF(MONTH($D40)=U$7,$E40,0)) -> 0 | V40: =IF($D40="","",IF(MONTH($D40)=V$7,$E40,0)) -> 0 | ... Z40: =IF($D40="","",IF(MONTH($D40)=Z$7,$E40,0)) -> 0
B41: =B40+2 -> 43868 | C41: -50 | D41: 43870 | E41: -50 | F41: Cartão de crédito | G41: 6216044 | I41: Correios | L41: =C41+L40 -> 30839 | M41: =E41+M40 -> 30839 | O41: =IF($D41="","",IF(MONTH($D41)=O$7,$E41,0)) -> 0 | P41: =IF($D41="","",IF(MONTH($D41)=P$7,$E41,0)) -> -50 | Q41: =IF($D41="","",IF(MONTH($D41)=Q$7,$E41,0)) -> 0 | R41: =IF($D41="","",IF(MONTH($D41)=R$7,$E41,0)) -> 0 | S41: =IF($D41="","",IF(MONTH($D41)=S$7,$E41,0)) -> 0 | T41: =IF($D41="","",IF(MONTH($D41)=T$7,$E41,0)) -> 0 | U41: =IF($D41="","",IF(MONTH($D41)=U$7,$E41,0)) -> 0 | V41: =IF($D41="","",IF(MONTH($D41)=V$7,$E41,0)) -> 0 | ... Z41: =IF($D41="","",IF(MONTH($D41)=Z$7,$E41,0)) -> 0
B42: =B41+2 -> 43870 | C42: -1106 | D42: 43872 | E42: -1106 | F42: Cobrança bancária | G42: 6292097.2 | I42: Segurança | L42: =C42+L41 -> 29733 | M42: =E42+M41 -> 29733 | O42: =IF($D42="","",IF(MONTH($D42)=O$7,$E42,0)) -> 0 | P42: =IF($D42="","",IF(MONTH($D42)=P$7,$E42,0)) -> -1106 | Q42: =IF($D42="","",IF(MONTH($D42)=Q$7,$E42,0)) -> 0 | R42: =IF($D42="","",IF(MONTH($D42)=R$7,$E42,0)) -> 0 | S42: =IF($D42="","",IF(MONTH($D42)=S$7,$E42,0)) -> 0 | T42: =IF($D42="","",IF(MONTH($D42)=T$7,$E42,0)) -> 0 | U42: =IF($D42="","",IF(MONTH($D42)=U$7,$E42,0)) -> 0 | V42: =IF($D42="","",IF(MONTH($D42)=V$7,$E42,0)) -> 0 | ... Z42: =IF($D42="","",IF(MONTH($D42)=Z$7,$E42,0)) -> 0
B43: =B42+2 -> 43872 | C43: 7846 | D43: 43875 | E43: 7846 | F43: Cheque | H43: 840043 | I43: Consultoria | J43: Cliente XYZ | L43: =C43+L42 -> 37579 | M43: =E43+M42 -> 37579 | O43: =IF($D43="","",IF(MONTH($D43)=O$7,$E43,0)) -> 0 | P43: =IF($D43="","",IF(MONTH($D43)=P$7,$E43,0)) -> 7846 | Q43: =IF($D43="","",IF(MONTH($D43)=Q$7,$E43,0)) -> 0 | R43: =IF($D43="","",IF(MONTH($D43)=R$7,$E43,0)) -> 0 | S43: =IF($D43="","",IF(MONTH($D43)=S$7,$E43,0)) -> 0 | T43: =IF($D43="","",IF(MONTH($D43)=T$7,$E43,0)) -> 0 | U43: =IF($D43="","",IF(MONTH($D43)=U$7,$E43,0)) -> 0 | V43: =IF($D43="","",IF(MONTH($D43)=V$7,$E43,0)) -> 0 | ... Z43: =IF($D43="","",IF(MONTH($D43)=Z$7,$E43,0)) -> 0
B44: =B43+2 -> 43874 | C44: 4731 | D44: 43876 | E44: 4731 | F44: Deposito bancário | H44: 641495 | I44: Consultoria | J44: Cliente ABC | L44: =C44+L43 -> 42310 | M44: =E44+M43 -> 42310 | O44: =IF($D44="","",IF(MONTH($D44)=O$7,$E44,0)) -> 0 | P44: =IF($D44="","",IF(MONTH($D44)=P$7,$E44,0)) -> 4731 | Q44: =IF($D44="","",IF(MONTH($D44)=Q$7,$E44,0)) -> 0 | R44: =IF($D44="","",IF(MONTH($D44)=R$7,$E44,0)) -> 0 | S44: =IF($D44="","",IF(MONTH($D44)=S$7,$E44,0)) -> 0 | T44: =IF($D44="","",IF(MONTH($D44)=T$7,$E44,0)) -> 0 | U44: =IF($D44="","",IF(MONTH($D44)=U$7,$E44,0)) -> 0 | V44: =IF($D44="","",IF(MONTH($D44)=V$7,$E44,0)) -> 0 | ... Z44: =IF($D44="","",IF(MONTH($D44)=Z$7,$E44,0)) -> 0
B45: =B44+2 -> 43876 | C45: 3812 | D45: 43878 | E45: 3812 | F45: Dinheiro | H45: 327592 | I45: Consultoria | J45: Cliente ABC | L45: =C45+L44 -> 46122 | M45: =E45+M44 -> 46122 | O45: =IF($D45="","",IF(MONTH($D45)=O$7,$E45,0)) -> 0 | P45: =IF($D45="","",IF(MONTH($D45)=P$7,$E45,0)) -> 3812 | Q45: =IF($D45="","",IF(MONTH($D45)=Q$7,$E45,0)) -> 0 | R45: =IF($D45="","",IF(MONTH($D45)=R$7,$E45,0)) -> 0 | S45: =IF($D45="","",IF(MONTH($D45)=S$7,$E45,0)) -> 0 | T45: =IF($D45="","",IF(MONTH($D45)=T$7,$E45,0)) -> 0 | U45: =IF($D45="","",IF(MONTH($D45)=U$7,$E45,0)) -> 0 | V45: =IF($D45="","",IF(MONTH($D45)=V$7,$E45,0)) -> 0 | ... Z45: =IF($D45="","",IF(MONTH($D45)=Z$7,$E45,0)) -> 0
B46: =B45+2 -> 43878 | C46: -30 | D46: 43881 | E46: -30 | F46: Deposito bancário | G46: 6368150.4 | I46: Fones / Comunicação | L46: =C46+L45 -> 46092 | M46: =E46+M45 -> 46092 | O46: =IF($D46="","",IF(MONTH($D46)=O$7,$E46,0)) -> 0 | P46: =IF($D46="","",IF(MONTH($D46)=P$7,$E46,0)) -> -30 | Q46: =IF($D46="","",IF(MONTH($D46)=Q$7,$E46,0)) -> 0 | R46: =IF($D46="","",IF(MONTH($D46)=R$7,$E46,0)) -> 0 | S46: =IF($D46="","",IF(MONTH($D46)=S$7,$E46,0)) -> 0 | T46: =IF($D46="","",IF(MONTH($D46)=T$7,$E46,0)) -> 0 | U46: =IF($D46="","",IF(MONTH($D46)=U$7,$E46,0)) -> 0 | V46: =IF($D46="","",IF(MONTH($D46)=V$7,$E46,0)) -> 0 | ... Z46: =IF($D46="","",IF(MONTH($D46)=Z$7,$E46,0)) -> 0
B47: =B46+2 -> 43880 | C47: -230 | D47: 43881 | E47: -230 | F47: Deposito bancário | G47: 6444203.6 | I47: Impostos/taxas diversas | L47: =C47+L46 -> 45862 | M47: =E47+M46 -> 45862 | O47: =IF($D47="","",IF(MONTH($D47)=O$7,$E47,0)) -> 0 | P47: =IF($D47="","",IF(MONTH($D47)=P$7,$E47,0)) -> -230 | Q47: =IF($D47="","",IF(MONTH($D47)=Q$7,$E47,0)) -> 0 | R47: =IF($D47="","",IF(MONTH($D47)=R$7,$E47,0)) -> 0 | S47: =IF($D47="","",IF(MONTH($D47)=S$7,$E47,0)) -> 0 | T47: =IF($D47="","",IF(MONTH($D47)=T$7,$E47,0)) -> 0 | U47: =IF($D47="","",IF(MONTH($D47)=U$7,$E47,0)) -> 0 | V47: =IF($D47="","",IF(MONTH($D47)=V$7,$E47,0)) -> 0 | ... Z47: =IF($D47="","",IF(MONTH($D47)=Z$7,$E47,0)) -> 0
B48: =B47+2 -> 43882 | C48: -606 | D48: 43885 | E48: -606 | F48: Deposito bancário | G48: 6520256.8 | I48: Outras DFs | L48: =C48+L47 -> 45256 | M48: =E48+M47 -> 45256 | O48: =IF($D48="","",IF(MONTH($D48)=O$7,$E48,0)) -> 0 | P48: =IF($D48="","",IF(MONTH($D48)=P$7,$E48,0)) -> -606 | Q48: =IF($D48="","",IF(MONTH($D48)=Q$7,$E48,0)) -> 0 | R48: =IF($D48="","",IF(MONTH($D48)=R$7,$E48,0)) -> 0 | S48: =IF($D48="","",IF(MONTH($D48)=S$7,$E48,0)) -> 0 | T48: =IF($D48="","",IF(MONTH($D48)=T$7,$E48,0)) -> 0 | U48: =IF($D48="","",IF(MONTH($D48)=U$7,$E48,0)) -> 0 | V48: =IF($D48="","",IF(MONTH($D48)=V$7,$E48,0)) -> 0 | ... Z48: =IF($D48="","",IF(MONTH($D48)=Z$7,$E48,0)) -> 0
B49: =B48+2 -> 43884 | C49: -846 | D49: 43886 | E49: -846 | F49: Dinheiro | G49: 6596310 | I49: Pro-labore | L49: =C49+L48 -> 44410 | M49: =E49+M48 -> 44410 | O49: =IF($D49="","",IF(MONTH($D49)=O$7,$E49,0)) -> 0 | P49: =IF($D49="","",IF(MONTH($D49)=P$7,$E49,0)) -> -846 | Q49: =IF($D49="","",IF(MONTH($D49)=Q$7,$E49,0)) -> 0 | R49: =IF($D49="","",IF(MONTH($D49)=R$7,$E49,0)) -> 0 | S49: =IF($D49="","",IF(MONTH($D49)=S$7,$E49,0)) -> 0 | T49: =IF($D49="","",IF(MONTH($D49)=T$7,$E49,0)) -> 0 | U49: =IF($D49="","",IF(MONTH($D49)=U$7,$E49,0)) -> 0 | V49: =IF($D49="","",IF(MONTH($D49)=V$7,$E49,0)) -> 0 | ... Z49: =IF($D49="","",IF(MONTH($D49)=Z$7,$E49,0)) -> 0
B50: =B49+2 -> 43886 | C50: -2421 | D50: 43889 | E50: -2421 | F50: Dinheiro | G50: 6672363.2 | I50: Impostos federais | L50: =C50+L49 -> 41989 | M50: =E50+M49 -> 41989 | O50: =IF($D50="","",IF(MONTH($D50)=O$7,$E50,0)) -> 0 | P50: =IF($D50="","",IF(MONTH($D50)=P$7,$E50,0)) -> -2421 | Q50: =IF($D50="","",IF(MONTH($D50)=Q$7,$E50,0)) -> 0 | R50: =IF($D50="","",IF(MONTH($D50)=R$7,$E50,0)) -> 0 | S50: =IF($D50="","",IF(MONTH($D50)=S$7,$E50,0)) -> 0 | T50: =IF($D50="","",IF(MONTH($D50)=T$7,$E50,0)) -> 0 | U50: =IF($D50="","",IF(MONTH($D50)=U$7,$E50,0)) -> 0 | V50: =IF($D50="","",IF(MONTH($D50)=V$7,$E50,0)) -> 0 | ... Z50: =IF($D50="","",IF(MONTH($D50)=Z$7,$E50,0)) -> 0
B51: =B50+2 -> 43888 | C51: -1806 | D51: 43890 | E51: -1806 | F51: Cheque | G51: 6748416.4 | I51: Fones / Comunicação | L51: =C51+L50 -> 40183 | M51: =E51+M50 -> 40183 | O51: =IF($D51="","",IF(MONTH($D51)=O$7,$E51,0)) -> 0 | P51: =IF($D51="","",IF(MONTH($D51)=P$7,$E51,0)) -> -1806 | Q51: =IF($D51="","",IF(MONTH($D51)=Q$7,$E51,0)) -> 0 | R51: =IF($D51="","",IF(MONTH($D51)=R$7,$E51,0)) -> 0 | S51: =IF($D51="","",IF(MONTH($D51)=S$7,$E51,0)) -> 0 | T51: =IF($D51="","",IF(MONTH($D51)=T$7,$E51,0)) -> 0 | U51: =IF($D51="","",IF(MONTH($D51)=U$7,$E51,0)) -> 0 | V51: =IF($D51="","",IF(MONTH($D51)=V$7,$E51,0)) -> 0 | ... Z51: =IF($D51="","",IF(MONTH($D51)=Z$7,$E51,0)) -> 0
B52: =B51+2 -> 43890 | C52: 8451 | D52: 43892 | E52: 8451 | F52: Deposito bancário | H52: 349911 | I52: Consultoria | J52: Cliente XYZ | L52: =C52+L51 -> 48634 | M52: =E52+M51 -> 48634 | O52: =IF($D52="","",IF(MONTH($D52)=O$7,$E52,0)) -> 0 | P52: =IF($D52="","",IF(MONTH($D52)=P$7,$E52,0)) -> 0 | Q52: =IF($D52="","",IF(MONTH($D52)=Q$7,$E52,0)) -> 8451 | R52: =IF($D52="","",IF(MONTH($D52)=R$7,$E52,0)) -> 0 | S52: =IF($D52="","",IF(MONTH($D52)=S$7,$E52,0)) -> 0 | T52: =IF($D52="","",IF(MONTH($D52)=T$7,$E52,0)) -> 0 | U52: =IF($D52="","",IF(MONTH($D52)=U$7,$E52,0)) -> 0 | V52: =IF($D52="","",IF(MONTH($D52)=V$7,$E52,0)) -> 0 | ... Z52: =IF($D52="","",IF(MONTH($D52)=Z$7,$E52,0)) -> 0
B53: =B52+2 -> 43892 | C53: 13338 | D53: 43895 | E53: 13338 | F53: Dinheiro | H53: 148050 | I53: Manutenção de Sistemas | J53: Cliente ABC | L53: =C53+L52 -> 61972 | M53: =E53+M52 -> 61972 | O53: =IF($D53="","",IF(MONTH($D53)=O$7,$E53,0)) -> 0 | P53: =IF($D53="","",IF(MONTH($D53)=P$7,$E53,0)) -> 0 | Q53: =IF($D53="","",IF(MONTH($D53)=Q$7,$E53,0)) -> 13338 | R53: =IF($D53="","",IF(MONTH($D53)=R$7,$E53,0)) -> 0 | S53: =IF($D53="","",IF(MONTH($D53)=S$7,$E53,0)) -> 0 | T53: =IF($D53="","",IF(MONTH($D53)=T$7,$E53,0)) -> 0 | U53: =IF($D53="","",IF(MONTH($D53)=U$7,$E53,0)) -> 0 | V53: =IF($D53="","",IF(MONTH($D53)=V$7,$E53,0)) -> 0 | ... Z53: =IF($D53="","",IF(MONTH($D53)=Z$7,$E53,0)) -> 0
B54: =B53+2 -> 43894 | C54: 6415 | D54: 43896 | E54: 6415 | F54: Deposito bancário | H54: 703210 | I54: Manutenção de Sistemas | J54: Cliente ABC | L54: =C54+L53 -> 68387 | M54: =E54+M53 -> 68387 | O54: =IF($D54="","",IF(MONTH($D54)=O$7,$E54,0)) -> 0 | P54: =IF($D54="","",IF(MONTH($D54)=P$7,$E54,0)) -> 0 | Q54: =IF($D54="","",IF(MONTH($D54)=Q$7,$E54,0)) -> 6415 | R54: =IF($D54="","",IF(MONTH($D54)=R$7,$E54,0)) -> 0 | S54: =IF($D54="","",IF(MONTH($D54)=S$7,$E54,0)) -> 0 | T54: =IF($D54="","",IF(MONTH($D54)=T$7,$E54,0)) -> 0 | U54: =IF($D54="","",IF(MONTH($D54)=U$7,$E54,0)) -> 0 | V54: =IF($D54="","",IF(MONTH($D54)=V$7,$E54,0)) -> 0 | ... Z54: =IF($D54="","",IF(MONTH($D54)=Z$7,$E54,0)) -> 0
B55: =B54+2 -> 43896 | C55: -2634 | D55: 43898 | E55: -2634 | F55: Deposito bancário | G55: 6824469.6 | I55: Material escritório | L55: =C55+L54 -> 65753 | M55: =E55+M54 -> 65753 | O55: =IF($D55="","",IF(MONTH($D55)=O$7,$E55,0)) -> 0 | P55: =IF($D55="","",IF(MONTH($D55)=P$7,$E55,0)) -> 0 | Q55: =IF($D55="","",IF(MONTH($D55)=Q$7,$E55,0)) -> -2634 | R55: =IF($D55="","",IF(MONTH($D55)=R$7,$E55,0)) -> 0 | S55: =IF($D55="","",IF(MONTH($D55)=S$7,$E55,0)) -> 0 | T55: =IF($D55="","",IF(MONTH($D55)=T$7,$E55,0)) -> 0 | U55: =IF($D55="","",IF(MONTH($D55)=U$7,$E55,0)) -> 0 | V55: =IF($D55="","",IF(MONTH($D55)=V$7,$E55,0)) -> 0 | ... Z55: =IF($D55="","",IF(MONTH($D55)=Z$7,$E55,0)) -> 0
B56: =B55+2 -> 43898 | C56: -1358 | D56: 43900 | E56: -1358 | F56: Deposito bancário | G56: 6900522.8 | I56: Segurança | L56: =C56+L55 -> 64395 | M56: =E56+M55 -> 64395 | O56: =IF($D56="","",IF(MONTH($D56)=O$7,$E56,0)) -> 0 | P56: =IF($D56="","",IF(MONTH($D56)=P$7,$E56,0)) -> 0 | Q56: =IF($D56="","",IF(MONTH($D56)=Q$7,$E56,0)) -> -1358 | R56: =IF($D56="","",IF(MONTH($D56)=R$7,$E56,0)) -> 0 | S56: =IF($D56="","",IF(MONTH($D56)=S$7,$E56,0)) -> 0 | T56: =IF($D56="","",IF(MONTH($D56)=T$7,$E56,0)) -> 0 | U56: =IF($D56="","",IF(MONTH($D56)=U$7,$E56,0)) -> 0 | V56: =IF($D56="","",IF(MONTH($D56)=V$7,$E56,0)) -> 0 | ... Z56: =IF($D56="","",IF(MONTH($D56)=Z$7,$E56,0)) -> 0
B57: =B56+2 -> 43900 | C57: 10267 | D57: 43901 | E57: 10267 | F57: Dinheiro | H57: 373054 | I57: Licença de software | J57: Cliente ABC | L57: =C57+L56 -> 74662 | M57: =E57+M56 -> 74662 | O57: =IF($D57="","",IF(MONTH($D57)=O$7,$E57,0)) -> 0 | P57: =IF($D57="","",IF(MONTH($D57)=P$7,$E57,0)) -> 0 | Q57: =IF($D57="","",IF(MONTH($D57)=Q$7,$E57,0)) -> 10267 | R57: =IF($D57="","",IF(MONTH($D57)=R$7,$E57,0)) -> 0 | S57: =IF($D57="","",IF(MONTH($D57)=S$7,$E57,0)) -> 0 | T57: =IF($D57="","",IF(MONTH($D57)=T$7,$E57,0)) -> 0 | U57: =IF($D57="","",IF(MONTH($D57)=U$7,$E57,0)) -> 0 | V57: =IF($D57="","",IF(MONTH($D57)=V$7,$E57,0)) -> 0 | ... Z57: =IF($D57="","",IF(MONTH($D57)=Z$7,$E57,0)) -> 0
B58: =B57+2 -> 43902 | C58: -1980 | D58: 43904 | E58: -1980 | F58: Dinheiro | G58: 6976576 | I58: Impostos/taxas diversas | L58: =C58+L57 -> 72682 | M58: =E58+M57 -> 72682 | O58: =IF($D58="","",IF(MONTH($D58)=O$7,$E58,0)) -> 0 | P58: =IF($D58="","",IF(MONTH($D58)=P$7,$E58,0)) -> 0 | Q58: =IF($D58="","",IF(MONTH($D58)=Q$7,$E58,0)) -> -1980 | R58: =IF($D58="","",IF(MONTH($D58)=R$7,$E58,0)) -> 0 | S58: =IF($D58="","",IF(MONTH($D58)=S$7,$E58,0)) -> 0 | T58: =IF($D58="","",IF(MONTH($D58)=T$7,$E58,0)) -> 0 | U58: =IF($D58="","",IF(MONTH($D58)=U$7,$E58,0)) -> 0 | V58: =IF($D58="","",IF(MONTH($D58)=V$7,$E58,0)) -> 0 | ... Z58: =IF($D58="","",IF(MONTH($D58)=Z$7,$E58,0)) -> 0
B59: =B58+2 -> 43904 | C59: -2302 | D59: 43905 | E59: -2302 | F59: Deposito bancário | G59: 7052629.2 | I59: Impostos municipais | L59: =C59+L58 -> 70380 | M59: =E59+M58 -> 70380 | O59: =IF($D59="","",IF(MONTH($D59)=O$7,$E59,0)) -> 0 | P59: =IF($D59="","",IF(MONTH($D59)=P$7,$E59,0)) -> 0 | Q59: =IF($D59="","",IF(MONTH($D59)=Q$7,$E59,0)) -> -2302 | R59: =IF($D59="","",IF(MONTH($D59)=R$7,$E59,0)) -> 0 | S59: =IF($D59="","",IF(MONTH($D59)=S$7,$E59,0)) -> 0 | T59: =IF($D59="","",IF(MONTH($D59)=T$7,$E59,0)) -> 0 | U59: =IF($D59="","",IF(MONTH($D59)=U$7,$E59,0)) -> 0 | V59: =IF($D59="","",IF(MONTH($D59)=V$7,$E59,0)) -> 0 | ... Z59: =IF($D59="","",IF(MONTH($D59)=Z$7,$E59,0)) -> 0
B60: =B59+2 -> 43906 | C60: -1735 | D60: 43908 | E60: -1735 | F60: Dinheiro | G60: 7128682.4 | I60: Pro-labore | L60: =C60+L59 -> 68645 | M60: =E60+M59 -> 68645 | O60: =IF($D60="","",IF(MONTH($D60)=O$7,$E60,0)) -> 0 | P60: =IF($D60="","",IF(MONTH($D60)=P$7,$E60,0)) -> 0 | Q60: =IF($D60="","",IF(MONTH($D60)=Q$7,$E60,0)) -> -1735 | R60: =IF($D60="","",IF(MONTH($D60)=R$7,$E60,0)) -> 0 | S60: =IF($D60="","",IF(MONTH($D60)=S$7,$E60,0)) -> 0 | T60: =IF($D60="","",IF(MONTH($D60)=T$7,$E60,0)) -> 0 | U60: =IF($D60="","",IF(MONTH($D60)=U$7,$E60,0)) -> 0 | V60: =IF($D60="","",IF(MONTH($D60)=V$7,$E60,0)) -> 0 | ... Z60: =IF($D60="","",IF(MONTH($D60)=Z$7,$E60,0)) -> 0
B61: =B60+2 -> 43908 | C61: -1380 | D61: 43911 | E61: -1380 | F61: Cheque | G61: 7204735.6 | I61: Segurança | L61: =C61+L60 -> 67265 | M61: =E61+M60 -> 67265 | O61: =IF($D61="","",IF(MONTH($D61)=O$7,$E61,0)) -> 0 | P61: =IF($D61="","",IF(MONTH($D61)=P$7,$E61,0)) -> 0 | Q61: =IF($D61="","",IF(MONTH($D61)=Q$7,$E61,0)) -> -1380 | R61: =IF($D61="","",IF(MONTH($D61)=R$7,$E61,0)) -> 0 | S61: =IF($D61="","",IF(MONTH($D61)=S$7,$E61,0)) -> 0 | T61: =IF($D61="","",IF(MONTH($D61)=T$7,$E61,0)) -> 0 | U61: =IF($D61="","",IF(MONTH($D61)=U$7,$E61,0)) -> 0 | V61: =IF($D61="","",IF(MONTH($D61)=V$7,$E61,0)) -> 0 | ... Z61: =IF($D61="","",IF(MONTH($D61)=Z$7,$E61,0)) -> 0
B62: =B61+2 -> 43910 | C62: -1556 | D62: 43913 | E62: -1556 | F62: Deposito bancário | G62: 7280788.8 | I62: Fones / Comunicação | L62: =C62+L61 -> 65709 | M62: =E62+M61 -> 65709 | O62: =IF($D62="","",IF(MONTH($D62)=O$7,$E62,0)) -> 0 | P62: =IF($D62="","",IF(MONTH($D62)=P$7,$E62,0)) -> 0 | Q62: =IF($D62="","",IF(MONTH($D62)=Q$7,$E62,0)) -> -1556 | R62: =IF($D62="","",IF(MONTH($D62)=R$7,$E62,0)) -> 0 | S62: =IF($D62="","",IF(MONTH($D62)=S$7,$E62,0)) -> 0 | T62: =IF($D62="","",IF(MONTH($D62)=T$7,$E62,0)) -> 0 | U62: =IF($D62="","",IF(MONTH($D62)=U$7,$E62,0)) -> 0 | V62: =IF($D62="","",IF(MONTH($D62)=V$7,$E62,0)) -> 0 | ... Z62: =IF($D62="","",IF(MONTH($D62)=Z$7,$E62,0)) -> 0
B63: =B62+2 -> 43912 | C63: 8534 | D63: 43913 | E63: 8534 | F63: Dinheiro | H63: 119538 | I63: Manutenção de Sistemas | J63: Cliente XYZ | L63: =C63+L62 -> 74243 | M63: =E63+M62 -> 74243 | O63: =IF($D63="","",IF(MONTH($D63)=O$7,$E63,0)) -> 0 | P63: =IF($D63="","",IF(MONTH($D63)=P$7,$E63,0)) -> 0 | Q63: =IF($D63="","",IF(MONTH($D63)=Q$7,$E63,0)) -> 8534 | R63: =IF($D63="","",IF(MONTH($D63)=R$7,$E63,0)) -> 0 | S63: =IF($D63="","",IF(MONTH($D63)=S$7,$E63,0)) -> 0 | T63: =IF($D63="","",IF(MONTH($D63)=T$7,$E63,0)) -> 0 | U63: =IF($D63="","",IF(MONTH($D63)=U$7,$E63,0)) -> 0 | V63: =IF($D63="","",IF(MONTH($D63)=V$7,$E63,0)) -> 0 | ... Z63: =IF($D63="","",IF(MONTH($D63)=Z$7,$E63,0)) -> 0
B64: =B63+2 -> 43914 | C64: 4635 | D64: 43917 | E64: 4635 | F64: Deposito bancário | H64: 525607 | I64: Manutenção de Sistemas | J64: Cliente ABC | L64: =C64+L63 -> 78878 | M64: =E64+M63 -> 78878 | O64: =IF($D64="","",IF(MONTH($D64)=O$7,$E64,0)) -> 0 | P64: =IF($D64="","",IF(MONTH($D64)=P$7,$E64,0)) -> 0 | Q64: =IF($D64="","",IF(MONTH($D64)=Q$7,$E64,0)) -> 4635 | R64: =IF($D64="","",IF(MONTH($D64)=R$7,$E64,0)) -> 0 | S64: =IF($D64="","",IF(MONTH($D64)=S$7,$E64,0)) -> 0 | T64: =IF($D64="","",IF(MONTH($D64)=T$7,$E64,0)) -> 0 | U64: =IF($D64="","",IF(MONTH($D64)=U$7,$E64,0)) -> 0 | V64: =IF($D64="","",IF(MONTH($D64)=V$7,$E64,0)) -> 0 | ... Z64: =IF($D64="","",IF(MONTH($D64)=Z$7,$E64,0)) -> 0
B65: =B64+2 -> 43916 | C65: 11307 | D65: 43917 | E65: 11307 | F65: Deposito bancário | H65: 560783 | I65: Manutenção de Sistemas | J65: Cliente ABC | L65: =C65+L64 -> 90185 | M65: =E65+M64 -> 90185 | O65: =IF($D65="","",IF(MONTH($D65)=O$7,$E65,0)) -> 0 | P65: =IF($D65="","",IF(MONTH($D65)=P$7,$E65,0)) -> 0 | Q65: =IF($D65="","",IF(MONTH($D65)=Q$7,$E65,0)) -> 11307 | R65: =IF($D65="","",IF(MONTH($D65)=R$7,$E65,0)) -> 0 | S65: =IF($D65="","",IF(MONTH($D65)=S$7,$E65,0)) -> 0 | T65: =IF($D65="","",IF(MONTH($D65)=T$7,$E65,0)) -> 0 | U65: =IF($D65="","",IF(MONTH($D65)=U$7,$E65,0)) -> 0 | V65: =IF($D65="","",IF(MONTH($D65)=V$7,$E65,0)) -> 0 | ... Z65: =IF($D65="","",IF(MONTH($D65)=Z$7,$E65,0)) -> 0
B66: =B65+2 -> 43918 | C66: -593 | D66: 43921 | E66: -593 | F66: Deposito bancário | G66: 7356842 | I66: Material escritório | L66: =C66+L65 -> 89592 | M66: =E66+M65 -> 89592 | O66: =IF($D66="","",IF(MONTH($D66)=O$7,$E66,0)) -> 0 | P66: =IF($D66="","",IF(MONTH($D66)=P$7,$E66,0)) -> 0 | Q66: =IF($D66="","",IF(MONTH($D66)=Q$7,$E66,0)) -> -593 | R66: =IF($D66="","",IF(MONTH($D66)=R$7,$E66,0)) -> 0 | S66: =IF($D66="","",IF(MONTH($D66)=S$7,$E66,0)) -> 0 | T66: =IF($D66="","",IF(MONTH($D66)=T$7,$E66,0)) -> 0 | U66: =IF($D66="","",IF(MONTH($D66)=U$7,$E66,0)) -> 0 | V66: =IF($D66="","",IF(MONTH($D66)=V$7,$E66,0)) -> 0 | ... Z66: =IF($D66="","",IF(MONTH($D66)=Z$7,$E66,0)) -> 0
B67: =B66+2 -> 43920 | C67: -3135 | D67: 43922 | E67: -3135 | F67: Dinheiro | G67: 7432895.2 | I67: Comissões | L67: =C67+L66 -> 86457 | M67: =E67+M66 -> 86457 | O67: =IF($D67="","",IF(MONTH($D67)=O$7,$E67,0)) -> 0 | P67: =IF($D67="","",IF(MONTH($D67)=P$7,$E67,0)) -> 0 | Q67: =IF($D67="","",IF(MONTH($D67)=Q$7,$E67,0)) -> 0 | R67: =IF($D67="","",IF(MONTH($D67)=R$7,$E67,0)) -> -3135 | S67: =IF($D67="","",IF(MONTH($D67)=S$7,$E67,0)) -> 0 | T67: =IF($D67="","",IF(MONTH($D67)=T$7,$E67,0)) -> 0 | U67: =IF($D67="","",IF(MONTH($D67)=U$7,$E67,0)) -> 0 | V67: =IF($D67="","",IF(MONTH($D67)=V$7,$E67,0)) -> 0 | ... Z67: =IF($D67="","",IF(MONTH($D67)=Z$7,$E67,0)) -> 0
B68: =B67+2 -> 43922 | C68: -1669 | D68: 43925 | E68: -1669 | F68: Dinheiro | G68: 7508948.4 | I68: Segurança | L68: =C68+L67 -> 84788 | M68: =E68+M67 -> 84788 | O68: =IF($D68="","",IF(MONTH($D68)=O$7,$E68,0)) -> 0 | P68: =IF($D68="","",IF(MONTH($D68)=P$7,$E68,0)) -> 0 | Q68: =IF($D68="","",IF(MONTH($D68)=Q$7,$E68,0)) -> 0 | R68: =IF($D68="","",IF(MONTH($D68)=R$7,$E68,0)) -> -1669 | S68: =IF($D68="","",IF(MONTH($D68)=S$7,$E68,0)) -> 0 | T68: =IF($D68="","",IF(MONTH($D68)=T$7,$E68,0)) -> 0 | U68: =IF($D68="","",IF(MONTH($D68)=U$7,$E68,0)) -> 0 | V68: =IF($D68="","",IF(MONTH($D68)=V$7,$E68,0)) -> 0 | ... Z68: =IF($D68="","",IF(MONTH($D68)=Z$7,$E68,0)) -> 0
B69: =B68+2 -> 43924 | C69: -876 | D69: 43925 | E69: -876 | F69: Deposito bancário | G69: 7585001.6 | I69: Fones / Comunicação | L69: =C69+L68 -> 83912 | M69: =E69+M68 -> 83912 | O69: =IF($D69="","",IF(MONTH($D69)=O$7,$E69,0)) -> 0 | P69: =IF($D69="","",IF(MONTH($D69)=P$7,$E69,0)) -> 0 | Q69: =IF($D69="","",IF(MONTH($D69)=Q$7,$E69,0)) -> 0 | R69: =IF($D69="","",IF(MONTH($D69)=R$7,$E69,0)) -> -876 | S69: =IF($D69="","",IF(MONTH($D69)=S$7,$E69,0)) -> 0 | T69: =IF($D69="","",IF(MONTH($D69)=T$7,$E69,0)) -> 0 | U69: =IF($D69="","",IF(MONTH($D69)=U$7,$E69,0)) -> 0 | V69: =IF($D69="","",IF(MONTH($D69)=V$7,$E69,0)) -> 0 | ... Z69: =IF($D69="","",IF(MONTH($D69)=Z$7,$E69,0)) -> 0
B70: =B69+2 -> 43926 | C70: -2072 | D70: 43929 | E70: -2072 | F70: Dinheiro | G70: 7661054.8 | I70: Impostos/taxas diversas | L70: =C70+L69 -> 81840 | M70: =E70+M69 -> 81840 | O70: =IF($D70="","",IF(MONTH($D70)=O$7,$E70,0)) -> 0 | P70: =IF($D70="","",IF(MONTH($D70)=P$7,$E70,0)) -> 0 | Q70: =IF($D70="","",IF(MONTH($D70)=Q$7,$E70,0)) -> 0 | R70: =IF($D70="","",IF(MONTH($D70)=R$7,$E70,0)) -> -2072 | S70: =IF($D70="","",IF(MONTH($D70)=S$7,$E70,0)) -> 0 | T70: =IF($D70="","",IF(MONTH($D70)=T$7,$E70,0)) -> 0 | U70: =IF($D70="","",IF(MONTH($D70)=U$7,$E70,0)) -> 0 | V70: =IF($D70="","",IF(MONTH($D70)=V$7,$E70,0)) -> 0 | ... Z70: =IF($D70="","",IF(MONTH($D70)=Z$7,$E70,0)) -> 0
B71: =B70+2 -> 43928 | C71: 9096 | D71: 43930 | E71: 9096 | F71: Dinheiro | H71: 819413 | I71: Consultoria | J71: Cliente ABC | L71: =C71+L70 -> 90936 | M71: =E71+M70 -> 90936 | O71: =IF($D71="","",IF(MONTH($D71)=O$7,$E71,0)) -> 0 | P71: =IF($D71="","",IF(MONTH($D71)=P$7,$E71,0)) -> 0 | Q71: =IF($D71="","",IF(MONTH($D71)=Q$7,$E71,0)) -> 0 | R71: =IF($D71="","",IF(MONTH($D71)=R$7,$E71,0)) -> 9096 | S71: =IF($D71="","",IF(MONTH($D71)=S$7,$E71,0)) -> 0 | T71: =IF($D71="","",IF(MONTH($D71)=T$7,$E71,0)) -> 0 | U71: =IF($D71="","",IF(MONTH($D71)=U$7,$E71,0)) -> 0 | V71: =IF($D71="","",IF(MONTH($D71)=V$7,$E71,0)) -> 0 | ... Z71: =IF($D71="","",IF(MONTH($D71)=Z$7,$E71,0)) -> 0
B72: =B71+2 -> 43930 | C72: 9570 | D72: 43932 | E72: 9570 | F72: Cheque | H72: 609575 | I72: Licença de software | J72: Cliente ABC | L72: =C72+L71 -> 100506 | M72: =E72+M71 -> 100506 | O72: =IF($D72="","",IF(MONTH($D72)=O$7,$E72,0)) -> 0 | P72: =IF($D72="","",IF(MONTH($D72)=P$7,$E72,0)) -> 0 | Q72: =IF($D72="","",IF(MONTH($D72)=Q$7,$E72,0)) -> 0 | R72: =IF($D72="","",IF(MONTH($D72)=R$7,$E72,0)) -> 9570 | S72: =IF($D72="","",IF(MONTH($D72)=S$7,$E72,0)) -> 0 | T72: =IF($D72="","",IF(MONTH($D72)=T$7,$E72,0)) -> 0 | U72: =IF($D72="","",IF(MONTH($D72)=U$7,$E72,0)) -> 0 | V72: =IF($D72="","",IF(MONTH($D72)=V$7,$E72,0)) -> 0 | ... Z72: =IF($D72="","",IF(MONTH($D72)=Z$7,$E72,0)) -> 0
B73: =B72+2 -> 43932 | C73: 3679 | D73: 43933 | E73: 3679 | F73: Deposito bancário | H73: 172621 | I73: Consultoria | J73: Cliente ABC | L73: =C73+L72 -> 104185 | M73: =E73+M72 -> 104185 | O73: =IF($D73="","",IF(MONTH($D73)=O$7,$E73,0)) -> 0 | P73: =IF($D73="","",IF(MONTH($D73)=P$7,$E73,0)) -> 0 | Q73: =IF($D73="","",IF(MONTH($D73)=Q$7,$E73,0)) -> 0 | R73: =IF($D73="","",IF(MONTH($D73)=R$7,$E73,0)) -> 3679 | S73: =IF($D73="","",IF(MONTH($D73)=S$7,$E73,0)) -> 0 | T73: =IF($D73="","",IF(MONTH($D73)=T$7,$E73,0)) -> 0 | U73: =IF($D73="","",IF(MONTH($D73)=U$7,$E73,0)) -> 0 | V73: =IF($D73="","",IF(MONTH($D73)=V$7,$E73,0)) -> 0 | ... Z73: =IF($D73="","",IF(MONTH($D73)=Z$7,$E73,0)) -> 0
B74: =B73+2 -> 43934 | C74: -1145 | D74: 43936 | E74: -1145 | F74: Dinheiro | G74: 7737108 | I74: Fones / Comunicação | L74: =C74+L73 -> 103040 | M74: =E74+M73 -> 103040 | O74: =IF($D74="","",IF(MONTH($D74)=O$7,$E74,0)) -> 0 | P74: =IF($D74="","",IF(MONTH($D74)=P$7,$E74,0)) -> 0 | Q74: =IF($D74="","",IF(MONTH($D74)=Q$7,$E74,0)) -> 0 | R74: =IF($D74="","",IF(MONTH($D74)=R$7,$E74,0)) -> -1145 | S74: =IF($D74="","",IF(MONTH($D74)=S$7,$E74,0)) -> 0 | T74: =IF($D74="","",IF(MONTH($D74)=T$7,$E74,0)) -> 0 | U74: =IF($D74="","",IF(MONTH($D74)=U$7,$E74,0)) -> 0 | V74: =IF($D74="","",IF(MONTH($D74)=V$7,$E74,0)) -> 0 | ... Z74: =IF($D74="","",IF(MONTH($D74)=Z$7,$E74,0)) -> 0
B75: =B74+2 -> 43936 | C75: -1484 | D75: 43937 | E75: -1484 | F75: Deposito bancário | G75: 7813161.2 | I75: Material escritório | L75: =C75+L74 -> 101556 | M75: =E75+M74 -> 101556 | O75: =IF($D75="","",IF(MONTH($D75)=O$7,$E75,0)) -> 0 | P75: =IF($D75="","",IF(MONTH($D75)=P$7,$E75,0)) -> 0 | Q75: =IF($D75="","",IF(MONTH($D75)=Q$7,$E75,0)) -> 0 | R75: =IF($D75="","",IF(MONTH($D75)=R$7,$E75,0)) -> -1484 | S75: =IF($D75="","",IF(MONTH($D75)=S$7,$E75,0)) -> 0 | T75: =IF($D75="","",IF(MONTH($D75)=T$7,$E75,0)) -> 0 | U75: =IF($D75="","",IF(MONTH($D75)=U$7,$E75,0)) -> 0 | V75: =IF($D75="","",IF(MONTH($D75)=V$7,$E75,0)) -> 0 | ... Z75: =IF($D75="","",IF(MONTH($D75)=Z$7,$E75,0)) -> 0
B76: =B75+2 -> 43938 | C76: 9493 | D76: 43940 | E76: 9493 | F76: Deposito bancário | H76: 489260 | I76: Licença de software | J76: Cliente ABC | L76: =C76+L75 -> 111049 | M76: =E76+M75 -> 111049 | O76: =IF($D76="","",IF(MONTH($D76)=O$7,$E76,0)) -> 0 | P76: =IF($D76="","",IF(MONTH($D76)=P$7,$E76,0)) -> 0 | Q76: =IF($D76="","",IF(MONTH($D76)=Q$7,$E76,0)) -> 0 | R76: =IF($D76="","",IF(MONTH($D76)=R$7,$E76,0)) -> 9493 | S76: =IF($D76="","",IF(MONTH($D76)=S$7,$E76,0)) -> 0 | T76: =IF($D76="","",IF(MONTH($D76)=T$7,$E76,0)) -> 0 | U76: =IF($D76="","",IF(MONTH($D76)=U$7,$E76,0)) -> 0 | V76: =IF($D76="","",IF(MONTH($D76)=V$7,$E76,0)) -> 0 | ... Z76: =IF($D76="","",IF(MONTH($D76)=Z$7,$E76,0)) -> 0
B77: =B76+2 -> 43940 | C77: -380 | D77: 43942 | E77: -380 | F77: Deposito bancário | G77: 7889214.4 | I77: Impostos/taxas diversas | L77: =C77+L76 -> 110669 | M77: =E77+M76 -> 110669 | O77: =IF($D77="","",IF(MONTH($D77)=O$7,$E77,0)) -> 0 | P77: =IF($D77="","",IF(MONTH($D77)=P$7,$E77,0)) -> 0 | Q77: =IF($D77="","",IF(MONTH($D77)=Q$7,$E77,0)) -> 0 | R77: =IF($D77="","",IF(MONTH($D77)=R$7,$E77,0)) -> -380 | S77: =IF($D77="","",IF(MONTH($D77)=S$7,$E77,0)) -> 0 | T77: =IF($D77="","",IF(MONTH($D77)=T$7,$E77,0)) -> 0 | U77: =IF($D77="","",IF(MONTH($D77)=U$7,$E77,0)) -> 0 | V77: =IF($D77="","",IF(MONTH($D77)=V$7,$E77,0)) -> 0 | ... Z77: =IF($D77="","",IF(MONTH($D77)=Z$7,$E77,0)) -> 0
B78: =B77+2 -> 43942 | C78: -2428 | D78: 43943 | E78: -2428 | F78: Dinheiro | G78: 7965267.6 | I78: Impostos municipais | L78: =C78+L77 -> 108241 | M78: =E78+M77 -> 108241 | O78: =IF($D78="","",IF(MONTH($D78)=O$7,$E78,0)) -> 0 | P78: =IF($D78="","",IF(MONTH($D78)=P$7,$E78,0)) -> 0 | Q78: =IF($D78="","",IF(MONTH($D78)=Q$7,$E78,0)) -> 0 | R78: =IF($D78="","",IF(MONTH($D78)=R$7,$E78,0)) -> -2428 | S78: =IF($D78="","",IF(MONTH($D78)=S$7,$E78,0)) -> 0 | T78: =IF($D78="","",IF(MONTH($D78)=T$7,$E78,0)) -> 0 | U78: =IF($D78="","",IF(MONTH($D78)=U$7,$E78,0)) -> 0 | V78: =IF($D78="","",IF(MONTH($D78)=V$7,$E78,0)) -> 0 | ... Z78: =IF($D78="","",IF(MONTH($D78)=Z$7,$E78,0)) -> 0
B79: =B78+2 -> 43944 | C79: -482 | D79: 43946 | E79: -482 | F79: Dinheiro | G79: 8041320.8 | I79: Pro-labore | L79: =C79+L78 -> 107759 | M79: =E79+M78 -> 107759 | O79: =IF($D79="","",IF(MONTH($D79)=O$7,$E79,0)) -> 0 | P79: =IF($D79="","",IF(MONTH($D79)=P$7,$E79,0)) -> 0 | Q79: =IF($D79="","",IF(MONTH($D79)=Q$7,$E79,0)) -> 0 | R79: =IF($D79="","",IF(MONTH($D79)=R$7,$E79,0)) -> -482 | S79: =IF($D79="","",IF(MONTH($D79)=S$7,$E79,0)) -> 0 | T79: =IF($D79="","",IF(MONTH($D79)=T$7,$E79,0)) -> 0 | U79: =IF($D79="","",IF(MONTH($D79)=U$7,$E79,0)) -> 0 | V79: =IF($D79="","",IF(MONTH($D79)=V$7,$E79,0)) -> 0 | ... Z79: =IF($D79="","",IF(MONTH($D79)=Z$7,$E79,0)) -> 0
B80: =B79+2 -> 43946 | C80: -3081 | D80: 43948 | E80: -3081 | F80: Deposito bancário | G80: 8117374 | I80: Segurança | L80: =C80+L79 -> 104678 | M80: =E80+M79 -> 104678 | O80: =IF($D80="","",IF(MONTH($D80)=O$7,$E80,0)) -> 0 | P80: =IF($D80="","",IF(MONTH($D80)=P$7,$E80,0)) -> 0 | Q80: =IF($D80="","",IF(MONTH($D80)=Q$7,$E80,0)) -> 0 | R80: =IF($D80="","",IF(MONTH($D80)=R$7,$E80,0)) -> -3081 | S80: =IF($D80="","",IF(MONTH($D80)=S$7,$E80,0)) -> 0 | T80: =IF($D80="","",IF(MONTH($D80)=T$7,$E80,0)) -> 0 | U80: =IF($D80="","",IF(MONTH($D80)=U$7,$E80,0)) -> 0 | V80: =IF($D80="","",IF(MONTH($D80)=V$7,$E80,0)) -> 0 | ... Z80: =IF($D80="","",IF(MONTH($D80)=Z$7,$E80,0)) -> 0
B81: =B80+2 -> 43948 | C81: -1934 | D81: 43949 | E81: -1934 | F81: Deposito bancário | G81: 8193427.2 | I81: Fones / Comunicação | L81: =C81+L80 -> 102744 | M81: =E81+M80 -> 102744 | O81: =IF($D81="","",IF(MONTH($D81)=O$7,$E81,0)) -> 0 | P81: =IF($D81="","",IF(MONTH($D81)=P$7,$E81,0)) -> 0 | Q81: =IF($D81="","",IF(MONTH($D81)=Q$7,$E81,0)) -> 0 | R81: =IF($D81="","",IF(MONTH($D81)=R$7,$E81,0)) -> -1934 | S81: =IF($D81="","",IF(MONTH($D81)=S$7,$E81,0)) -> 0 | T81: =IF($D81="","",IF(MONTH($D81)=T$7,$E81,0)) -> 0 | U81: =IF($D81="","",IF(MONTH($D81)=U$7,$E81,0)) -> 0 | V81: =IF($D81="","",IF(MONTH($D81)=V$7,$E81,0)) -> 0 | ... Z81: =IF($D81="","",IF(MONTH($D81)=Z$7,$E81,0)) -> 0
B82: =B81+2 -> 43950 | C82: -1626 | D82: 43953 | E82: -1626 | F82: Deposito bancário | G82: 8269480.4 | I82: Material escritório | L82: =C82+L81 -> 101118 | M82: =E82+M81 -> 101118 | O82: =IF($D82="","",IF(MONTH($D82)=O$7,$E82,0)) -> 0 | P82: =IF($D82="","",IF(MONTH($D82)=P$7,$E82,0)) -> 0 | Q82: =IF($D82="","",IF(MONTH($D82)=Q$7,$E82,0)) -> 0 | R82: =IF($D82="","",IF(MONTH($D82)=R$7,$E82,0)) -> 0 | S82: =IF($D82="","",IF(MONTH($D82)=S$7,$E82,0)) -> -1626 | T82: =IF($D82="","",IF(MONTH($D82)=T$7,$E82,0)) -> 0 | U82: =IF($D82="","",IF(MONTH($D82)=U$7,$E82,0)) -> 0 | V82: =IF($D82="","",IF(MONTH($D82)=V$7,$E82,0)) -> 0 | ... Z82: =IF($D82="","",IF(MONTH($D82)=Z$7,$E82,0)) -> 0
B83: =B82+2 -> 43952 | C83: -1488 | D83: 43954 | E83: -1488 | F83: Deposito bancário | G83: 8345533.6 | I83: Propaganda | L83: =C83+L82 -> 99630 | M83: =E83+M82 -> 99630 | O83: =IF($D83="","",IF(MONTH($D83)=O$7,$E83,0)) -> 0 | P83: =IF($D83="","",IF(MONTH($D83)=P$7,$E83,0)) -> 0 | Q83: =IF($D83="","",IF(MONTH($D83)=Q$7,$E83,0)) -> 0 | R83: =IF($D83="","",IF(MONTH($D83)=R$7,$E83,0)) -> 0 | S83: =IF($D83="","",IF(MONTH($D83)=S$7,$E83,0)) -> -1488 | T83: =IF($D83="","",IF(MONTH($D83)=T$7,$E83,0)) -> 0 | U83: =IF($D83="","",IF(MONTH($D83)=U$7,$E83,0)) -> 0 | V83: =IF($D83="","",IF(MONTH($D83)=V$7,$E83,0)) -> 0 | ... Z83: =IF($D83="","",IF(MONTH($D83)=Z$7,$E83,0)) -> 0
B84: =B83+2 -> 43954 | C84: -2853 | D84: 43957 | E84: -2853 | F84: Deposito bancário | G84: 8421586.8 | I84: Outras despesas variáveis | L84: =C84+L83 -> 96777 | M84: =E84+M83 -> 96777 | O84: =IF($D84="","",IF(MONTH($D84)=O$7,$E84,0)) -> 0 | P84: =IF($D84="","",IF(MONTH($D84)=P$7,$E84,0)) -> 0 | Q84: =IF($D84="","",IF(MONTH($D84)=Q$7,$E84,0)) -> 0 | R84: =IF($D84="","",IF(MONTH($D84)=R$7,$E84,0)) -> 0 | S84: =IF($D84="","",IF(MONTH($D84)=S$7,$E84,0)) -> -2853 | T84: =IF($D84="","",IF(MONTH($D84)=T$7,$E84,0)) -> 0 | U84: =IF($D84="","",IF(MONTH($D84)=U$7,$E84,0)) -> 0 | V84: =IF($D84="","",IF(MONTH($D84)=V$7,$E84,0)) -> 0 | ... Z84: =IF($D84="","",IF(MONTH($D84)=Z$7,$E84,0)) -> 0
B85: =B84+2 -> 43956 | C85: -1911 | D85: 43958 | E85: -1911 | F85: Cheque | G85: 8497640 | I85: Segurança | L85: =C85+L84 -> 94866 | M85: =E85+M84 -> 94866 | O85: =IF($D85="","",IF(MONTH($D85)=O$7,$E85,0)) -> 0 | P85: =IF($D85="","",IF(MONTH($D85)=P$7,$E85,0)) -> 0 | Q85: =IF($D85="","",IF(MONTH($D85)=Q$7,$E85,0)) -> 0 | R85: =IF($D85="","",IF(MONTH($D85)=R$7,$E85,0)) -> 0 | S85: =IF($D85="","",IF(MONTH($D85)=S$7,$E85,0)) -> -1911 | T85: =IF($D85="","",IF(MONTH($D85)=T$7,$E85,0)) -> 0 | U85: =IF($D85="","",IF(MONTH($D85)=U$7,$E85,0)) -> 0 | V85: =IF($D85="","",IF(MONTH($D85)=V$7,$E85,0)) -> 0 | ... Z85: =IF($D85="","",IF(MONTH($D85)=Z$7,$E85,0)) -> 0
B86: =B85+2 -> 43958 | C86: -1358 | D86: 43959 | E86: -1358 | F86: Deposito bancário | G86: 8573693.2 | I86: Seguros | L86: =C86+L85 -> 93508 | M86: =E86+M85 -> 93508 | O86: =IF($D86="","",IF(MONTH($D86)=O$7,$E86,0)) -> 0 | P86: =IF($D86="","",IF(MONTH($D86)=P$7,$E86,0)) -> 0 | Q86: =IF($D86="","",IF(MONTH($D86)=Q$7,$E86,0)) -> 0 | R86: =IF($D86="","",IF(MONTH($D86)=R$7,$E86,0)) -> 0 | S86: =IF($D86="","",IF(MONTH($D86)=S$7,$E86,0)) -> -1358 | T86: =IF($D86="","",IF(MONTH($D86)=T$7,$E86,0)) -> 0 | U86: =IF($D86="","",IF(MONTH($D86)=U$7,$E86,0)) -> 0 | V86: =IF($D86="","",IF(MONTH($D86)=V$7,$E86,0)) -> 0 | ... Z86: =IF($D86="","",IF(MONTH($D86)=Z$7,$E86,0)) -> 0
B87: =B86+2 -> 43960 | C87: -1525 | D87: 43963 | E87: -1525 | F87: Dinheiro | G87: 8649746.4 | I87: Terceirizados | L87: =C87+L86 -> 91983 | M87: =E87+M86 -> 91983 | O87: =IF($D87="","",IF(MONTH($D87)=O$7,$E87,0)) -> 0 | P87: =IF($D87="","",IF(MONTH($D87)=P$7,$E87,0)) -> 0 | Q87: =IF($D87="","",IF(MONTH($D87)=Q$7,$E87,0)) -> 0 | R87: =IF($D87="","",IF(MONTH($D87)=R$7,$E87,0)) -> 0 | S87: =IF($D87="","",IF(MONTH($D87)=S$7,$E87,0)) -> -1525 | T87: =IF($D87="","",IF(MONTH($D87)=T$7,$E87,0)) -> 0 | U87: =IF($D87="","",IF(MONTH($D87)=U$7,$E87,0)) -> 0 | V87: =IF($D87="","",IF(MONTH($D87)=V$7,$E87,0)) -> 0 | ... Z87: =IF($D87="","",IF(MONTH($D87)=Z$7,$E87,0)) -> 0
B88: =B87+2 -> 43962 | C88: -1047 | D88: 43964 | E88: -1047 | F88: Deposito bancário | G88: 8725799.6 | I88: Viagens | L88: =C88+L87 -> 90936 | M88: =E88+M87 -> 90936 | O88: =IF($D88="","",IF(MONTH($D88)=O$7,$E88,0)) -> 0 | P88: =IF($D88="","",IF(MONTH($D88)=P$7,$E88,0)) -> 0 | Q88: =IF($D88="","",IF(MONTH($D88)=Q$7,$E88,0)) -> 0 | R88: =IF($D88="","",IF(MONTH($D88)=R$7,$E88,0)) -> 0 | S88: =IF($D88="","",IF(MONTH($D88)=S$7,$E88,0)) -> -1047 | T88: =IF($D88="","",IF(MONTH($D88)=T$7,$E88,0)) -> 0 | U88: =IF($D88="","",IF(MONTH($D88)=U$7,$E88,0)) -> 0 | V88: =IF($D88="","",IF(MONTH($D88)=V$7,$E88,0)) -> 0 | ... Z88: =IF($D88="","",IF(MONTH($D88)=Z$7,$E88,0)) -> 0
B89: =B88+2 -> 43964 | C89: 12726 | D89: 43965 | E89: 12726 | F89: Deposito bancário | H89: 819413 | I89: Consultoria | J89: Cliente ABC | L89: =C89+L88 -> 103662 | M89: =E89+M88 -> 103662 | O89: =IF($D89="","",IF(MONTH($D89)=O$7,$E89,0)) -> 0 | P89: =IF($D89="","",IF(MONTH($D89)=P$7,$E89,0)) -> 0 | Q89: =IF($D89="","",IF(MONTH($D89)=Q$7,$E89,0)) -> 0 | R89: =IF($D89="","",IF(MONTH($D89)=R$7,$E89,0)) -> 0 | S89: =IF($D89="","",IF(MONTH($D89)=S$7,$E89,0)) -> 12726 | T89: =IF($D89="","",IF(MONTH($D89)=T$7,$E89,0)) -> 0 | U89: =IF($D89="","",IF(MONTH($D89)=U$7,$E89,0)) -> 0 | V89: =IF($D89="","",IF(MONTH($D89)=V$7,$E89,0)) -> 0 | ... Z89: =IF($D89="","",IF(MONTH($D89)=Z$7,$E89,0)) -> 0
B90: =B89+2 -> 43966 | C90: 13006 | D90: 43969 | E90: 13006 | F90: Deposito bancário | H90: 609575 | I90: Consultoria | J90: Cliente ABC | L90: =C90+L89 -> 116668 | M90: =E90+M89 -> 116668 | O90: =IF($D90="","",IF(MONTH($D90)=O$7,$E90,0)) -> 0 | P90: =IF($D90="","",IF(MONTH($D90)=P$7,$E90,0)) -> 0 | Q90: =IF($D90="","",IF(MONTH($D90)=Q$7,$E90,0)) -> 0 | R90: =IF($D90="","",IF(MONTH($D90)=R$7,$E90,0)) -> 0 | S90: =IF($D90="","",IF(MONTH($D90)=S$7,$E90,0)) -> 13006 | T90: =IF($D90="","",IF(MONTH($D90)=T$7,$E90,0)) -> 0 | U90: =IF($D90="","",IF(MONTH($D90)=U$7,$E90,0)) -> 0 | V90: =IF($D90="","",IF(MONTH($D90)=V$7,$E90,0)) -> 0 | ... Z90: =IF($D90="","",IF(MONTH($D90)=Z$7,$E90,0)) -> 0
B91: =B90+2 -> 43968 | C91: 5579 | D91: 43970 | E91: 5579 | F91: Dinheiro | H91: 172621 | I91: Consultoria | J91: Cliente ABC | L91: =C91+L90 -> 122247 | M91: =E91+M90 -> 122247 | O91: =IF($D91="","",IF(MONTH($D91)=O$7,$E91,0)) -> 0 | P91: =IF($D91="","",IF(MONTH($D91)=P$7,$E91,0)) -> 0 | Q91: =IF($D91="","",IF(MONTH($D91)=Q$7,$E91,0)) -> 0 | R91: =IF($D91="","",IF(MONTH($D91)=R$7,$E91,0)) -> 0 | S91: =IF($D91="","",IF(MONTH($D91)=S$7,$E91,0)) -> 5579 | T91: =IF($D91="","",IF(MONTH($D91)=T$7,$E91,0)) -> 0 | U91: =IF($D91="","",IF(MONTH($D91)=U$7,$E91,0)) -> 0 | V91: =IF($D91="","",IF(MONTH($D91)=V$7,$E91,0)) -> 0 | ... Z91: =IF($D91="","",IF(MONTH($D91)=Z$7,$E91,0)) -> 0
B92: =B91+2 -> 43970 | C92: -896 | D92: 43972 | E92: -896 | F92: Dinheiro | G92: 7737108 | I92: Propaganda | L92: =C92+L91 -> 121351 | M92: =E92+M91 -> 121351 | O92: =IF($D92="","",IF(MONTH($D92)=O$7,$E92,0)) -> 0 | P92: =IF($D92="","",IF(MONTH($D92)=P$7,$E92,0)) -> 0 | Q92: =IF($D92="","",IF(MONTH($D92)=Q$7,$E92,0)) -> 0 | R92: =IF($D92="","",IF(MONTH($D92)=R$7,$E92,0)) -> 0 | S92: =IF($D92="","",IF(MONTH($D92)=S$7,$E92,0)) -> -896 | T92: =IF($D92="","",IF(MONTH($D92)=T$7,$E92,0)) -> 0 | U92: =IF($D92="","",IF(MONTH($D92)=U$7,$E92,0)) -> 0 | V92: =IF($D92="","",IF(MONTH($D92)=V$7,$E92,0)) -> 0 | ... Z92: =IF($D92="","",IF(MONTH($D92)=Z$7,$E92,0)) -> 0
B93: =B92+2 -> 43972 | C93: -1319 | D93: 43973 | E93: -1319 | F93: Deposito bancário | G93: 7813161.2 | I93: Salários | L93: =C93+L92 -> 120032 | M93: =E93+M92 -> 120032 | O93: =IF($D93="","",IF(MONTH($D93)=O$7,$E93,0)) -> 0 | P93: =IF($D93="","",IF(MONTH($D93)=P$7,$E93,0)) -> 0 | Q93: =IF($D93="","",IF(MONTH($D93)=Q$7,$E93,0)) -> 0 | R93: =IF($D93="","",IF(MONTH($D93)=R$7,$E93,0)) -> 0 | S93: =IF($D93="","",IF(MONTH($D93)=S$7,$E93,0)) -> -1319 | T93: =IF($D93="","",IF(MONTH($D93)=T$7,$E93,0)) -> 0 | U93: =IF($D93="","",IF(MONTH($D93)=U$7,$E93,0)) -> 0 | V93: =IF($D93="","",IF(MONTH($D93)=V$7,$E93,0)) -> 0 | ... Z93: =IF($D93="","",IF(MONTH($D93)=Z$7,$E93,0)) -> 0
B94: =B93+2 -> 43974 | C94: 6978 | D94: 43976 | E94: 6978 | F94: Deposito bancário | H94: 489260 | I94: Licença de software | J94: Cliente ABC | L94: =C94+L93 -> 127010 | M94: =E94+M93 -> 127010 | O94: =IF($D94="","",IF(MONTH($D94)=O$7,$E94,0)) -> 0 | P94: =IF($D94="","",IF(MONTH($D94)=P$7,$E94,0)) -> 0 | Q94: =IF($D94="","",IF(MONTH($D94)=Q$7,$E94,0)) -> 0 | R94: =IF($D94="","",IF(MONTH($D94)=R$7,$E94,0)) -> 0 | S94: =IF($D94="","",IF(MONTH($D94)=S$7,$E94,0)) -> 6978 | T94: =IF($D94="","",IF(MONTH($D94)=T$7,$E94,0)) -> 0 | U94: =IF($D94="","",IF(MONTH($D94)=U$7,$E94,0)) -> 0 | V94: =IF($D94="","",IF(MONTH($D94)=V$7,$E94,0)) -> 0 | ... Z94: =IF($D94="","",IF(MONTH($D94)=Z$7,$E94,0)) -> 0
B95: =B94+2 -> 43976 | C95: 3579 | D95: 43978 | E95: 3579 | F95: Dinheiro | H95: 819413 | I95: Manutenção de Sistemas | J95: Cliente ABC | L95: =C95+L94 -> 130589 | M95: =E95+M94 -> 130589 | O95: =IF($D95="","",IF(MONTH($D95)=O$7,$E95,0)) -> 0 | P95: =IF($D95="","",IF(MONTH($D95)=P$7,$E95,0)) -> 0 | Q95: =IF($D95="","",IF(MONTH($D95)=Q$7,$E95,0)) -> 0 | R95: =IF($D95="","",IF(MONTH($D95)=R$7,$E95,0)) -> 0 | S95: =IF($D95="","",IF(MONTH($D95)=S$7,$E95,0)) -> 3579 | T95: =IF($D95="","",IF(MONTH($D95)=T$7,$E95,0)) -> 0 | U95: =IF($D95="","",IF(MONTH($D95)=U$7,$E95,0)) -> 0 | V95: =IF($D95="","",IF(MONTH($D95)=V$7,$E95,0)) -> 0 | ... Z95: =IF($D95="","",IF(MONTH($D95)=Z$7,$E95,0)) -> 0
B96: =B95+2 -> 43978 | C96: 5263 | D96: 43980 | E96: 5263 | F96: Dinheiro | H96: 609575 | I96: Licença de software | J96: Cliente ABC | L96: =C96+L95 -> 135852 | M96: =E96+M95 -> 135852 | O96: =IF($D96="","",IF(MONTH($D96)=O$7,$E96,0)) -> 0 | P96: =IF($D96="","",IF(MONTH($D96)=P$7,$E96,0)) -> 0 | Q96: =IF($D96="","",IF(MONTH($D96)=Q$7,$E96,0)) -> 0 | R96: =IF($D96="","",IF(MONTH($D96)=R$7,$E96,0)) -> 0 | S96: =IF($D96="","",IF(MONTH($D96)=S$7,$E96,0)) -> 5263 | T96: =IF($D96="","",IF(MONTH($D96)=T$7,$E96,0)) -> 0 | U96: =IF($D96="","",IF(MONTH($D96)=U$7,$E96,0)) -> 0 | V96: =IF($D96="","",IF(MONTH($D96)=V$7,$E96,0)) -> 0 | ... Z96: =IF($D96="","",IF(MONTH($D96)=Z$7,$E96,0)) -> 0
B97: =B96+2 -> 43980 | C97: 6435 | D97: 43982 | E97: 6435 | F97: Deposito bancário | H97: 172621 | I97: Licença de software | J97: Cliente XYZ | L97: =C97+L96 -> 142287 | M97: =E97+M96 -> 142287 | O97: =IF($D97="","",IF(MONTH($D97)=O$7,$E97,0)) -> 0 | P97: =IF($D97="","",IF(MONTH($D97)=P$7,$E97,0)) -> 0 | Q97: =IF($D97="","",IF(MONTH($D97)=Q$7,$E97,0)) -> 0 | R97: =IF($D97="","",IF(MONTH($D97)=R$7,$E97,0)) -> 0 | S97: =IF($D97="","",IF(MONTH($D97)=S$7,$E97,0)) -> 6435 | T97: =IF($D97="","",IF(MONTH($D97)=T$7,$E97,0)) -> 0 | U97: =IF($D97="","",IF(MONTH($D97)=U$7,$E97,0)) -> 0 | V97: =IF($D97="","",IF(MONTH($D97)=V$7,$E97,0)) -> 0 | ... Z97: =IF($D97="","",IF(MONTH($D97)=Z$7,$E97,0)) -> 0
B98: =B97+2 -> 43982 | C98: -1516 | D98: 43983 | E98: -1516 | F98: Deposito bancário | G98: 7737108 | I98: Pro-labore | L98: =C98+L97 -> 140771 | M98: =E98+M97 -> 140771 | O98: =IF($D98="","",IF(MONTH($D98)=O$7,$E98,0)) -> 0 | P98: =IF($D98="","",IF(MONTH($D98)=P$7,$E98,0)) -> 0 | Q98: =IF($D98="","",IF(MONTH($D98)=Q$7,$E98,0)) -> 0 | R98: =IF($D98="","",IF(MONTH($D98)=R$7,$E98,0)) -> 0 | S98: =IF($D98="","",IF(MONTH($D98)=S$7,$E98,0)) -> 0 | T98: =IF($D98="","",IF(MONTH($D98)=T$7,$E98,0)) -> -1516 | U98: =IF($D98="","",IF(MONTH($D98)=U$7,$E98,0)) -> 0 | V98: =IF($D98="","",IF(MONTH($D98)=V$7,$E98,0)) -> 0 | ... Z98: =IF($D98="","",IF(MONTH($D98)=Z$7,$E98,0)) -> 0
B99: =B98+2 -> 43984 | C99: -586 | D99: 43985 | E99: -586 | F99: Deposito bancário | G99: 7813161.2 | I99: Segurança | L99: =C99+L98 -> 140185 | M99: =E99+M98 -> 140185 | O99: =IF($D99="","",IF(MONTH($D99)=O$7,$E99,0)) -> 0 | P99: =IF($D99="","",IF(MONTH($D99)=P$7,$E99,0)) -> 0 | Q99: =IF($D99="","",IF(MONTH($D99)=Q$7,$E99,0)) -> 0 | R99: =IF($D99="","",IF(MONTH($D99)=R$7,$E99,0)) -> 0 | S99: =IF($D99="","",IF(MONTH($D99)=S$7,$E99,0)) -> 0 | T99: =IF($D99="","",IF(MONTH($D99)=T$7,$E99,0)) -> -586 | U99: =IF($D99="","",IF(MONTH($D99)=U$7,$E99,0)) -> 0 | V99: =IF($D99="","",IF(MONTH($D99)=V$7,$E99,0)) -> 0 | ... Z99: =IF($D99="","",IF(MONTH($D99)=Z$7,$E99,0)) -> 0
B100: =B99+2 -> 43986 | C100: 11353 | D100: 43988 | E100: 11353 | F100: Deposito bancário | H100: 489260 | I100: Licença de software | J100: Cliente ABC | L100: =C100+L99 -> 151538 | M100: =E100+M99 -> 151538 | O100: =IF($D100="","",IF(MONTH($D100)=O$7,$E100,0)) -> 0 | P100: =IF($D100="","",IF(MONTH($D100)=P$7,$E100,0)) -> 0 | Q100: =IF($D100="","",IF(MONTH($D100)=Q$7,$E100,0)) -> 0 | R100: =IF($D100="","",IF(MONTH($D100)=R$7,$E100,0)) -> 0 | S100: =IF($D100="","",IF(MONTH($D100)=S$7,$E100,0)) -> 0 | T100: =IF($D100="","",IF(MONTH($D100)=T$7,$E100,0)) -> 11353 | U100: =IF($D100="","",IF(MONTH($D100)=U$7,$E100,0)) -> 0 | V100: =IF($D100="","",IF(MONTH($D100)=V$7,$E100,0)) -> 0 | ... Z100: =IF($D100="","",IF(MONTH($D100)=Z$7,$E100,0)) -> 0
B101: =B100+2 -> 43988 | C101: 13562 | D101: 43990 | E101: 13562 | F101: Deposito bancário | H101: 819413 | I101: Licença de software | J101: Cliente ABC | L101: =C101+L100 -> 165100 | M101: =E101+M100 -> 165100 | O101: =IF($D101="","",IF(MONTH($D101)=O$7,$E101,0)) -> 0 | P101: =IF($D101="","",IF(MONTH($D101)=P$7,$E101,0)) -> 0 | Q101: =IF($D101="","",IF(MONTH($D101)=Q$7,$E101,0)) -> 0 | R101: =IF($D101="","",IF(MONTH($D101)=R$7,$E101,0)) -> 0 | S101: =IF($D101="","",IF(MONTH($D101)=S$7,$E101,0)) -> 0 | T101: =IF($D101="","",IF(MONTH($D101)=T$7,$E101,0)) -> 13562 | U101: =IF($D101="","",IF(MONTH($D101)=U$7,$E101,0)) -> 0 | V101: =IF($D101="","",IF(MONTH($D101)=V$7,$E101,0)) -> 0 | ... Z101: =IF($D101="","",IF(MONTH($D101)=Z$7,$E101,0)) -> 0
B102: =B101+2 -> 43990 | C102: 7775 | D102: 43992 | E102: 7775 | F102: Cheque | H102: 609575 | I102: Consultoria | J102: Cliente ABC | L102: =C102+L101 -> 172875 | M102: =E102+M101 -> 172875 | O102: =IF($D102="","",IF(MONTH($D102)=O$7,$E102,0)) -> 0 | P102: =IF($D102="","",IF(MONTH($D102)=P$7,$E102,0)) -> 0 | Q102: =IF($D102="","",IF(MONTH($D102)=Q$7,$E102,0)) -> 0 | R102: =IF($D102="","",IF(MONTH($D102)=R$7,$E102,0)) -> 0 | S102: =IF($D102="","",IF(MONTH($D102)=S$7,$E102,0)) -> 0 | T102: =IF($D102="","",IF(MONTH($D102)=T$7,$E102,0)) -> 7775 | U102: =IF($D102="","",IF(MONTH($D102)=U$7,$E102,0)) -> 0 | V102: =IF($D102="","",IF(MONTH($D102)=V$7,$E102,0)) -> 0 | ... Z102: =IF($D102="","",IF(MONTH($D102)=Z$7,$E102,0)) -> 0
...

Sheet Fluxo_Diário_DB
B2: Data de Reg. | C2: Valor | D2: Acum. | F2: Data Efet. | G2: Valor | H2: Acum. | J2: Real Mil | K2: 1000 | L2: Jan | M2: Fev | N2: Mar | O2: Abr | P2: Mai | Q2: Jun | R2: Jul | S2: Ago | T2: Set | U2: Out | V2: Nov | W2: Dez
B3: =Fluxo_Diário!B9 -> 43830 | C3: =SUMIF(Fluxo_Diário!$B$9:$B$1048576,Fluxo_Diário_DB!B3,Fluxo_Diário!$C$9:$C$1048576) -> 0 | D3: =C3 -> 0 | F3: =B3 -> 43830 | G3: =SUMIF(Fluxo_Diário!$D$9:$D$1048576,Fluxo_Diário_DB!B3,Fluxo_Diário!$E$9:$E$1048576) -> 0 | H3: =G3 -> 0 | J3: Receitas Operacionais | K3: Proj | L3: =Fluxo_Projetado!C55/$K$2 -> 11.68425 | M3: =Fluxo_Projetado!D55/$K$2 -> 28.4895 | N3: =Fluxo_Projetado!E55/$K$2 -> 28.79475 | O3: =Fluxo_Projetado!F55/$K$2 -> 29.8745 | P3: =Fluxo_Projetado!G55/$K$2 -> 29.66875 | Q3: =Fluxo_Projetado!H55/$K$2 -> 29.83025 | R3: =Fluxo_Projetado!I55/$K$2 -> 29.662 | S3: =Fluxo_Projetado!J55/$K$2 -> 30.19775 | ... W3: =Fluxo_Projetado!N55/$K$2 -> 28.70725
B4: =B3+1 -> 43831 | C4: =SUMIF(Fluxo_Diário!$B$9:$B$1048576,Fluxo_Diário_DB!B4,Fluxo_Diário!$C$9:$C$1048576) -> 0 | D4: =C4+D3 -> 0 | F4: =B4 -> 43831 | G4: =SUMIF(Fluxo_Diário!$D$9:$D$1048576,Fluxo_Diário_DB!B4,Fluxo_Diário!$E$9:$E$1048576) -> 0 | H4: =G4+H3 -> 0 | L4: =L3 -> 11.68425 | M4: =M3+L4 -> 40.17375 | N4: =N3+M4 -> 68.9685 | O4: =O3+N4 -> 98.843 | P4: =P3+O4 -> 128.51175 | Q4: =Q3+P4 -> 158.342 | R4: =R3+Q4 -> 188.004 | S4: =S3+R4 -> 218.20175 | T4: =T3+S4 -> 248.31025 | ... W4: =W3+V4 -> 335.6025
B5: =B4+1 -> 43832 | C5: =SUMIF(Fluxo_Diário!$B$9:$B$1048576,Fluxo_Diário_DB!B5,Fluxo_Diário!$C$9:$C$1048576) -> 0 | D5: =C5+D4 -> 0 | F5: =B5 -> 43832 | G5: =SUMIF(Fluxo_Diário!$D$9:$D$1048576,Fluxo_Diário_DB!B5,Fluxo_Diário!$E$9:$E$1048576) -> 0 | H5: =G5+H4 -> 0 | K5: Real | L5: =Fluxo_Realizado!C55/$K$2 -> 56.325 | M5: =Fluxo_Realizado!D55/$K$2 -> 19.889 | N5: =Fluxo_Realizado!E55/$K$2 -> 62.947 | O5: =Fluxo_Realizado!F55/$K$2 -> 31.838 | P5: =Fluxo_Realizado!G55/$K$2 -> 53.566 | Q5: =Fluxo_Realizado!H55/$K$2 -> 91.372 | R5: =Fluxo_Realizado!I55/$K$2 -> 77.493 | S5: =Fluxo_Realizado!J55/$K$2 -> 0 | ... W5: =Fluxo_Realizado!N55/$K$2 -> 0
B6: =B5+1 -> 43833 | C6: =SUMIF(Fluxo_Diário!$B$9:$B$1048576,Fluxo_Diário_DB!B6,Fluxo_Diário!$C$9:$C$1048576) -> 1150 | D6: =C6+D5 -> 1150 | F6: =B6 -> 43833 | G6: =SUMIF(Fluxo_Diário!$D$9:$D$1048576,Fluxo_Diário_DB!B6,Fluxo_Diário!$E$9:$E$1048576) -> -50 | H6: =G6+H5 -> -50 | L6: =L5 -> 56.325 | M6: =M5+L6 -> 76.214 | N6: =N5+M6 -> 139.161 | O6: =O5+N6 -> 170.999 | P6: =P5+O6 -> 224.565 | Q6: =Q5+P6 -> 315.937 | R6: =R5+Q6 -> 393.43 | S6: =S5+R6 -> 393.43 | T6: =T5+S6 -> 393.43 | ... W6: =W5+V6 -> 393.43
B7: =B6+1 -> 43834 | C7: =SUMIF(Fluxo_Diário!$B$9:$B$1048576,Fluxo_Diário_DB!B7,Fluxo_Diário!$C$9:$C$1048576) -> -20 | D7: =C7+D6 -> 1130 | F7: =B7 -> 43834 | G7: =SUMIF(Fluxo_Diário!$D$9:$D$1048576,Fluxo_Diário_DB!B7,Fluxo_Diário!$E$9:$E$1048576) -> 1180 | H7: =G7+H6 -> 1130 | K7: % | L7: =L5/L3 -> 4.8205918 | M7: =M5/M3 -> 0.69811685 | N7: =N5/N3 -> 2.1860582 | O7: =O5/O3 -> 1.0657249 | P7: =P5/P3 -> 1.8054687 | Q7: =Q5/Q3 -> 3.0630652 | R7: =R5/R3 -> 2.6125346 | S7: =S5/S3 -> 0 | ... W7: =W5/W3 -> 0
B8: =B7+1 -> 43835 | C8: =SUMIF(Fluxo_Diário!$B$9:$B$1048576,Fluxo_Diário_DB!B8,Fluxo_Diário!$C$9:$C$1048576) -> 6300 | D8: =C8+D7 -> 7430 | F8: =B8 -> 43835 | G8: =SUMIF(Fluxo_Diário!$D$9:$D$1048576,Fluxo_Diário_DB!B8,Fluxo_Diário!$E$9:$E$1048576) -> 0 | H8: =G8+H7 -> 1130
B9: =B8+1 -> 43836 | C9: =SUMIF(Fluxo_Diário!$B$9:$B$1048576,Fluxo_Diário_DB!B9,Fluxo_Diário!$C$9:$C$1048576) -> 0 | D9: =C9+D8 -> 7430 | F9: =B9 -> 43836 | G9: =SUMIF(Fluxo_Diário!$D$9:$D$1048576,Fluxo_Diário_DB!B9,Fluxo_Diário!$E$9:$E$1048576) -> 0 | H9: =G9+H8 -> 1130 | J9: Despesas Fixas | K9: Proj | L9: =-Fluxo_Projetado!C56/$K$2 -> 11.19 | M9: =-Fluxo_Projetado!D56/$K$2 -> 11.19 | N9: =-Fluxo_Projetado!E56/$K$2 -> 11.19 | O9: =-Fluxo_Projetado!F56/$K$2 -> 11.19 | P9: =-Fluxo_Projetado!G56/$K$2 -> 11.19 | Q9: =-Fluxo_Projetado!H56/$K$2 -> 11.19 | R9: =-Fluxo_Projetado!I56/$K$2 -> 11.19 | S9: =-Fluxo_Projetado!J56/$K$2 -> 11.19 | ... W9: =-Fluxo_Projetado!N56/$K$2 -> 11.19
B10: =B9+1 -> 43837 | C10: =SUMIF(Fluxo_Diário!$B$9:$B$1048576,Fluxo_Diário_DB!B10,Fluxo_Diário!$C$9:$C$1048576) -> -2505 | D10: =C10+D9 -> 4925 | F10: =B10 -> 43837 | G10: =SUMIF(Fluxo_Diário!$D$9:$D$1048576,Fluxo_Diário_DB!B10,Fluxo_Diário!$E$9:$E$1048576) -> -2505 | H10: =G10+H9 -> -1375 | L10: =L9 -> 11.19 | M10: =M9+L10 -> 22.38 | N10: =N9+M10 -> 33.57 | O10: =O9+N10 -> 44.76 | P10: =P9+O10 -> 55.95 | Q10: =Q9+P10 -> 67.14 | R10: =R9+Q10 -> 78.33 | S10: =S9+R10 -> 89.52 | T10: =T9+S10 -> 100.71 | ... W10: =W9+V10 -> 134.28
B11: =B10+1 -> 43838 | C11: =SUMIF(Fluxo_Diário!$B$9:$B$1048576,Fluxo_Diário_DB!B11,Fluxo_Diário!$C$9:$C$1048576) -> -500 | D11: =C11+D10 -> 4425 | F11: =B11 -> 43838 | G11: =SUMIF(Fluxo_Diário!$D$9:$D$1048576,Fluxo_Diário_DB!B11,Fluxo_Diário!$E$9:$E$1048576) -> 0 | H11: =G11+H10 -> -1375 | K11: Real | L11: =-Fluxo_Realizado!C56/$K$2 -> 14.82 | M11: =-Fluxo_Realizado!D56/$K$2 -> 10.767 | N11: =-Fluxo_Realizado!E56/$K$2 -> 11.236 | O11: =-Fluxo_Realizado!F56/$K$2 -> 13.123 | P11: =-Fluxo_Realizado!G56/$K$2 -> 11.17 | Q11: =-Fluxo_Realizado!H56/$K$2 -> 7.145 | R11: =-Fluxo_Realizado!I56/$K$2 -> 6.506 | S11: =-Fluxo_Realizado!J56/$K$2 -> 1.355 | ... W11: =-Fluxo_Realizado!N56/$K$2 -> 0
B12: =B11+1 -> 43839 | C12: =SUMIF(Fluxo_Diário!$B$9:$B$1048576,Fluxo_Diário_DB!B12,Fluxo_Diário!$C$9:$C$1048576) -> 0 | D12: =C12+D11 -> 4425 | F12: =B12 -> 43839 | G12: =SUMIF(Fluxo_Diário!$D$9:$D$1048576,Fluxo_Diário_DB!B12,Fluxo_Diário!$E$9:$E$1048576) -> 0 | H12: =G12+H11 -> -1375 | L12: =L11 -> 14.82 | M12: =M11+L12 -> 25.587 | N12: =N11+M12 -> 36.823 | O12: =O11+N12 -> 49.946 | P12: =P11+O12 -> 61.116 | Q12: =Q11+P12 -> 68.261 | R12: =R11+Q12 -> 74.767 | S12: =S11+R12 -> 76.122 | T12: =T11+S12 -> 76.122 | ... W12: =W11+V12 -> 76.122
B13: =B12+1 -> 43840 | C13: =SUMIF(Fluxo_Diário!$B$9:$B$1048576,Fluxo_Diário_DB!B13,Fluxo_Diário!$C$9:$C$1048576) -> -2209 | D13: =C13+D12 -> 2216 | F13: =B13 -> 43840 | G13: =SUMIF(Fluxo_Diário!$D$9:$D$1048576,Fluxo_Diário_DB!B13,Fluxo_Diário!$E$9:$E$1048576) -> 6300 | H13: =G13+H12 -> 4925 | K13: % | L13: =L11/L9 -> 1.3243968 | M13: =M11/M9 -> 0.96219839 | N13: =N11/N9 -> 1.0041108 | O13: =O11/O9 -> 1.1727435 | P13: =P11/P9 -> 0.99821269 | Q13: =Q11/Q9 -> 0.63851653 | R13: =R11/R9 -> 0.58141197 | S13: =S11/S9 -> 0.12109026 | ... W13: =W11/W9 -> 0
B14: =B13+1 -> 43841 | C14: =SUMIF(Fluxo_Diário!$B$9:$B$1048576,Fluxo_Diário_DB!B14,Fluxo_Diário!$C$9:$C$1048576) -> 0 | D14: =C14+D13 -> 2216 | F14: =B14 -> 43841 | G14: =SUMIF(Fluxo_Diário!$D$9:$D$1048576,Fluxo_Diário_DB!B14,Fluxo_Diário!$E$9:$E$1048576) -> -2209 | H14: =G14+H13 -> 2716
B15: =B14+1 -> 43842 | C15: =SUMIF(Fluxo_Diário!$B$9:$B$1048576,Fluxo_Diário_DB!B15,Fluxo_Diário!$C$9:$C$1048576) -> -2713 | D15: =C15+D14 -> -497 | F15: =B15 -> 43842 | G15: =SUMIF(Fluxo_Diário!$D$9:$D$1048576,Fluxo_Diário_DB!B15,Fluxo_Diário!$E$9:$E$1048576) -> 0 | H15: =G15+H14 -> 2716 | J15: Despesas Variáveis | K15: Proj | L15: =-Fluxo_Projetado!C57/$K$2 -> 1.43385 | M15: =-Fluxo_Projetado!D57/$K$2 -> 6.1152541 | N15: =-Fluxo_Projetado!E57/$K$2 -> 6.1312918 | O15: =-Fluxo_Projetado!F57/$K$2 -> 6.2304044 | P15: =-Fluxo_Projetado!G57/$K$2 -> 6.3490876 | Q15: =-Fluxo_Projetado!H57/$K$2 -> 6.3594709 | R15: =-Fluxo_Projetado!I57/$K$2 -> 6.2761143 | S15: =-Fluxo_Projetado!J57/$K$2 -> 6.5318099 | ... W15: =-Fluxo_Projetado!N57/$K$2 -> 6.1495798
B16: =B15+1 -> 43843 | C16: =SUMIF(Fluxo_Diário!$B$9:$B$1048576,Fluxo_Diário_DB!B16,Fluxo_Diário!$C$9:$C$1048576) -> 0 | D16: =C16+D15 -> -497 | F16: =B16 -> 43843 | G16: =SUMIF(Fluxo_Diário!$D$9:$D$1048576,Fluxo_Diário_DB!B16,Fluxo_Diário!$E$9:$E$1048576) -> 0 | H16: =G16+H15 -> 2716 | L16: =L15 -> 1.43385 | M16: =M15+L16 -> 7.5491041 | N16: =N15+M16 -> 13.680396 | O16: =O15+N16 -> 19.9108 | P16: =P15+O16 -> 26.259888 | Q16: =Q15+P16 -> 32.619359 | R16: =R15+Q16 -> 38.895473 | S16: =S15+R16 -> 45.427283 | T16: =T15+S16 -> 51.787736 | ... W16: =W15+V16 -> 70.416517
B17: =B16+1 -> 43844 | C17: =SUMIF(Fluxo_Diário!$B$9:$B$1048576,Fluxo_Diário_DB!B17,Fluxo_Diário!$C$9:$C$1048576) -> -2946 | D17: =C17+D16 -> -3443 | F17: =B17 -> 43844 | G17: =SUMIF(Fluxo_Diário!$D$9:$D$1048576,Fluxo_Diário_DB!B17,Fluxo_Diário!$E$9:$E$1048576) -> 0 | H17: =G17+H16 -> 2716 | K17: Real | L17: =-Fluxo_Realizado!C57/$K$2 -> 2.713 | M17: =-Fluxo_Realizado!D57/$K$2 -> 7.731 | N17: =-Fluxo_Realizado!E57/$K$2 -> 2.302 | O17: =-Fluxo_Realizado!F57/$K$2 -> 5.563 | P17: =-Fluxo_Realizado!G57/$K$2 -> 2.853 | Q17: =-Fluxo_Realizado!H57/$K$2 -> 2.396 | R17: =-Fluxo_Realizado!I57/$K$2 -> 0 | S17: =-Fluxo_Realizado!J57/$K$2 -> 0 | ... W17: =-Fluxo_Realizado!N57/$K$2 -> 0
B18: =B17+1 -> 43845 | C18: =SUMIF(Fluxo_Diário!$B$9:$B$1048576,Fluxo_Diário_DB!B18,Fluxo_Diário!$C$9:$C$1048576) -> 0 | D18: =C18+D17 -> -3443 | F18: =B18 -> 43845 | G18: =SUMIF(Fluxo_Diário!$D$9:$D$1048576,Fluxo_Diário_DB!B18,Fluxo_Diário!$E$9:$E$1048576) -> -5659 | H18: =G18+H17 -> -2943 | L18: =L17 -> 2.713 | M18: =M17+L18 -> 10.444 | N18: =N17+M18 -> 12.746 | O18: =O17+N18 -> 18.309 | P18: =P17+O18 -> 21.162 | Q18: =Q17+P18 -> 23.558 | R18: =R17+Q18 -> 23.558 | S18: =S17+R18 -> 23.558 | T18: =T17+S18 -> 23.558 | ... W18: =W17+V18 -> 23.558
B19: =B18+1 -> 43846 | C19: =SUMIF(Fluxo_Diário!$B$9:$B$1048576,Fluxo_Diário_DB!B19,Fluxo_Diário!$C$9:$C$1048576) -> -3164 | D19: =C19+D18 -> -6607 | F19: =B19 -> 43846 | G19: =SUMIF(Fluxo_Diário!$D$9:$D$1048576,Fluxo_Diário_DB!B19,Fluxo_Diário!$E$9:$E$1048576) -> 0 | H19: =G19+H18 -> -2943 | K19: % | L19: =L17/L15 -> 1.8921087 | M19: =M17/M15 -> 1.2642157 | N19: =N17/N15 -> 0.37545106 | O19: =O17/O15 -> 0.89287944 | P19: =P17/P15 -> 0.4493559 | Q19: =Q17/Q15 -> 0.3767609 | R19: =R17/R15 -> 0 | S19: =S17/S15 -> 0 | ... W19: =W17/W15 -> 0
B20: =B19+1 -> 43847 | C20: =SUMIF(Fluxo_Diário!$B$9:$B$1048576,Fluxo_Diário_DB!B20,Fluxo_Diário!$C$9:$C$1048576) -> 0 | D20: =C20+D19 -> -6607 | F20: =B20 -> 43847 | G20: =SUMIF(Fluxo_Diário!$D$9:$D$1048576,Fluxo_Diário_DB!B20,Fluxo_Diário!$E$9:$E$1048576) -> 0 | H20: =G20+H19 -> -2943
B21: =B20+1 -> 43848 | C21: =SUMIF(Fluxo_Diário!$B$9:$B$1048576,Fluxo_Diário_DB!B21,Fluxo_Diário!$C$9:$C$1048576) -> -2037 | D21: =C21+D20 -> -8644 | F21: =B21 -> 43848 | G21: =SUMIF(Fluxo_Diário!$D$9:$D$1048576,Fluxo_Diário_DB!B21,Fluxo_Diário!$E$9:$E$1048576) -> 0 | H21: =G21+H20 -> -2943 | J21: Margem de Contribuição | K21: Proj | L21: =Fluxo_Projetado!C70 -> 0.87728352 | M21: =Fluxo_Projetado!D70 -> 0.7853506 | N21: =Fluxo_Projetado!E70 -> 0.78706911 | O21: =Fluxo_Projetado!F70 -> 0.79144741 | P21: =Fluxo_Projetado!G70 -> 0.78600084 | Q21: =Fluxo_Projetado!H70 -> 0.78681134 | R21: =Fluxo_Projetado!I70 -> 0.7884123 | S21: =Fluxo_Projetado!J70 -> 0.78369879 | ... W21: =Fluxo_Projetado!N70 -> 0.78578304
B22: =B21+1 -> 43849 | C22: =SUMIF(Fluxo_Diário!$B$9:$B$1048576,Fluxo_Diário_DB!B22,Fluxo_Diário!$C$9:$C$1048576) -> 0 | D22: =C22+D21 -> -8644 | F22: =B22 -> 43849 | G22: =SUMIF(Fluxo_Diário!$D$9:$D$1048576,Fluxo_Diário_DB!B22,Fluxo_Diário!$E$9:$E$1048576) -> -5201 | H22: =G22+H21 -> -8144
B23: =B22+1 -> 43850 | C23: =SUMIF(Fluxo_Diário!$B$9:$B$1048576,Fluxo_Diário_DB!B23,Fluxo_Diário!$C$9:$C$1048576) -> 14762 | D23: =C23+D22 -> 6118 | F23: =B23 -> 43850 | G23: =SUMIF(Fluxo_Diário!$D$9:$D$1048576,Fluxo_Diário_DB!B23,Fluxo_Diário!$E$9:$E$1048576) -> 0 | H23: =G23+H22 -> -8144 | K23: Real | L23: =IFERROR(Fluxo_Realizado!C70,"") -> 0.95183311 | M23: =IFERROR(Fluxo_Realizado!D70,"") -> 0.61129267 | N23: =IFERROR(Fluxo_Realizado!E70,"") -> 0.96342955 | O23: =IFERROR(Fluxo_Realizado!F70,"") -> 0.82527169 | P23: =IFERROR(Fluxo_Realizado!G70,"") -> 0.9467386 | Q23: =IFERROR(Fluxo_Realizado!H70,"") -> 0.97377752 | R23: =IFERROR(Fluxo_Realizado!I70,"") -> 1 | S23: =IFERROR(Fluxo_Realizado!J70,"") | ... W23: =IFERROR(Fluxo_Realizado!N70,"")
B24: =B23+1 -> 43851 | C24: =SUMIF(Fluxo_Diário!$B$9:$B$1048576,Fluxo_Diário_DB!B24,Fluxo_Diário!$C$9:$C$1048576) -> 0 | D24: =C24+D23 -> 6118 | F24: =B24 -> 43851 | G24: =SUMIF(Fluxo_Diário!$D$9:$D$1048576,Fluxo_Diário_DB!B24,Fluxo_Diário!$E$9:$E$1048576) -> 0 | H24: =G24+H23 -> -8144
B25: =B24+1 -> 43852 | C25: =SUMIF(Fluxo_Diário!$B$9:$B$1048576,Fluxo_Diário_DB!B25,Fluxo_Diário!$C$9:$C$1048576) -> 11949 | D25: =C25+D24 -> 18067 | F25: =B25 -> 43852 | G25: =SUMIF(Fluxo_Diário!$D$9:$D$1048576,Fluxo_Diário_DB!B25,Fluxo_Diário!$E$9:$E$1048576) -> 0 | H25: =G25+H24 -> -8144
B26: =B25+1 -> 43853 | C26: =SUMIF(Fluxo_Diário!$B$9:$B$1048576,Fluxo_Diário_DB!B26,Fluxo_Diário!$C$9:$C$1048576) -> 0 | D26: =C26+D25 -> 18067 | F26: =B26 -> 43853 | G26: =SUMIF(Fluxo_Diário!$D$9:$D$1048576,Fluxo_Diário_DB!B26,Fluxo_Diário!$E$9:$E$1048576) -> 26711 | H26: =G26+H25 -> 18567 | J26: Margem de Lucro | K26: Proj | L26: =Fluxo_Projetado!C71 -> 0.12271648 | M26: =Fluxo_Projetado!D71 -> 0.2146494 | N26: =Fluxo_Projetado!E71 -> 0.21293089 | O26: =Fluxo_Projetado!F71 -> 0.20855259 | P26: =Fluxo_Projetado!G71 -> 0.21399916 | Q26: =Fluxo_Projetado!H71 -> 0.21318866 | R26: =Fluxo_Projetado!I71 -> 0.2115877 | S26: =Fluxo_Projetado!J71 -> 0.21630121 | ... W26: =Fluxo_Projetado!N71 -> 0.21421696
B27: =B26+1 -> 43854 | C27: =SUMIF(Fluxo_Diário!$B$9:$B$1048576,Fluxo_Diário_DB!B27,Fluxo_Diário!$C$9:$C$1048576) -> 14655 | D27: =C27+D26 -> 32722 | F27: =B27 -> 43854 | G27: =SUMIF(Fluxo_Diário!$D$9:$D$1048576,Fluxo_Diário_DB!B27,Fluxo_Diário!$E$9:$E$1048576) -> 0 | H27: =G27+H26 -> 18567
B28: =B27+1 -> 43855 | C28: =SUMIF(Fluxo_Diário!$B$9:$B$1048576,Fluxo_Diário_DB!B28,Fluxo_Diário!$C$9:$C$1048576) -> 0 | D28: =C28+D27 -> 32722 | F28: =B28 -> 43855 | G28: =SUMIF(Fluxo_Diário!$D$9:$D$1048576,Fluxo_Diário_DB!B28,Fluxo_Diário!$E$9:$E$1048576) -> 0 | H28: =G28+H27 -> 18567 | K28: Real | L28: =IFERROR(Fluxo_Realizado!C71,"") -> 0.048166889 | M28: =IFERROR(Fluxo_Realizado!D71,"") -> 0.38870733 | N28: =IFERROR(Fluxo_Realizado!E71,"") -> 0.036570448 | O28: =IFERROR(Fluxo_Realizado!F71,"") -> 0.17472831 | P28: =IFERROR(Fluxo_Realizado!G71,"") -> 0.053261397 | Q28: =IFERROR(Fluxo_Realizado!H71,"") -> 0.026222475 | R28: =IFERROR(Fluxo_Realizado!I71,"") -> 0 | S28: =IFERROR(Fluxo_Realizado!J71,"") | ... W28: =IFERROR(Fluxo_Realizado!N71,"")
B29: =B28+1 -> 43856 | C29: =SUMIF(Fluxo_Diário!$B$9:$B$1048576,Fluxo_Diário_DB!B29,Fluxo_Diário!$C$9:$C$1048576) -> 7459 | D29: =C29+D28 -> 40181 | F29: =B29 -> 43856 | G29: =SUMIF(Fluxo_Diário!$D$9:$D$1048576,Fluxo_Diário_DB!B29,Fluxo_Diário!$E$9:$E$1048576) -> 0 | H29: =G29+H28 -> 18567
B30: =B29+1 -> 43857 | C30: =SUMIF(Fluxo_Diário!$B$9:$B$1048576,Fluxo_Diário_DB!B30,Fluxo_Diário!$C$9:$C$1048576) -> 0 | D30: =C30+D29 -> 40181 | F30: =B30 -> 43857 | G30: =SUMIF(Fluxo_Diário!$D$9:$D$1048576,Fluxo_Diário_DB!B30,Fluxo_Diário!$E$9:$E$1048576) -> 14655 | H30: =G30+H29 -> 33222
B31: =B30+1 -> 43858 | C31: =SUMIF(Fluxo_Diário!$B$9:$B$1048576,Fluxo_Diário_DB!B31,Fluxo_Diário!$C$9:$C$1048576) -> -1889 | D31: =C31+D30 -> 38292 | F31: =B31 -> 43858 | G31: =SUMIF(Fluxo_Diário!$D$9:$D$1048576,Fluxo_Diário_DB!B31,Fluxo_Diário!$E$9:$E$1048576) -> 7459 | H31: =G31+H30 -> 40681 | J31: Ponto de Equilíbrio | K31: Proj | L31: =Fluxo_Projetado!C72/$K$2 -> 12.755283 | M31: =Fluxo_Projetado!D72/$K$2 -> 14.248413 | N31: =Fluxo_Projetado!E72/$K$2 -> 14.217303 | O31: =Fluxo_Projetado!F72/$K$2 -> 14.138653 | P31: =Fluxo_Projetado!G72/$K$2 -> 14.236626 | Q31: =Fluxo_Projetado!H72/$K$2 -> 14.221961 | R31: =Fluxo_Projetado!I72/$K$2 -> 14.193081 | S31: =Fluxo_Projetado!J72/$K$2 -> 14.278445 | ... W31: =Fluxo_Projetado!N72/$K$2 -> 14.240572
B32: =B31+1 -> 43859 | C32: =SUMIF(Fluxo_Diário!$B$9:$B$1048576,Fluxo_Diário_DB!B32,Fluxo_Diário!$C$9:$C$1048576) -> 0 | D32: =C32+D31 -> 38292 | F32: =B32 -> 43859 | G32: =SUMIF(Fluxo_Diário!$D$9:$D$1048576,Fluxo_Diário_DB!B32,Fluxo_Diário!$E$9:$E$1048576) -> 0 | H32: =G32+H31 -> 40681
B33: =B32+1 -> 43860 | C33: =SUMIF(Fluxo_Diário!$B$9:$B$1048576,Fluxo_Diário_DB!B33,Fluxo_Diário!$C$9:$C$1048576) -> -3004 | D33: =C33+D32 -> 35288 | F33: =B33 -> 43860 | G33: =SUMIF(Fluxo_Diário!$D$9:$D$1048576,Fluxo_Diário_DB!B33,Fluxo_Diário!$E$9:$E$1048576) -> 0 | H33: =G33+H32 -> 40681 | K33: Real | L33: =IFERROR(Fluxo_Realizado!C72/$K$2,"") -> 15.569956 | M33: =IFERROR(Fluxo_Realizado!D72/$K$2,"") -> 17.613494 | N33: =IFERROR(Fluxo_Realizado!E72/$K$2,"") -> 11.662503 | O33: =IFERROR(Fluxo_Realizado!F72/$K$2,"") -> 15.90143 | P33: =IFERROR(Fluxo_Realizado!G72/$K$2,"") -> 11.798399 | Q33: =IFERROR(Fluxo_Realizado!H72/$K$2,"") -> 7.3374049 | R33: =IFERROR(Fluxo_Realizado!I72/$K$2,"") -> 6.506 | S33: =IFERROR(Fluxo_Realizado!J72/$K$2,"") | ... W33: =IFERROR(Fluxo_Realizado!N72/$K$2,"")
B34: =B33+1 -> 43861 | C34: =SUMIF(Fluxo_Diário!$B$9:$B$1048576,Fluxo_Diário_DB!B34,Fluxo_Diário!$C$9:$C$1048576) -> 0 | D34: =C34+D33 -> 35288 | F34: =B34 -> 43861 | G34: =SUMIF(Fluxo_Diário!$D$9:$D$1048576,Fluxo_Diário_DB!B34,Fluxo_Diário!$E$9:$E$1048576) -> -1889 | H34: =G34+H33 -> 38792
B35: =B34+1 -> 43862 | C35: =SUMIF(Fluxo_Diário!$B$9:$B$1048576,Fluxo_Diário_DB!B35,Fluxo_Diário!$C$9:$C$1048576) -> -1619 | D35: =C35+D34 -> 33669 | F35: =B35 -> 43862 | G35: =SUMIF(Fluxo_Diário!$D$9:$D$1048576,Fluxo_Diário_DB!B35,Fluxo_Diário!$E$9:$E$1048576) -> -3004 | H35: =G35+H34 -> 35788
B36: =B35+1 -> 43863 | C36: =SUMIF(Fluxo_Diário!$B$9:$B$1048576,Fluxo_Diário_DB!B36,Fluxo_Diário!$C$9:$C$1048576) -> 0 | D36: =C36+D35 -> 33669 | F36: =B36 -> 43863 | G36: =SUMIF(Fluxo_Diário!$D$9:$D$1048576,Fluxo_Diário_DB!B36,Fluxo_Diário!$E$9:$E$1048576) -> -1619 | H36: =G36+H35 -> 34169
B37: =B36+1 -> 43864 | C37: =SUMIF(Fluxo_Diário!$B$9:$B$1048576,Fluxo_Diário_DB!B37,Fluxo_Diário!$C$9:$C$1048576) -> -2306 | D37: =C37+D36 -> 31363 | F37: =B37 -> 43864 | G37: =SUMIF(Fluxo_Diário!$D$9:$D$1048576,Fluxo_Diário_DB!B37,Fluxo_Diário!$E$9:$E$1048576) -> 0 | H37: =G37+H36 -> 34169
B38: =B37+1 -> 43865 | C38: =SUMIF(Fluxo_Diário!$B$9:$B$1048576,Fluxo_Diário_DB!B38,Fluxo_Diário!$C$9:$C$1048576) -> 0 | D38: =C38+D37 -> 31363 | F38: =B38 -> 43865 | G38: =SUMIF(Fluxo_Diário!$D$9:$D$1048576,Fluxo_Diário_DB!B38,Fluxo_Diário!$E$9:$E$1048576) -> 0 | H38: =G38+H37 -> 34169
B39: =B38+1 -> 43866 | C39: =SUMIF(Fluxo_Diário!$B$9:$B$1048576,Fluxo_Diário_DB!B39,Fluxo_Diário!$C$9:$C$1048576) -> -474 | D39: =C39+D38 -> 30889 | F39: =B39 -> 43866 | G39: =SUMIF(Fluxo_Diário!$D$9:$D$1048576,Fluxo_Diário_DB!B39,Fluxo_Diário!$E$9:$E$1048576) -> -2306 | H39: =G39+H38 -> 31863
B40: =B39+1 -> 43867 | C40: =SUMIF(Fluxo_Diário!$B$9:$B$1048576,Fluxo_Diário_DB!B40,Fluxo_Diário!$C$9:$C$1048576) -> 0 | D40: =C40+D39 -> 30889 | F40: =B40 -> 43867 | G40: =SUMIF(Fluxo_Diário!$D$9:$D$1048576,Fluxo_Diário_DB!B40,Fluxo_Diário!$E$9:$E$1048576) -> 0 | H40: =G40+H39 -> 31863
B41: =B40+1 -> 43868 | C41: =SUMIF(Fluxo_Diário!$B$9:$B$1048576,Fluxo_Diário_DB!B41,Fluxo_Diário!$C$9:$C$1048576) -> -50 | D41: =C41+D40 -> 30839 | F41: =B41 -> 43868 | G41: =SUMIF(Fluxo_Diário!$D$9:$D$1048576,Fluxo_Diário_DB!B41,Fluxo_Diário!$E$9:$E$1048576) -> -474 | H41: =G41+H40 -> 31389
B42: =B41+1 -> 43869 | C42: =SUMIF(Fluxo_Diário!$B$9:$B$1048576,Fluxo_Diário_DB!B42,Fluxo_Diário!$C$9:$C$1048576) -> 0 | D42: =C42+D41 -> 30839 | F42: =B42 -> 43869 | G42: =SUMIF(Fluxo_Diário!$D$9:$D$1048576,Fluxo_Diário_DB!B42,Fluxo_Diário!$E$9:$E$1048576) -> 0 | H42: =G42+H41 -> 31389
B43: =B42+1 -> 43870 | C43: =SUMIF(Fluxo_Diário!$B$9:$B$1048576,Fluxo_Diário_DB!B43,Fluxo_Diário!$C$9:$C$1048576) -> -1106 | D43: =C43+D42 -> 29733 | F43: =B43 -> 43870 | G43: =SUMIF(Fluxo_Diário!$D$9:$D$1048576,Fluxo_Diário_DB!B43,Fluxo_Diário!$E$9:$E$1048576) -> -50 | H43: =G43+H42 -> 31339
B44: =B43+1 -> 43871 | C44: =SUMIF(Fluxo_Diário!$B$9:$B$1048576,Fluxo_Diário_DB!B44,Fluxo_Diário!$C$9:$C$1048576) -> 0 | D44: =C44+D43 -> 29733 | F44: =B44 -> 43871 | G44: =SUMIF(Fluxo_Diário!$D$9:$D$1048576,Fluxo_Diário_DB!B44,Fluxo_Diário!$E$9:$E$1048576) -> -4000 | H44: =G44+H43 -> 27339
B45: =B44+1 -> 43872 | C45: =SUMIF(Fluxo_Diário!$B$9:$B$1048576,Fluxo_Diário_DB!B45,Fluxo_Diário!$C$9:$C$1048576) -> 7846 | D45: =C45+D44 -> 37579 | F45: =B45 -> 43872 | G45: =SUMIF(Fluxo_Diário!$D$9:$D$1048576,Fluxo_Diário_DB!B45,Fluxo_Diário!$E$9:$E$1048576) -> -1106 | H45: =G45+H44 -> 26233
... B369: =B368+1 -> 44196 | C369: =SUMIF(Fluxo_Diário!$B$9:$B$1048576,Fluxo_Diário_DB!B369,Fluxo_Diário!$C$9:$C$1048576) -> 0 | D369: =C369+D368 -> 293750 | F369: =B369 -> 44196 | G369: =SUMIF(Fluxo_Diário!$D$9:$D$1048576,Fluxo_Diário_DB!B369,Fluxo_Diário!$E$9:$E$1048576) -> 0 | H369: =G369+H368 -> 293750

Sheet Fluxo_Realizado
A2: ="Fluxo de Caixa Realizado - "&Premissas!C4 -> Fluxo de Caixa Realizado - 2020
B4: Contas | C4: Jan | D4: Fev | E4: Mar | F4: Abr | G4: Mai | H4: Jun | I4: Jul | J4: Ago | K4: Set | L4: Out | M4: Nov | N4: Dez | O4: Jan | P4: Total | Q4: Média
B5: ='Plano de Contas'!B5 -> RECEITAS OPERACIONAIS | C5: =SUM(C6:C10) -> 56325 | D5: =SUM(D6:D10) -> 19889 | E5: =SUM(E6:E10) -> 62947 | F5: =SUM(F6:F10) -> 31838 | G5: =SUM(G6:G10) -> 53566 | H5: =SUM(H6:H10) -> 91372 | I5: =SUM(I6:I10) -> 77493 | J5: =SUM(J6:J10) -> 0 | ... O5: =SUM(O6:O10) -> 0 | P5: =SUM(C5:O5) -> 393430 | Q5: =IF(P5=0,0,AVERAGE(C5:O5)) -> 30263.846
B6: ='Plano de Contas'!B6 -> Consultoria | C6: =SUMIF(Fluxo_Diário!$I:$I,Fluxo_Realizado!$B6,Fluxo_Diário!O:O) -> 28421 | D6: =SUMIF(Fluxo_Diário!$I:$I,Fluxo_Realizado!$B6,Fluxo_Diário!P:P) -> 19889 | E6: =SUMIF(Fluxo_Diário!$I:$I,Fluxo_Realizado!$B6,Fluxo_Diário!Q:Q) -> 8451 | F6: =SUMIF(Fluxo_Diário!$I:$I,Fluxo_Realizado!$B6,Fluxo_Diário!R:R) -> 12775 | G6: =SUMIF(Fluxo_Diário!$I:$I,Fluxo_Realizado!$B6,Fluxo_Diário!S:S) -> 31311 | H6: =SUMIF(Fluxo_Diário!$I:$I,Fluxo_Realizado!$B6,Fluxo_Diário!T:T) -> 36030 | I6: =SUMIF(Fluxo_Diário!$I:$I,Fluxo_Realizado!$B6,Fluxo_Diário!U:U) -> 48694 | J6: =SUMIF(Fluxo_Diário!$I:$I,Fluxo_Realizado!$B6,Fluxo_Diário!V:V) -> 0 | K6: =SUMIF(Fluxo_Diário!$I:$I,Fluxo_Realizado!$B6,Fluxo_Diário!W:W) -> 0 | L6: =SUMIF(Fluxo_Diário!$I:$I,Fluxo_Realizado!$B6,Fluxo_Diário!X:X) -> 0 | M6: =SUMIF(Fluxo_Diário!$I:$I,Fluxo_Realizado!$B6,Fluxo_Diário!Y:Y) -> 0 | N6: =SUMIF(Fluxo_Diário!$I:$I,Fluxo_Realizado!$B6,Fluxo_Diário!Z:Z) -> 0 | O6: =SUMIF(Fluxo_Diário!$I:$I,Fluxo_Realizado!$B6,Fluxo_Diário!AA:AA) -> 0 | P6: =SUM(C6:O6) -> 185571 | Q6: =IF(P6=0,0,AVERAGE(C6:O6)) -> 14274.692
B7: ='Plano de Contas'!B7 -> Licença de software | C7: =SUMIF(Fluxo_Diário!$I:$I,Fluxo_Realizado!$B7,Fluxo_Diário!O:O) -> 12449 | D7: =SUMIF(Fluxo_Diário!$I:$I,Fluxo_Realizado!$B7,Fluxo_Diário!P:P) -> 0 | E7: =SUMIF(Fluxo_Diário!$I:$I,Fluxo_Realizado!$B7,Fluxo_Diário!Q:Q) -> 10267 | F7: =SUMIF(Fluxo_Diário!$I:$I,Fluxo_Realizado!$B7,Fluxo_Diário!R:R) -> 19063 | G7: =SUMIF(Fluxo_Diário!$I:$I,Fluxo_Realizado!$B7,Fluxo_Diário!S:S) -> 18676 | H7: =SUMIF(Fluxo_Diário!$I:$I,Fluxo_Realizado!$B7,Fluxo_Diário!T:T) -> 33102 | I7: =SUMIF(Fluxo_Diário!$I:$I,Fluxo_Realizado!$B7,Fluxo_Diário!U:U) -> 0 | J7: =SUMIF(Fluxo_Diário!$I:$I,Fluxo_Realizado!$B7,Fluxo_Diário!V:V) -> 0 | K7: =SUMIF(Fluxo_Diário!$I:$I,Fluxo_Realizado!$B7,Fluxo_Diário!W:W) -> 0 | L7: =SUMIF(Fluxo_Diário!$I:$I,Fluxo_Realizado!$B7,Fluxo_Diário!X:X) -> 0 | M7: =SUMIF(Fluxo_Diário!$I:$I,Fluxo_Realizado!$B7,Fluxo_Diário!Y:Y) -> 0 | N7: =SUMIF(Fluxo_Diário!$I:$I,Fluxo_Realizado!$B7,Fluxo_Diário!Z:Z) -> 0 | O7: =SUMIF(Fluxo_Diário!$I:$I,Fluxo_Realizado!$B7,Fluxo_Diário!AA:AA) -> 0 | P7: =SUM(C7:O7) -> 93557 | Q7: =IF(P7=0,0,AVERAGE(C7:O7)) -> 7196.6923
B8: ='Plano de Contas'!B8 -> Manutenção de estrutura | C8: =SUMIF(Fluxo_Diário!$I:$I,Fluxo_Realizado!$B8,Fluxo_Diário!O:O) -> 0 | D8: =SUMIF(Fluxo_Diário!$I:$I,Fluxo_Realizado!$B8,Fluxo_Diário!P:P) -> 0 | E8: =SUMIF(Fluxo_Diário!$I:$I,Fluxo_Realizado!$B8,Fluxo_Diário!Q:Q) -> 0 | F8: =SUMIF(Fluxo_Diário!$I:$I,Fluxo_Realizado!$B8,Fluxo_Diário!R:R) -> 0 | G8: =SUMIF(Fluxo_Diário!$I:$I,Fluxo_Realizado!$B8,Fluxo_Diário!S:S) -> 0 | H8: =SUMIF(Fluxo_Diário!$I:$I,Fluxo_Realizado!$B8,Fluxo_Diário!T:T) -> 0 | I8: =SUMIF(Fluxo_Diário!$I:$I,Fluxo_Realizado!$B8,Fluxo_Diário!U:U) -> 0 | J8: =SUMIF(Fluxo_Diário!$I:$I,Fluxo_Realizado!$B8,Fluxo_Diário!V:V) -> 0 | K8: =SUMIF(Fluxo_Diário!$I:$I,Fluxo_Realizado!$B8,Fluxo_Diário!W:W) -> 0 | L8: =SUMIF(Fluxo_Diário!$I:$I,Fluxo_Realizado!$B8,Fluxo_Diário!X:X) -> 0 | M8: =SUMIF(Fluxo_Diário!$I:$I,Fluxo_Realizado!$B8,Fluxo_Diário!Y:Y) -> 0 | N8: =SUMIF(Fluxo_Diário!$I:$I,Fluxo_Realizado!$B8,Fluxo_Diário!Z:Z) -> 0 | O8: =SUMIF(Fluxo_Diário!$I:$I,Fluxo_Realizado!$B8,Fluxo_Diário!AA:AA) -> 0 | P8: =SUM(C8:O8) -> 0 | Q8: =IF(P8=0,0,AVERAGE(C8:O8)) -> 0
B9: ='Plano de Contas'!B9 -> Manutenção de Sistemas | C9: =SUMIF(Fluxo_Diário!$I:$I,Fluxo_Realizado!$B9,Fluxo_Diário!O:O) -> 15455 | D9: =SUMIF(Fluxo_Diário!$I:$I,Fluxo_Realizado!$B9,Fluxo_Diário!P:P) -> 0 | E9: =SUMIF(Fluxo_Diário!$I:$I,Fluxo_Realizado!$B9,Fluxo_Diário!Q:Q) -> 44229 | F9: =SUMIF(Fluxo_Diário!$I:$I,Fluxo_Realizado!$B9,Fluxo_Diário!R:R) -> 0 | G9: =SUMIF(Fluxo_Diário!$I:$I,Fluxo_Realizado!$B9,Fluxo_Diário!S:S) -> 3579 | H9: =SUMIF(Fluxo_Diário!$I:$I,Fluxo_Realizado!$B9,Fluxo_Diário!T:T) -> 22240 | I9: =SUMIF(Fluxo_Diário!$I:$I,Fluxo_Realizado!$B9,Fluxo_Diário!U:U) -> 28799 | J9: =SUMIF(Fluxo_Diário!$I:$I,Fluxo_Realizado!$B9,Fluxo_Diário!V:V) -> 0 | K9: =SUMIF(Fluxo_Diário!$I:$I,Fluxo_Realizado!$B9,Fluxo_Diário!W:W) -> 0 | L9: =SUMIF(Fluxo_Diário!$I:$I,Fluxo_Realizado!$B9,Fluxo_Diário!X:X) -> 0 | M9: =SUMIF(Fluxo_Diário!$I:$I,Fluxo_Realizado!$B9,Fluxo_Diário!Y:Y) -> 0 | N9: =SUMIF(Fluxo_Diário!$I:$I,Fluxo_Realizado!$B9,Fluxo_Diário!Z:Z) -> 0 | O9: =SUMIF(Fluxo_Diário!$I:$I,Fluxo_Realizado!$B9,Fluxo_Diário!AA:AA) -> 0 | P9: =SUM(C9:O9) -> 114302 | Q9: =IF(P9=0,0,AVERAGE(C9:O9)) -> 8792.4615
B10: ='Plano de Contas'!B10 -> Outras receitas | C10: =SUMIF(Fluxo_Diário!$I:$I,Fluxo_Realizado!$B10,Fluxo_Diário!O:O) -> 0 | D10: =SUMIF(Fluxo_Diário!$I:$I,Fluxo_Realizado!$B10,Fluxo_Diário!P:P) -> 0 | E10: =SUMIF(Fluxo_Diário!$I:$I,Fluxo_Realizado!$B10,Fluxo_Diário!Q:Q) -> 0 | F10: =SUMIF(Fluxo_Diário!$I:$I,Fluxo_Realizado!$B10,Fluxo_Diário!R:R) -> 0 | G10: =SUMIF(Fluxo_Diário!$I:$I,Fluxo_Realizado!$B10,Fluxo_Diário!S:S) -> 0 | H10: =SUMIF(Fluxo_Diário!$I:$I,Fluxo_Realizado!$B10,Fluxo_Diário!T:T) -> 0 | I10: =SUMIF(Fluxo_Diário!$I:$I,Fluxo_Realizado!$B10,Fluxo_Diário!U:U) -> 0 | J10: =SUMIF(Fluxo_Diário!$I:$I,Fluxo_Realizado!$B10,Fluxo_Diário!V:V) -> 0 | K10: =SUMIF(Fluxo_Diário!$I:$I,Fluxo_Realizado!$B10,Fluxo_Diário!W:W) -> 0 | L10: =SUMIF(Fluxo_Diário!$I:$I,Fluxo_Realizado!$B10,Fluxo_Diário!X:X) -> 0 | M10: =SUMIF(Fluxo_Diário!$I:$I,Fluxo_Realizado!$B10,Fluxo_Diário!Y:Y) -> 0 | N10: =SUMIF(Fluxo_Diário!$I:$I,Fluxo_Realizado!$B10,Fluxo_Diário!Z:Z) -> 0 | O10: =SUMIF(Fluxo_Diário!$I:$I,Fluxo_Realizado!$B10,Fluxo_Diário!AA:AA) -> 0 | P10: =SUM(C10:O10) -> 0 | Q10: =IF(P10=0,0,AVERAGE(C10:O10)) -> 0
B11: ='Plano de Contas'!B11 -> DESPESAS FIXAS | C11: =SUM(C12:C32) -> -14820 | D11: =SUM(D12:D32) -> -10767 | E11: =SUM(E12:E32) -> -11236 | F11: =SUM(F12:F32) -> -13123 | G11: =SUM(G12:G32) -> -11170 | H11: =SUM(H12:H32) -> -7145 | I11: =SUM(I12:I32) -> -6506 | J11: =SUM(J12:J32) -> -1355 | ... O11: =SUM(O12:O32) -> 0 | P11: =SUM(C11:O11) -> -76122 | Q11: =IF(P11=0,0,AVERAGE(C11:O11)) -> -5855.5385
B12: ='Plano de Contas'!B12 -> Água | C12: =SUMIF(Fluxo_Diário!$I:$I,Fluxo_Realizado!$B12,Fluxo_Diário!O:O) -> -100 | D12: =SUMIF(Fluxo_Diário!$I:$I,Fluxo_Realizado!$B12,Fluxo_Diário!P:P) -> 0 | E12: =SUMIF(Fluxo_Diário!$I:$I,Fluxo_Realizado!$B12,Fluxo_Diário!Q:Q) -> 0 | F12: =SUMIF(Fluxo_Diário!$I:$I,Fluxo_Realizado!$B12,Fluxo_Diário!R:R) -> 0 | G12: =SUMIF(Fluxo_Diário!$I:$I,Fluxo_Realizado!$B12,Fluxo_Diário!S:S) -> 0 | H12: =SUMIF(Fluxo_Diário!$I:$I,Fluxo_Realizado!$B12,Fluxo_Diário!T:T) -> 0 | I12: =SUMIF(Fluxo_Diário!$I:$I,Fluxo_Realizado!$B12,Fluxo_Diário!U:U) -> 0 | J12: =SUMIF(Fluxo_Diário!$I:$I,Fluxo_Realizado!$B12,Fluxo_Diário!V:V) -> 0 | K12: =SUMIF(Fluxo_Diário!$I:$I,Fluxo_Realizado!$B12,Fluxo_Diário!W:W) -> 0 | L12: =SUMIF(Fluxo_Diário!$I:$I,Fluxo_Realizado!$B12,Fluxo_Diário!X:X) -> 0 | M12: =SUMIF(Fluxo_Diário!$I:$I,Fluxo_Realizado!$B12,Fluxo_Diário!Y:Y) -> 0 | N12: =SUMIF(Fluxo_Diário!$I:$I,Fluxo_Realizado!$B12,Fluxo_Diário!Z:Z) -> 0 | O12: =SUMIF(Fluxo_Diário!$I:$I,Fluxo_Realizado!$B12,Fluxo_Diário!AA:AA) -> 0 | P12: =SUM(C12:O12) -> -100 | Q12: =IF(P12=0,0,AVERAGE(C12:O12)) -> -7.6923077
B13: ='Plano de Contas'!B13 -> Aluguel | C13: =SUMIF(Fluxo_Diário!$I:$I,Fluxo_Realizado!$B13,Fluxo_Diário!O:O) -> 0 | D13: =SUMIF(Fluxo_Diário!$I:$I,Fluxo_Realizado!$B13,Fluxo_Diário!P:P) -> 0 | E13: =SUMIF(Fluxo_Diário!$I:$I,Fluxo_Realizado!$B13,Fluxo_Diário!Q:Q) -> 0 | F13: =SUMIF(Fluxo_Diário!$I:$I,Fluxo_Realizado!$B13,Fluxo_Diário!R:R) -> 0 | G13: =SUMIF(Fluxo_Diário!$I:$I,Fluxo_Realizado!$B13,Fluxo_Diário!S:S) -> 0 | H13: =SUMIF(Fluxo_Diário!$I:$I,Fluxo_Realizado!$B13,Fluxo_Diário!T:T) -> 0 | I13: =SUMIF(Fluxo_Diário!$I:$I,Fluxo_Realizado!$B13,Fluxo_Diário!U:U) -> 0 | J13: =SUMIF(Fluxo_Diário!$I:$I,Fluxo_Realizado!$B13,Fluxo_Diário!V:V) -> 0 | K13: =SUMIF(Fluxo_Diário!$I:$I,Fluxo_Realizado!$B13,Fluxo_Diário!W:W) -> 0 | L13: =SUMIF(Fluxo_Diário!$I:$I,Fluxo_Realizado!$B13,Fluxo_Diário!X:X) -> 0 | M13: =SUMIF(Fluxo_Diário!$I:$I,Fluxo_Realizado!$B13,Fluxo_Diário!Y:Y) -> 0 | N13: =SUMIF(Fluxo_Diário!$I:$I,Fluxo_Realizado!$B13,Fluxo_Diário!Z:Z) -> 0 | O13: =SUMIF(Fluxo_Diário!$I:$I,Fluxo_Realizado!$B13,Fluxo_Diário!AA:AA) -> 0 | P13: =SUM(C13:O13) -> 0 | Q13: =IF(P13=0,0,AVERAGE(C13:O13)) -> 0
B14: ='Plano de Contas'!B14 -> Cartório | C14: =SUMIF(Fluxo_Diário!$I:$I,Fluxo_Realizado!$B14,Fluxo_Diário!O:O) -> -20 | D14: =SUMIF(Fluxo_Diário!$I:$I,Fluxo_Realizado!$B14,Fluxo_Diário!P:P) -> 0 | E14: =SUMIF(Fluxo_Diário!$I:$I,Fluxo_Realizado!$B14,Fluxo_Diário!Q:Q) -> 0 | F14: =SUMIF(Fluxo_Diário!$I:$I,Fluxo_Realizado!$B14,Fluxo_Diário!R:R) -> 0 | G14: =SUMIF(Fluxo_Diário!$I:$I,Fluxo_Realizado!$B14,Fluxo_Diário!S:S) -> 0 | H14: =SUMIF(Fluxo_Diário!$I:$I,Fluxo_Realizado!$B14,Fluxo_Diário!T:T) -> 0 | I14: =SUMIF(Fluxo_Diário!$I:$I,Fluxo_Realizado!$B14,Fluxo_Diário!U:U) -> 0 | J14: =SUMIF(Fluxo_Diário!$I:$I,Fluxo_Realizado!$B14,Fluxo_Diário!V:V) -> 0 | K14: =SUMIF(Fluxo_Diário!$I:$I,Fluxo_Realizado!$B14,Fluxo_Diário!W:W) -> 0 | L14: =SUMIF(Fluxo_Diário!$I:$I,Fluxo_Realizado!$B14,Fluxo_Diário!X:X) -> 0 | M14: =SUMIF(Fluxo_Diário!$I:$I,Fluxo_Realizado!$B14,Fluxo_Diário!Y:Y) -> 0 | N14: =SUMIF(Fluxo_Diário!$I:$I,Fluxo_Realizado!$B14,Fluxo_Diário!Z:Z) -> 0 | O14: =SUMIF(Fluxo_Diário!$I:$I,Fluxo_Realizado!$B14,Fluxo_Diário!AA:AA) -> 0 | P14: =SUM(C14:O14) -> -20 | Q14: =IF(P14=0,0,AVERAGE(C14:O14)) -> -1.5384615
B15: ='Plano de Contas'!B15 -> Combustível | C15: =SUMIF(Fluxo_Diário!$I:$I,Fluxo_Realizado!$B15,Fluxo_Diário!O:O) -> 0 | D15: =SUMIF(Fluxo_Diário!$I:$I,Fluxo_Realizado!$B15,Fluxo_Diário!P:P) -> 0 | E15: =SUMIF(Fluxo_Diário!$I:$I,Fluxo_Realizado!$B15,Fluxo_Diário!Q:Q) -> 0 | F15: =SUMIF(Fluxo_Diário!$I:$I,Fluxo_Realizado!$B15,Fluxo_Diário!R:R) -> 0 | G15: =SUMIF(Fluxo_Diário!$I:$I,Fluxo_Realizado!$B15,Fluxo_Diário!S:S) -> 0 | H15: =SUMIF(Fluxo_Diário!$I:$I,Fluxo_Realizado!$B15,Fluxo_Diário!T:T) -> 0 | I15: =SUMIF(Fluxo_Diário!$I:$I,Fluxo_Realizado!$B15,Fluxo_Diário!U:U) -> 0 | J15: =SUMIF(Fluxo_Diário!$I:$I,Fluxo_Realizado!$B15,Fluxo_Diário!V:V) -> 0 | K15: =SUMIF(Fluxo_Diário!$I:$I,Fluxo_Realizado!$B15,Fluxo_Diário!W:W) -> 0 | L15: =SUMIF(Fluxo_Diário!$I:$I,Fluxo_Realizado!$B15,Fluxo_Diário!X:X) -> 0 | M15: =SUMIF(Fluxo_Diário!$I:$I,Fluxo_Realizado!$B15,Fluxo_Diário!Y:Y) -> 0 | N15: =SUMIF(Fluxo_Diário!$I:$I,Fluxo_Realizado!$B15,Fluxo_Diário!Z:Z) -> 0 | O15: =SUMIF(Fluxo_Diário!$I:$I,Fluxo_Realizado!$B15,Fluxo_Diário!AA:AA) -> 0 | P15: =SUM(C15:O15) -> 0 | Q15: =IF(P15=0,0,AVERAGE(C15:O15)) -> 0
B16: ='Plano de Contas'!B16 -> Correios | C16: =SUMIF(Fluxo_Diário!$I:$I,Fluxo_Realizado!$B16,Fluxo_Diário!O:O) -> -2284 | D16: =SUMIF(Fluxo_Diário!$I:$I,Fluxo_Realizado!$B16,Fluxo_Diário!P:P) -> -524 | E16: =SUMIF(Fluxo_Diário!$I:$I,Fluxo_Realizado!$B16,Fluxo_Diário!Q:Q) -> 0 | F16: =SUMIF(Fluxo_Diário!$I:$I,Fluxo_Realizado!$B16,Fluxo_Diário!R:R) -> 0 | G16: =SUMIF(Fluxo_Diário!$I:$I,Fluxo_Realizado!$B16,Fluxo_Diário!S:S) -> 0 | H16: =SUMIF(Fluxo_Diário!$I:$I,Fluxo_Realizado!$B16,Fluxo_Diário!T:T) -> 0 | I16: =SUMIF(Fluxo_Diário!$I:$I,Fluxo_Realizado!$B16,Fluxo_Diário!U:U) -> 0 | J16: =SUMIF(Fluxo_Diário!$I:$I,Fluxo_Realizado!$B16,Fluxo_Diário!V:V) -> 0 | K16: =SUMIF(Fluxo_Diário!$I:$I,Fluxo_Realizado!$B16,Fluxo_Diário!W:W) -> 0 | L16: =SUMIF(Fluxo_Diário!$I:$I,Fluxo_Realizado!$B16,Fluxo_Diário!X:X) -> 0 | M16: =SUMIF(Fluxo_Diário!$I:$I,Fluxo_Realizado!$B16,Fluxo_Diário!Y:Y) -> 0 | N16: =SUMIF(Fluxo_Diário!$I:$I,Fluxo_Realizado!$B16,Fluxo_Diário!Z:Z) -> 0 | O16: =SUMIF(Fluxo_Diário!$I:$I,Fluxo_Realizado!$B16,Fluxo_Diário!AA:AA) -> 0 | P16: =SUM(C16:O16) -> -2808 | Q16: =IF(P16=0,0,AVERAGE(C16:O16)) -> -216
B17: ='Plano de Contas'!B17 -> Encargos sociais | C17: =SUMIF(Fluxo_Diário!$I:$I,Fluxo_Realizado!$B17,Fluxo_Diário!O:O) -> 0 | D17: =SUMIF(Fluxo_Diário!$I:$I,Fluxo_Realizado!$B17,Fluxo_Diário!P:P) -> 0 | E17: =SUMIF(Fluxo_Diário!$I:$I,Fluxo_Realizado!$B17,Fluxo_Diário!Q:Q) -> 0 | F17: =SUMIF(Fluxo_Diário!$I:$I,Fluxo_Realizado!$B17,Fluxo_Diário!R:R) -> 0 | G17: =SUMIF(Fluxo_Diário!$I:$I,Fluxo_Realizado!$B17,Fluxo_Diário!S:S) -> 0 | H17: =SUMIF(Fluxo_Diário!$I:$I,Fluxo_Realizado!$B17,Fluxo_Diário!T:T) -> 0 | I17: =SUMIF(Fluxo_Diário!$I:$I,Fluxo_Realizado!$B17,Fluxo_Diário!U:U) -> 0 | J17: =SUMIF(Fluxo_Diário!$I:$I,Fluxo_Realizado!$B17,Fluxo_Diário!V:V) -> 0 | K17: =SUMIF(Fluxo_Diário!$I:$I,Fluxo_Realizado!$B17,Fluxo_Diário!W:W) -> 0 | L17: =SUMIF(Fluxo_Diário!$I:$I,Fluxo_Realizado!$B17,Fluxo_Diário!X:X) -> 0 | M17: =SUMIF(Fluxo_Diário!$I:$I,Fluxo_Realizado!$B17,Fluxo_Diário!Y:Y) -> 0 | N17: =SUMIF(Fluxo_Diário!$I:$I,Fluxo_Realizado!$B17,Fluxo_Diário!Z:Z) -> 0 | O17: =SUMIF(Fluxo_Diário!$I:$I,Fluxo_Realizado!$B17,Fluxo_Diário!AA:AA) -> 0 | P17: =SUM(C17:O17) -> 0 | Q17: =IF(P17=0,0,AVERAGE(C17:O17)) -> 0
B18: ='Plano de Contas'!B18 -> Energia | C18: =SUMIF(Fluxo_Diário!$I:$I,Fluxo_Realizado!$B18,Fluxo_Diário!O:O) -> -4835 | D18: =SUMIF(Fluxo_Diário!$I:$I,Fluxo_Realizado!$B18,Fluxo_Diário!P:P) -> 0 | E18: =SUMIF(Fluxo_Diário!$I:$I,Fluxo_Realizado!$B18,Fluxo_Diário!Q:Q) -> 0 | F18: =SUMIF(Fluxo_Diário!$I:$I,Fluxo_Realizado!$B18,Fluxo_Diário!R:R) -> 0 | G18: =SUMIF(Fluxo_Diário!$I:$I,Fluxo_Realizado!$B18,Fluxo_Diário!S:S) -> 0 | H18: =SUMIF(Fluxo_Diário!$I:$I,Fluxo_Realizado!$B18,Fluxo_Diário!T:T) -> 0 | I18: =SUMIF(Fluxo_Diário!$I:$I,Fluxo_Realizado!$B18,Fluxo_Diário!U:U) -> 0 | J18: =SUMIF(Fluxo_Diário!$I:$I,Fluxo_Realizado!$B18,Fluxo_Diário!V:V) -> 0 | K18: =SUMIF(Fluxo_Diário!$I:$I,Fluxo_Realizado!$B18,Fluxo_Diário!W:W) -> 0 | L18: =SUMIF(Fluxo_Diário!$I:$I,Fluxo_Realizado!$B18,Fluxo_Diário!X:X) -> 0 | M18: =SUMIF(Fluxo_Diário!$I:$I,Fluxo_Realizado!$B18,Fluxo_Diário!Y:Y) -> 0 | N18: =SUMIF(Fluxo_Diário!$I:$I,Fluxo_Realizado!$B18,Fluxo_Diário!Z:Z) -> 0 | O18: =SUMIF(Fluxo_Diário!$I:$I,Fluxo_Realizado!$B18,Fluxo_Diário!AA:AA) -> 0 | P18: =SUM(C18:O18) -> -4835 | Q18: =IF(P18=0,0,AVERAGE(C18:O18)) -> -371.92308
B19: ='Plano de Contas'!B19 -> Fones / Comunicação | C19: =SUMIF(Fluxo_Diário!$I:$I,Fluxo_Realizado!$B19,Fluxo_Diário!O:O) -> -3164 | D19: =SUMIF(Fluxo_Diário!$I:$I,Fluxo_Realizado!$B19,Fluxo_Diário!P:P) -> -1836 | E19: =SUMIF(Fluxo_Diário!$I:$I,Fluxo_Realizado!$B19,Fluxo_Diário!Q:Q) -> -1556 | F19: =SUMIF(Fluxo_Diário!$I:$I,Fluxo_Realizado!$B19,Fluxo_Diário!R:R) -> -3955 | G19: =SUMIF(Fluxo_Diário!$I:$I,Fluxo_Realizado!$B19,Fluxo_Diário!S:S) -> 0 | H19: =SUMIF(Fluxo_Diário!$I:$I,Fluxo_Realizado!$B19,Fluxo_Diário!T:T) -> 0 | I19: =SUMIF(Fluxo_Diário!$I:$I,Fluxo_Realizado!$B19,Fluxo_Diário!U:U) -> -2364 | J19: =SUMIF(Fluxo_Diário!$I:$I,Fluxo_Realizado!$B19,Fluxo_Diário!V:V) -> 0 | K19: =SUMIF(Fluxo_Diário!$I:$I,Fluxo_Realizado!$B19,Fluxo_Diário!W:W) -> 0 | L19: =SUMIF(Fluxo_Diário!$I:$I,Fluxo_Realizado!$B19,Fluxo_Diário!X:X) -> 0 | M19: =SUMIF(Fluxo_Diário!$I:$I,Fluxo_Realizado!$B19,Fluxo_Diário!Y:Y) -> 0 | N19: =SUMIF(Fluxo_Diário!$I:$I,Fluxo_Realizado!$B19,Fluxo_Diário!Z:Z) -> 0 | O19: =SUMIF(Fluxo_Diário!$I:$I,Fluxo_Realizado!$B19,Fluxo_Diário!AA:AA) -> 0 | P19: =SUM(C19:O19) -> -12875 | Q19: =IF(P19=0,0,AVERAGE(C19:O19)) -> -990.38462
B20: ='Plano de Contas'!B20 -> Impostos/taxas diversas | C20: =SUMIF(Fluxo_Diário!$I:$I,Fluxo_Realizado!$B20,Fluxo_Diário!O:O) -> -2037 | D20: =SUMIF(Fluxo_Diário!$I:$I,Fluxo_Realizado!$B20,Fluxo_Diário!P:P) -> -230 | E20: =SUMIF(Fluxo_Diário!$I:$I,Fluxo_Realizado!$B20,Fluxo_Diário!Q:Q) -> -1980 | F20: =SUMIF(Fluxo_Diário!$I:$I,Fluxo_Realizado!$B20,Fluxo_Diário!R:R) -> -2452 | G20: =SUMIF(Fluxo_Diário!$I:$I,Fluxo_Realizado!$B20,Fluxo_Diário!S:S) -> 0 | H20: =SUMIF(Fluxo_Diário!$I:$I,Fluxo_Realizado!$B20,Fluxo_Diário!T:T) -> 0 | I20: =SUMIF(Fluxo_Diário!$I:$I,Fluxo_Realizado!$B20,Fluxo_Diário!U:U) -> 0 | J20: =SUMIF(Fluxo_Diário!$I:$I,Fluxo_Realizado!$B20,Fluxo_Diário!V:V) -> -1355 | K20: =SUMIF(Fluxo_Diário!$I:$I,Fluxo_Realizado!$B20,Fluxo_Diário!W:W) -> 0 | L20: =SUMIF(Fluxo_Diário!$I:$I,Fluxo_Realizado!$B20,Fluxo_Diário!X:X) -> 0 | M20: =SUMIF(Fluxo_Diário!$I:$I,Fluxo_Realizado!$B20,Fluxo_Diário!Y:Y) -> 0 | N20: =SUMIF(Fluxo_Diário!$I:$I,Fluxo_Realizado!$B20,Fluxo_Diário!Z:Z) -> 0 | O20: =SUMIF(Fluxo_Diário!$I:$I,Fluxo_Realizado!$B20,Fluxo_Diário!AA:AA) -> 0 | P20: =SUM(C20:O20) -> -8054 | Q20: =IF(P20=0,0,AVERAGE(C20:O20)) -> -619.53846
B21: ='Plano de Contas'!B21 -> Manutenção equipamentos | C21: =SUMIF(Fluxo_Diário!$I:$I,Fluxo_Realizado!$B21,Fluxo_Diário!O:O) -> -1000 | D21: =SUMIF(Fluxo_Diário!$I:$I,Fluxo_Realizado!$B21,Fluxo_Diário!P:P) -> 0 | E21: =SUMIF(Fluxo_Diário!$I:$I,Fluxo_Realizado!$B21,Fluxo_Diário!Q:Q) -> 0 | F21: =SUMIF(Fluxo_Diário!$I:$I,Fluxo_Realizado!$B21,Fluxo_Diário!R:R) -> 0 | G21: =SUMIF(Fluxo_Diário!$I:$I,Fluxo_Realizado!$B21,Fluxo_Diário!S:S) -> 0 | H21: =SUMIF(Fluxo_Diário!$I:$I,Fluxo_Realizado!$B21,Fluxo_Diário!T:T) -> 0 | I21: =SUMIF(Fluxo_Diário!$I:$I,Fluxo_Realizado!$B21,Fluxo_Diário!U:U) -> 0 | J21: =SUMIF(Fluxo_Diário!$I:$I,Fluxo_Realizado!$B21,Fluxo_Diário!V:V) -> 0 | K21: =SUMIF(Fluxo_Diário!$I:$I,Fluxo_Realizado!$B21,Fluxo_Diário!W:W) -> 0 | L21: =SUMIF(Fluxo_Diário!$I:$I,Fluxo_Realizado!$B21,Fluxo_Diário!X:X) -> 0 | M21: =SUMIF(Fluxo_Diário!$I:$I,Fluxo_Realizado!$B21,Fluxo_Diário!Y:Y) -> 0 | N21: =SUMIF(Fluxo_Diário!$I:$I,Fluxo_Realizado!$B21,Fluxo_Diário!Z:Z) -> 0 | O21: =SUMIF(Fluxo_Diário!$I:$I,Fluxo_Realizado!$B21,Fluxo_Diário!AA:AA) -> 0 | P21: =SUM(C21:O21) -> -1000 | Q21: =IF(P21=0,0,AVERAGE(C21:O21)) -> -76.923077
B22: ='Plano de Contas'!B22 -> Manutenção prédio | C22: =SUMIF(Fluxo_Diário!$I:$I,Fluxo_Realizado!$B22,Fluxo_Diário!O:O) -> -50 | D22: =SUMIF(Fluxo_Diário!$I:$I,Fluxo_Realizado!$B22,Fluxo_Diário!P:P) -> 0 | E22: =SUMIF(Fluxo_Diário!$I:$I,Fluxo_Realizado!$B22,Fluxo_Diário!Q:Q) -> 0 | F22: =SUMIF(Fluxo_Diário!$I:$I,Fluxo_Realizado!$B22,Fluxo_Diário!R:R) -> 0 | G22: =SUMIF(Fluxo_Diário!$I:$I,Fluxo_Realizado!$B22,Fluxo_Diário!S:S) -> 0 | H22: =SUMIF(Fluxo_Diário!$I:$I,Fluxo_Realizado!$B22,Fluxo_Diário!T:T) -> 0 | I22: =SUMIF(Fluxo_Diário!$I:$I,Fluxo_Realizado!$B22,Fluxo_Diário!U:U) -> 0 | J22: =SUMIF(Fluxo_Diário!$I:$I,Fluxo_Realizado!$B22,Fluxo_Diário!V:V) -> 0 | K22: =SUMIF(Fluxo_Diário!$I:$I,Fluxo_Realizado!$B22,Fluxo_Diário!W:W) -> 0 | L22: =SUMIF(Fluxo_Diário!$I:$I,Fluxo_Realizado!$B22,Fluxo_Diário!X:X) -> 0 | M22: =SUMIF(Fluxo_Diário!$I:$I,Fluxo_Realizado!$B22,Fluxo_Diário!Y:Y) -> 0 | N22: =SUMIF(Fluxo_Diário!$I:$I,Fluxo_Realizado!$B22,Fluxo_Diário!Z:Z) -> 0 | O22: =SUMIF(Fluxo_Diário!$I:$I,Fluxo_Realizado!$B22,Fluxo_Diário!AA:AA) -> 0 | P22: =SUM(C22:O22) -> -50 | Q22: =IF(P22=0,0,AVERAGE(C22:O22)) -> -3.8461538
B23: ='Plano de Contas'!B23 -> Material escritório | C23: =SUMIF(Fluxo_Diário!$I:$I,Fluxo_Realizado!$B23,Fluxo_Diário!O:O) -> -30 | D23: =SUMIF(Fluxo_Diário!$I:$I,Fluxo_Realizado!$B23,Fluxo_Diário!P:P) -> 0 | E23: =SUMIF(Fluxo_Diário!$I:$I,Fluxo_Realizado!$B23,Fluxo_Diário!Q:Q) -> -3227 | F23: =SUMIF(Fluxo_Diário!$I:$I,Fluxo_Realizado!$B23,Fluxo_Diário!R:R) -> -1484 | G23: =SUMIF(Fluxo_Diário!$I:$I,Fluxo_Realizado!$B23,Fluxo_Diário!S:S) -> -1626 | H23: =SUMIF(Fluxo_Diário!$I:$I,Fluxo_Realizado!$B23,Fluxo_Diário!T:T) -> 0 | I23: =SUMIF(Fluxo_Diário!$I:$I,Fluxo_Realizado!$B23,Fluxo_Diário!U:U) -> 0 | J23: =SUMIF(Fluxo_Diário!$I:$I,Fluxo_Realizado!$B23,Fluxo_Diário!V:V) -> 0 | K23: =SUMIF(Fluxo_Diário!$I:$I,Fluxo_Realizado!$B23,Fluxo_Diário!W:W) -> 0 | L23: =SUMIF(Fluxo_Diário!$I:$I,Fluxo_Realizado!$B23,Fluxo_Diário!X:X) -> 0 | M23: =SUMIF(Fluxo_Diário!$I:$I,Fluxo_Realizado!$B23,Fluxo_Diário!Y:Y) -> 0 | N23: =SUMIF(Fluxo_Diário!$I:$I,Fluxo_Realizado!$B23,Fluxo_Diário!Z:Z) -> 0 | O23: =SUMIF(Fluxo_Diário!$I:$I,Fluxo_Realizado!$B23,Fluxo_Diário!AA:AA) -> 0 | P23: =SUM(C23:O23) -> -6367 | Q23: =IF(P23=0,0,AVERAGE(C23:O23)) -> -489.76923
... B32: ='Plano de Contas'!B32 -> Viagens | C32: =SUMIF(Fluxo_Diário!$I:$I,Fluxo_Realizado!$B32,Fluxo_Diário!O:O) -> 0 | D32: =SUMIF(Fluxo_Diário!$I:$I,Fluxo_Realizado!$B32,Fluxo_Diário!P:P) -> 0 | E32: =SUMIF(Fluxo_Diário!$I:$I,Fluxo_Realizado!$B32,Fluxo_Diário!Q:Q) -> 0 | F32: =SUMIF(Fluxo_Diário!$I:$I,Fluxo_Realizado!$B32,Fluxo_Diário!R:R) -> 0 | G32: =SUMIF(Fluxo_Diário!$I:$I,Fluxo_Realizado!$B32,Fluxo_Diário!S:S) -> -1047 | H32: =SUMIF(Fluxo_Diário!$I:$I,Fluxo_Realizado!$B32,Fluxo_Diário!T:T) -> 0 | I32: =SUMIF(Fluxo_Diário!$I:$I,Fluxo_Realizado!$B32,Fluxo_Diário!U:U) -> 0 | J32: =SUMIF(Fluxo_Diário!$I:$I,Fluxo_Realizado!$B32,Fluxo_Diário!V:V) -> 0 | K32: =SUMIF(Fluxo_Diário!$I:$I,Fluxo_Realizado!$B32,Fluxo_Diário!W:W) -> 0 | L32: =SUMIF(Fluxo_Diário!$I:$I,Fluxo_Realizado!$B32,Fluxo_Diário!X:X) -> 0 | M32: =SUMIF(Fluxo_Diário!$I:$I,Fluxo_Realizado!$B32,Fluxo_Diário!Y:Y) -> 0 | N32: =SUMIF(Fluxo_Diário!$I:$I,Fluxo_Realizado!$B32,Fluxo_Diário!Z:Z) -> 0 | O32: =SUMIF(Fluxo_Diário!$I:$I,Fluxo_Realizado!$B32,Fluxo_Diário!AA:AA) -> 0 | P32: =SUM(C32:O32) -> -1047 | Q32: =IF(P32=0,0,AVERAGE(C32:O32)) -> -80.538462
B33: ='Plano de Contas'!B33 -> DESPESAS VARIÁVEIS | C33: =SUM(C34:C38) -> -2713 | D33: =SUM(D34:D38) -> -7731 | E33: =SUM(E34:E38) -> -2302 | F33: =SUM(F34:F38) -> -5563 | G33: =SUM(G34:G38) -> -2853 | H33: =SUM(H34:H38) -> -2396 | I33: =SUM(I34:I38) -> 0 | J33: =SUM(J34:J38) -> 0 | ... O33: =SUM(O34:O38) -> 0 | P33: =SUM(C33:O33) -> -23558 | Q33: =IF(P33=0,0,AVERAGE(C33:O33)) -> -1812.1538
B34: ='Plano de Contas'!B34 -> Comissões | C34: =SUMIF(Fluxo_Diário!$I:$I,Fluxo_Realizado!$B34,Fluxo_Diário!O:O) -> 0 | D34: =SUMIF(Fluxo_Diário!$I:$I,Fluxo_Realizado!$B34,Fluxo_Diário!P:P) -> -2306 | E34: =SUMIF(Fluxo_Diário!$I:$I,Fluxo_Realizado!$B34,Fluxo_Diário!Q:Q) -> 0 | F34: =SUMIF(Fluxo_Diário!$I:$I,Fluxo_Realizado!$B34,Fluxo_Diário!R:R) -> -3135 | G34: =SUMIF(Fluxo_Diário!$I:$I,Fluxo_Realizado!$B34,Fluxo_Diário!S:S) -> 0 | H34: =SUMIF(Fluxo_Diário!$I:$I,Fluxo_Realizado!$B34,Fluxo_Diário!T:T) -> 0 | I34: =SUMIF(Fluxo_Diário!$I:$I,Fluxo_Realizado!$B34,Fluxo_Diário!U:U) -> 0 | J34: =SUMIF(Fluxo_Diário!$I:$I,Fluxo_Realizado!$B34,Fluxo_Diário!V:V) -> 0 | K34: =SUMIF(Fluxo_Diário!$I:$I,Fluxo_Realizado!$B34,Fluxo_Diário!W:W) -> 0 | L34: =SUMIF(Fluxo_Diário!$I:$I,Fluxo_Realizado!$B34,Fluxo_Diário!X:X) -> 0 | M34: =SUMIF(Fluxo_Diário!$I:$I,Fluxo_Realizado!$B34,Fluxo_Diário!Y:Y) -> 0 | N34: =SUMIF(Fluxo_Diário!$I:$I,Fluxo_Realizado!$B34,Fluxo_Diário!Z:Z) -> 0 | O34: =SUMIF(Fluxo_Diário!$I:$I,Fluxo_Realizado!$B34,Fluxo_Diário!AA:AA) -> 0 | P34: =SUM(C34:O34) -> -5441 | Q34: =IF(P34=0,0,AVERAGE(C34:O34)) -> -418.53846
B35: ='Plano de Contas'!B35 -> Impostos estaduais | C35: =SUMIF(Fluxo_Diário!$I:$I,Fluxo_Realizado!$B35,Fluxo_Diário!O:O) -> 0 | D35: =SUMIF(Fluxo_Diário!$I:$I,Fluxo_Realizado!$B35,Fluxo_Diário!P:P) -> 0 | E35: =SUMIF(Fluxo_Diário!$I:$I,Fluxo_Realizado!$B35,Fluxo_Diário!Q:Q) -> 0 | F35: =SUMIF(Fluxo_Diário!$I:$I,Fluxo_Realizado!$B35,Fluxo_Diário!R:R) -> 0 | G35: =SUMIF(Fluxo_Diário!$I:$I,Fluxo_Realizado!$B35,Fluxo_Diário!S:S) -> 0 | H35: =SUMIF(Fluxo_Diário!$I:$I,Fluxo_Realizado!$B35,Fluxo_Diário!T:T) -> 0 | I35: =SUMIF(Fluxo_Diário!$I:$I,Fluxo_Realizado!$B35,Fluxo_Diário!U:U) -> 0 | J35: =SUMIF(Fluxo_Diário!$I:$I,Fluxo_Realizado!$B35,Fluxo_Diário!V:V) -> 0 | K35: =SUMIF(Fluxo_Diário!$I:$I,Fluxo_Realizado!$B35,Fluxo_Diário!W:W) -> 0 | L35: =SUMIF(Fluxo_Diário!$I:$I,Fluxo_Realizado!$B35,Fluxo_Diário!X:X) -> 0 | M35: =SUMIF(Fluxo_Diário!$I:$I,Fluxo_Realizado!$B35,Fluxo_Diário!Y:Y) -> 0 | N35: =SUMIF(Fluxo_Diário!$I:$I,Fluxo_Realizado!$B35,Fluxo_Diário!Z:Z) -> 0 | O35: =SUMIF(Fluxo_Diário!$I:$I,Fluxo_Realizado!$B35,Fluxo_Diário!AA:AA) -> 0 | P35: =SUM(C35:O35) -> 0 | Q35: =IF(P35=0,0,AVERAGE(C35:O35)) -> 0
B36: ='Plano de Contas'!B36 -> Impostos federais | C36: =SUMIF(Fluxo_Diário!$I:$I,Fluxo_Realizado!$B36,Fluxo_Diário!O:O) -> 0 | D36: =SUMIF(Fluxo_Diário!$I:$I,Fluxo_Realizado!$B36,Fluxo_Diário!P:P) -> -5425 | E36: =SUMIF(Fluxo_Diário!$I:$I,Fluxo_Realizado!$B36,Fluxo_Diário!Q:Q) -> 0 | F36: =SUMIF(Fluxo_Diário!$I:$I,Fluxo_Realizado!$B36,Fluxo_Diário!R:R) -> 0 | G36: =SUMIF(Fluxo_Diário!$I:$I,Fluxo_Realizado!$B36,Fluxo_Diário!S:S) -> 0 | H36: =SUMIF(Fluxo_Diário!$I:$I,Fluxo_Realizado!$B36,Fluxo_Diário!T:T) -> 0 | I36: =SUMIF(Fluxo_Diário!$I:$I,Fluxo_Realizado!$B36,Fluxo_Diário!U:U) -> 0 | J36: =SUMIF(Fluxo_Diário!$I:$I,Fluxo_Realizado!$B36,Fluxo_Diário!V:V) -> 0 | K36: =SUMIF(Fluxo_Diário!$I:$I,Fluxo_Realizado!$B36,Fluxo_Diário!W:W) -> 0 | L36: =SUMIF(Fluxo_Diário!$I:$I,Fluxo_Realizado!$B36,Fluxo_Diário!X:X) -> 0 | M36: =SUMIF(Fluxo_Diário!$I:$I,Fluxo_Realizado!$B36,Fluxo_Diário!Y:Y) -> 0 | N36: =SUMIF(Fluxo_Diário!$I:$I,Fluxo_Realizado!$B36,Fluxo_Diário!Z:Z) -> 0 | O36: =SUMIF(Fluxo_Diário!$I:$I,Fluxo_Realizado!$B36,Fluxo_Diário!AA:AA) -> 0 | P36: =SUM(C36:O36) -> -5425 | Q36: =IF(P36=0,0,AVERAGE(C36:O36)) -> -417.30769
B37: ='Plano de Contas'!B37 -> Impostos municipais | C37: =SUMIF(Fluxo_Diário!$I:$I,Fluxo_Realizado!$B37,Fluxo_Diário!O:O) -> -2713 | D37: =SUMIF(Fluxo_Diário!$I:$I,Fluxo_Realizado!$B37,Fluxo_Diário!P:P) -> 0 | E37: =SUMIF(Fluxo_Diário!$I:$I,Fluxo_Realizado!$B37,Fluxo_Diário!Q:Q) -> -2302 | F37: =SUMIF(Fluxo_Diário!$I:$I,Fluxo_Realizado!$B37,Fluxo_Diário!R:R) -> -2428 | G37: =SUMIF(Fluxo_Diário!$I:$I,Fluxo_Realizado!$B37,Fluxo_Diário!S:S) -> 0 | H37: =SUMIF(Fluxo_Diário!$I:$I,Fluxo_Realizado!$B37,Fluxo_Diário!T:T) -> -2396 | I37: =SUMIF(Fluxo_Diário!$I:$I,Fluxo_Realizado!$B37,Fluxo_Diário!U:U) -> 0 | J37: =SUMIF(Fluxo_Diário!$I:$I,Fluxo_Realizado!$B37,Fluxo_Diário!V:V) -> 0 | K37: =SUMIF(Fluxo_Diário!$I:$I,Fluxo_Realizado!$B37,Fluxo_Diário!W:W) -> 0 | L37: =SUMIF(Fluxo_Diário!$I:$I,Fluxo_Realizado!$B37,Fluxo_Diário!X:X) -> 0 | M37: =SUMIF(Fluxo_Diário!$I:$I,Fluxo_Realizado!$B37,Fluxo_Diário!Y:Y) -> 0 | N37: =SUMIF(Fluxo_Diário!$I:$I,Fluxo_Realizado!$B37,Fluxo_Diário!Z:Z) -> 0 | O37: =SUMIF(Fluxo_Diário!$I:$I,Fluxo_Realizado!$B37,Fluxo_Diário!AA:AA) -> 0 | P37: =SUM(C37:O37) -> -9839 | Q37: =IF(P37=0,0,AVERAGE(C37:O37)) -> -756.84615
B38: ='Plano de Contas'!B38 -> Outras despesas variáveis | C38: =SUMIF(Fluxo_Diário!$I:$I,Fluxo_Realizado!$B38,Fluxo_Diário!O:O) -> 0 | D38: =SUMIF(Fluxo_Diário!$I:$I,Fluxo_Realizado!$B38,Fluxo_Diário!P:P) -> 0 | E38: =SUMIF(Fluxo_Diário!$I:$I,Fluxo_Realizado!$B38,Fluxo_Diário!Q:Q) -> 0 | F38: =SUMIF(Fluxo_Diário!$I:$I,Fluxo_Realizado!$B38,Fluxo_Diário!R:R) -> 0 | G38: =SUMIF(Fluxo_Diário!$I:$I,Fluxo_Realizado!$B38,Fluxo_Diário!S:S) -> -2853 | H38: =SUMIF(Fluxo_Diário!$I:$I,Fluxo_Realizado!$B38,Fluxo_Diário!T:T) -> 0 | I38: =SUMIF(Fluxo_Diário!$I:$I,Fluxo_Realizado!$B38,Fluxo_Diário!U:U) -> 0 | J38: =SUMIF(Fluxo_Diário!$I:$I,Fluxo_Realizado!$B38,Fluxo_Diário!V:V) -> 0 | K38: =SUMIF(Fluxo_Diário!$I:$I,Fluxo_Realizado!$B38,Fluxo_Diário!W:W) -> 0 | L38: =SUMIF(Fluxo_Diário!$I:$I,Fluxo_Realizado!$B38,Fluxo_Diário!X:X) -> 0 | M38: =SUMIF(Fluxo_Diário!$I:$I,Fluxo_Realizado!$B38,Fluxo_Diário!Y:Y) -> 0 | N38: =SUMIF(Fluxo_Diário!$I:$I,Fluxo_Realizado!$B38,Fluxo_Diário!Z:Z) -> 0 | O38: =SUMIF(Fluxo_Diário!$I:$I,Fluxo_Realizado!$B38,Fluxo_Diário!AA:AA) -> 0 | P38: =SUM(C38:O38) -> -2853 | Q38: =IF(P38=0,0,AVERAGE(C38:O38)) -> -219.46154
B39: ='Plano de Contas'!B39 -> ENTRADA FL. INVESTIMENTO | C39: =SUM(C40:C41) -> 0 | D39: =SUM(D40:D41) -> 0 | E39: =SUM(E40:E41) -> 0 | F39: =SUM(F40:F41) -> 0 | G39: =SUM(G40:G41) -> 0 | H39: =SUM(H40:H41) -> 0 | I39: =SUM(I40:I41) -> 0 | J39: =SUM(J40:J41) -> 0 | ... O39: =SUM(O40:O41) -> 0 | P39: =SUM(C39:O39) -> 0 | Q39: =IF(P39=0,0,AVERAGE(C39:O39)) -> 0
B40: ='Plano de Contas'!B40 -> Resgate Aplicações Financeiras | C40: =SUMIF(Fluxo_Diário!$I:$I,Fluxo_Realizado!$B40,Fluxo_Diário!O:O) -> 0 | D40: =SUMIF(Fluxo_Diário!$I:$I,Fluxo_Realizado!$B40,Fluxo_Diário!P:P) -> 0 | E40: =SUMIF(Fluxo_Diário!$I:$I,Fluxo_Realizado!$B40,Fluxo_Diário!Q:Q) -> 0 | F40: =SUMIF(Fluxo_Diário!$I:$I,Fluxo_Realizado!$B40,Fluxo_Diário!R:R) -> 0 | G40: =SUMIF(Fluxo_Diário!$I:$I,Fluxo_Realizado!$B40,Fluxo_Diário!S:S) -> 0 | H40: =SUMIF(Fluxo_Diário!$I:$I,Fluxo_Realizado!$B40,Fluxo_Diário!T:T) -> 0 | I40: =SUMIF(Fluxo_Diário!$I:$I,Fluxo_Realizado!$B40,Fluxo_Diário!U:U) -> 0 | J40: =SUMIF(Fluxo_Diário!$I:$I,Fluxo_Realizado!$B40,Fluxo_Diário!V:V) -> 0 | K40: =SUMIF(Fluxo_Diário!$I:$I,Fluxo_Realizado!$B40,Fluxo_Diário!W:W) -> 0 | L40: =SUMIF(Fluxo_Diário!$I:$I,Fluxo_Realizado!$B40,Fluxo_Diário!X:X) -> 0 | M40: =SUMIF(Fluxo_Diário!$I:$I,Fluxo_Realizado!$B40,Fluxo_Diário!Y:Y) -> 0 | N40: =SUMIF(Fluxo_Diário!$I:$I,Fluxo_Realizado!$B40,Fluxo_Diário!Z:Z) -> 0 | O40: =SUMIF(Fluxo_Diário!$I:$I,Fluxo_Realizado!$B40,Fluxo_Diário!AA:AA) -> 0 | P40: =SUM(C40:O40) -> 0 | Q40: =IF(P40=0,0,AVERAGE(C40:O40)) -> 0
B41: ='Plano de Contas'!B41 -> Venda Ativo | C41: =SUMIF(Fluxo_Diário!$I:$I,Fluxo_Realizado!$B41,Fluxo_Diário!O:O) -> 0 | D41: =SUMIF(Fluxo_Diário!$I:$I,Fluxo_Realizado!$B41,Fluxo_Diário!P:P) -> 0 | E41: =SUMIF(Fluxo_Diário!$I:$I,Fluxo_Realizado!$B41,Fluxo_Diário!Q:Q) -> 0 | F41: =SUMIF(Fluxo_Diário!$I:$I,Fluxo_Realizado!$B41,Fluxo_Diário!R:R) -> 0 | G41: =SUMIF(Fluxo_Diário!$I:$I,Fluxo_Realizado!$B41,Fluxo_Diário!S:S) -> 0 | H41: =SUMIF(Fluxo_Diário!$I:$I,Fluxo_Realizado!$B41,Fluxo_Diário!T:T) -> 0 | I41: =SUMIF(Fluxo_Diário!$I:$I,Fluxo_Realizado!$B41,Fluxo_Diário!U:U) -> 0 | J41: =SUMIF(Fluxo_Diário!$I:$I,Fluxo_Realizado!$B41,Fluxo_Diário!V:V) -> 0 | K41: =SUMIF(Fluxo_Diário!$I:$I,Fluxo_Realizado!$B41,Fluxo_Diário!W:W) -> 0 | L41: =SUMIF(Fluxo_Diário!$I:$I,Fluxo_Realizado!$B41,Fluxo_Diário!X:X) -> 0 | M41: =SUMIF(Fluxo_Diário!$I:$I,Fluxo_Realizado!$B41,Fluxo_Diário!Y:Y) -> 0 | N41: =SUMIF(Fluxo_Diário!$I:$I,Fluxo_Realizado!$B41,Fluxo_Diário!Z:Z) -> 0 | O41: =SUMIF(Fluxo_Diário!$I:$I,Fluxo_Realizado!$B41,Fluxo_Diário!AA:AA) -> 0 | P41: =SUM(C41:O41) -> 0 | Q41: =IF(P41=0,0,AVERAGE(C41:O41)) -> 0
B42: ='Plano de Contas'!B42 -> SAÍDA FL. INVESTIMENTO | C42: =SUM(C43:C45) -> 0 | D42: =SUM(D43:D45) -> 0 | E42: =SUM(E43:E45) -> 0 | F42: =SUM(F43:F45) -> 0 | G42: =SUM(G43:G45) -> 0 | H42: =SUM(H43:H45) -> 0 | I42: =SUM(I43:I45) -> 0 | J42: =SUM(J43:J45) -> 0 | ... O42: =SUM(O43:O45) -> 0 | P42: =SUM(C42:O42) -> 0 | Q42: =IF(P42=0,0,AVERAGE(C42:O42)) -> 0
B43: ='Plano de Contas'!B43 -> Aplicação financeira | C43: =SUMIF(Fluxo_Diário!$I:$I,Fluxo_Realizado!$B43,Fluxo_Diário!O:O) -> 0 | D43: =SUMIF(Fluxo_Diário!$I:$I,Fluxo_Realizado!$B43,Fluxo_Diário!P:P) -> 0 | E43: =SUMIF(Fluxo_Diário!$I:$I,Fluxo_Realizado!$B43,Fluxo_Diário!Q:Q) -> 0 | F43: =SUMIF(Fluxo_Diário!$I:$I,Fluxo_Realizado!$B43,Fluxo_Diário!R:R) -> 0 | G43: =SUMIF(Fluxo_Diário!$I:$I,Fluxo_Realizado!$B43,Fluxo_Diário!S:S) -> 0 | H43: =SUMIF(Fluxo_Diário!$I:$I,Fluxo_Realizado!$B43,Fluxo_Diário!T:T) -> 0 | I43: =SUMIF(Fluxo_Diário!$I:$I,Fluxo_Realizado!$B43,Fluxo_Diário!U:U) -> 0 | J43: =SUMIF(Fluxo_Diário!$I:$I,Fluxo_Realizado!$B43,Fluxo_Diário!V:V) -> 0 | K43: =SUMIF(Fluxo_Diário!$I:$I,Fluxo_Realizado!$B43,Fluxo_Diário!W:W) -> 0 | L43: =SUMIF(Fluxo_Diário!$I:$I,Fluxo_Realizado!$B43,Fluxo_Diário!X:X) -> 0 | M43: =SUMIF(Fluxo_Diário!$I:$I,Fluxo_Realizado!$B43,Fluxo_Diário!Y:Y) -> 0 | N43: =SUMIF(Fluxo_Diário!$I:$I,Fluxo_Realizado!$B43,Fluxo_Diário!Z:Z) -> 0 | O43: =SUMIF(Fluxo_Diário!$I:$I,Fluxo_Realizado!$B43,Fluxo_Diário!AA:AA) -> 0 | P43: =SUM(C43:O43) -> 0 | Q43: =IF(P43=0,0,AVERAGE(C43:O43)) -> 0
B44: ='Plano de Contas'!B44 -> Ativo imobilizado | C44: =SUMIF(Fluxo_Diário!$I:$I,Fluxo_Realizado!$B44,Fluxo_Diário!O:O) -> 0 | D44: =SUMIF(Fluxo_Diário!$I:$I,Fluxo_Realizado!$B44,Fluxo_Diário!P:P) -> 0 | E44: =SUMIF(Fluxo_Diário!$I:$I,Fluxo_Realizado!$B44,Fluxo_Diário!Q:Q) -> 0 | F44: =SUMIF(Fluxo_Diário!$I:$I,Fluxo_Realizado!$B44,Fluxo_Diário!R:R) -> 0 | G44: =SUMIF(Fluxo_Diário!$I:$I,Fluxo_Realizado!$B44,Fluxo_Diário!S:S) -> 0 | H44: =SUMIF(Fluxo_Diário!$I:$I,Fluxo_Realizado!$B44,Fluxo_Diário!T:T) -> 0 | I44: =SUMIF(Fluxo_Diário!$I:$I,Fluxo_Realizado!$B44,Fluxo_Diário!U:U) -> 0 | J44: =SUMIF(Fluxo_Diário!$I:$I,Fluxo_Realizado!$B44,Fluxo_Diário!V:V) -> 0 | K44: =SUMIF(Fluxo_Diário!$I:$I,Fluxo_Realizado!$B44,Fluxo_Diário!W:W) -> 0 | L44: =SUMIF(Fluxo_Diário!$I:$I,Fluxo_Realizado!$B44,Fluxo_Diário!X:X) -> 0 | M44: =SUMIF(Fluxo_Diário!$I:$I,Fluxo_Realizado!$B44,Fluxo_Diário!Y:Y) -> 0 | N44: =SUMIF(Fluxo_Diário!$I:$I,Fluxo_Realizado!$B44,Fluxo_Diário!Z:Z) -> 0 | O44: =SUMIF(Fluxo_Diário!$I:$I,Fluxo_Realizado!$B44,Fluxo_Diário!AA:AA) -> 0 | P44: =SUM(C44:O44) -> 0 | Q44: =IF(P44=0,0,AVERAGE(C44:O44)) -> 0
B45: ='Plano de Contas'!B45 -> Treinamento | C45: =SUMIF(Fluxo_Diário!$I:$I,Fluxo_Realizado!$B45,Fluxo_Diário!O:O) -> 0 | D45: =SUMIF(Fluxo_Diário!$I:$I,Fluxo_Realizado!$B45,Fluxo_Diário!P:P) -> 0 | E45: =SUMIF(Fluxo_Diário!$I:$I,Fluxo_Realizado!$B45,Fluxo_Diário!Q:Q) -> 0 | F45: =SUMIF(Fluxo_Diário!$I:$I,Fluxo_Realizado!$B45,Fluxo_Diário!R:R) -> 0 | G45: =SUMIF(Fluxo_Diário!$I:$I,Fluxo_Realizado!$B45,Fluxo_Diário!S:S) -> 0 | H45: =SUMIF(Fluxo_Diário!$I:$I,Fluxo_Realizado!$B45,Fluxo_Diário!T:T) -> 0 | I45: =SUMIF(Fluxo_Diário!$I:$I,Fluxo_Realizado!$B45,Fluxo_Diário!U:U) -> 0 | J45: =SUMIF(Fluxo_Diário!$I:$I,Fluxo_Realizado!$B45,Fluxo_Diário!V:V) -> 0 | K45: =SUMIF(Fluxo_Diário!$I:$I,Fluxo_Realizado!$B45,Fluxo_Diário!W:W) -> 0 | L45: =SUMIF(Fluxo_Diário!$I:$I,Fluxo_Realizado!$B45,Fluxo_Diário!X:X) -> 0 | M45: =SUMIF(Fluxo_Diário!$I:$I,Fluxo_Realizado!$B45,Fluxo_Diário!Y:Y) -> 0 | N45: =SUMIF(Fluxo_Diário!$I:$I,Fluxo_Realizado!$B45,Fluxo_Diário!Z:Z) -> 0 | O45: =SUMIF(Fluxo_Diário!$I:$I,Fluxo_Realizado!$B45,Fluxo_Diário!AA:AA) -> 0 | P45: =SUM(C45:O45) -> 0 | Q45: =IF(P45=0,0,AVERAGE(C45:O45)) -> 0
B46: ='Plano de Contas'!B46 -> ENTRADA FL. FINANCIAMENTO | C46: =SUM(C47:C48) -> 0 | D46: =SUM(D47:D48) -> 0 | E46: =SUM(E47:E48) -> 0 | F46: =SUM(F47:F48) -> 0 | G46: =SUM(G47:G48) -> 0 | H46: =SUM(H47:H48) -> 0 | I46: =SUM(I47:I48) -> 0 | J46: =SUM(J47:J48) -> 0 | ... O46: =SUM(O47:O48) -> 0 | P46: =SUM(C46:O46) -> 0 | Q46: =IF(P46=0,0,AVERAGE(C46:O46)) -> 0
B47: ='Plano de Contas'!B47 -> Aporte Sócios | C47: =SUMIF(Fluxo_Diário!$I:$I,Fluxo_Realizado!$B47,Fluxo_Diário!O:O) -> 0 | D47: =SUMIF(Fluxo_Diário!$I:$I,Fluxo_Realizado!$B47,Fluxo_Diário!P:P) -> 0 | E47: =SUMIF(Fluxo_Diário!$I:$I,Fluxo_Realizado!$B47,Fluxo_Diário!Q:Q) -> 0 | F47: =SUMIF(Fluxo_Diário!$I:$I,Fluxo_Realizado!$B47,Fluxo_Diário!R:R) -> 0 | G47: =SUMIF(Fluxo_Diário!$I:$I,Fluxo_Realizado!$B47,Fluxo_Diário!S:S) -> 0 | H47: =SUMIF(Fluxo_Diário!$I:$I,Fluxo_Realizado!$B47,Fluxo_Diário!T:T) -> 0 | I47: =SUMIF(Fluxo_Diário!$I:$I,Fluxo_Realizado!$B47,Fluxo_Diário!U:U) -> 0 | J47: =SUMIF(Fluxo_Diário!$I:$I,Fluxo_Realizado!$B47,Fluxo_Diário!V:V) -> 0 | K47: =SUMIF(Fluxo_Diário!$I:$I,Fluxo_Realizado!$B47,Fluxo_Diário!W:W) -> 0 | L47: =SUMIF(Fluxo_Diário!$I:$I,Fluxo_Realizado!$B47,Fluxo_Diário!X:X) -> 0 | M47: =SUMIF(Fluxo_Diário!$I:$I,Fluxo_Realizado!$B47,Fluxo_Diário!Y:Y) -> 0 | N47: =SUMIF(Fluxo_Diário!$I:$I,Fluxo_Realizado!$B47,Fluxo_Diário!Z:Z) -> 0 | O47: =SUMIF(Fluxo_Diário!$I:$I,Fluxo_Realizado!$B47,Fluxo_Diário!AA:AA) -> 0 | P47: =SUM(C47:O47) -> 0 | Q47: =IF(P47=0,0,AVERAGE(C47:O47)) -> 0
B48: ='Plano de Contas'!B48 -> Recebimento de Empréstimo | C48: =IF(SUM(C54,C64,C65,C49)<0,-1*SUM(C54,C64,C65,C49),0) -> 0 | D48: =IF(SUM(D54,D64,D65,D49)<0,-1*SUM(D54,D64,D65,D49),0) -> 0 | E48: =IF(SUM(E54,E64,E65,E49)<0,-1*SUM(E54,E64,E65,E49),0) -> 0 | F48: =IF(SUM(F54,F64,F65,F49)<0,-1*SUM(F54,F64,F65,F49),0) -> 0 | G48: =IF(SUM(G54,G64,G65,G49)<0,-1*SUM(G54,G64,G65,G49),0) -> 0 | H48: =IF(SUM(H54,H64,H65,H49)<0,-1*SUM(H54,H64,H65,H49),0) -> 0 | I48: =IF(SUM(I54,I64,I65,I49)<0,-1*SUM(I54,I64,I65,I49),0) -> 0 | J48: =IF(SUM(J54,J64,J65,J49)<0,-1*SUM(J54,J64,J65,J49),0) -> 0 | ... N48: =IF(SUM(N54,N64,N65,N49)<0,-1*SUM(N54,N64,N65,N49),0) -> 0 | P48: =SUM(C48:O48) -> 0 | Q48: =IF(P48=0,0,AVERAGE(C48:O48)) -> 0
B49: ='Plano de Contas'!B49 -> SAÍDA FL. FINANCIAMENTO | C49: =SUM(C50:C52) -> -15516.8 | D49: =SUM(D50:D52) -> -556.4 | E49: =SUM(E50:E52) -> -19763.6 | F49: =SUM(F50:F52) -> -5260.8 | G49: =SUM(G50:G52) -> -15817.2 | H49: =SUM(H50:H52) -> -32732.4 | I49: =SUM(I50:I52) -> -28394.8 | J49: =SUM(J50:J52) -> 0 | ... O49: =SUM(O50:O52) -> 0 | P49: =SUM(C49:O49) -> -118042 | Q49: =IF(P49=0,0,AVERAGE(C49:O49)) -> -9080.1538
B50: ='Plano de Contas'!B50 -> Distribuição de Lucros | C50: =IF(C66>0,-40%*C66,0) -> -15516.8 | D50: =IF(D66>0,-40%*D66,0) -> -556.4 | E50: =IF(E66>0,-40%*E66,0) -> -19763.6 | F50: =IF(F66>0,-40%*F66,0) -> -5260.8 | G50: =IF(G66>0,-40%*G66,0) -> -15817.2 | H50: =IF(H66>0,-40%*H66,0) -> -32732.4 | I50: =IF(I66>0,-40%*I66,0) -> -28394.8 | J50: =IF(J66>0,-40%*J66,0) -> 0 | ... O50: =IF(O66>0,-40%*O66,0) -> 0 | P50: =SUM(C50:O50) -> -118042 | Q50: =IF(P50=0,0,AVERAGE(C50:O50)) -> -9080.1538
B51: ='Plano de Contas'!B51 -> Pgto. empréstimo (principal) | D51: =IF(C48=0,0,-C48) -> 0 | E51: =IF(D48=0,0,-D48) -> 0 | F51: =IF(E48=0,0,-E48) -> 0 | G51: =IF(F48=0,0,-F48) -> 0 | H51: =IF(G48=0,0,-G48) -> 0 | I51: =IF(H48=0,0,-H48) -> 0 | J51: =IF(I48=0,0,-I48) -> 0 | K51: =IF(J48=0,0,-J48) -> 0 | ... O51: =IF(N48=0,0,-N48) -> 0 | P51: =SUM(C51:O51) -> 0 | Q51: =IF(P51=0,0,AVERAGE(C51:O51)) -> 0
B52: ='Plano de Contas'!B52 -> Pgto. empréstimo (juros) | D52: =IF(D51=0,0,2%*D51) -> 0 | E52: =IF(E51=0,0,2%*E51) -> 0 | F52: =IF(F51=0,0,2%*F51) -> 0 | G52: =IF(G51=0,0,2%*G51) -> 0 | H52: =IF(H51=0,0,2%*H51) -> 0 | I52: =IF(I51=0,0,2%*I51) -> 0 | J52: =IF(J51=0,0,2%*J51) -> 0 | K52: =IF(K51=0,0,2%*K51) -> 0 | ... O52: =IF(O51=0,0,2%*O51) -> 0 | P52: =SUM(C52:O52) -> 0 | Q52: =IF(P52=0,0,AVERAGE(C52:O52)) -> 0
B54: Saldos Iniciais | C54: =Premissas!C5 -> 0 | D54: =C62 -> 23275.2 | E54: =D62 -> 24109.8 | F54: =E62 -> 53755.2 | G54: =F62 -> 61646.4 | H54: =G62 -> 85372.2 | I54: =H62 -> 134470.8 | J54: =I62 -> 177063 | K54: =J62 -> 175708 | ... O54: =N62 -> 175708 | P54: =SUM(C54:O54) -> 1438232.6 | Q54: =IF(P54=0,0,AVERAGE(C54:O54)) -> 110633.28
B55: =B5 -> RECEITAS OPERACIONAIS | C55: =C5 -> 56325 | D55: =D5 -> 19889 | E55: =E5 -> 62947 | F55: =F5 -> 31838 | G55: =G5 -> 53566 | H55: =H5 -> 91372 | I55: =I5 -> 77493 | ... O55: =O5 -> 0 | P55: =SUM(C55:O55) -> 393430 | Q55: =IF(P55=0,0,AVERAGE(C55:O55)) -> 30263.846
B56: =B11 -> DESPESAS FIXAS | C56: =C11 -> -14820 | D56: =D11 -> -10767 | E56: =E11 -> -11236 | F56: =F11 -> -13123 | G56: =G11 -> -11170 | H56: =H11 -> -7145 | I56: =I11 -> -6506 | ... O56: =O11 -> 0 | P56: =SUM(C56:O56) -> -76122 | Q56: =IF(P56=0,0,AVERAGE(C56:O56)) -> -5855.5385
B57: =B33 -> DESPESAS VARIÁVEIS | C57: =C33 -> -2713 | D57: =D33 -> -7731 | E57: =E33 -> -2302 | F57: =F33 -> -5563 | G57: =G33 -> -2853 | H57: =H33 -> -2396 | I57: =I33 -> 0 | ... O57: =O33 -> 0 | P57: =SUM(C57:O57) -> -23558 | Q57: =IF(P57=0,0,AVERAGE(C57:O57)) -> -1812.1538
B58: =B39 -> ENTRADA FL. INVESTIMENTO | C58: =C39 -> 0 | D58: =D39 -> 0 | E58: =E39 -> 0 | F58: =F39 -> 0 | G58: =G39 -> 0 | H58: =H39 -> 0 | I58: =I39 -> 0 | ... O58: =O39 -> 0 | P58: =SUM(C58:O58) -> 0 | Q58: =IF(P58=0,0,AVERAGE(C58:O58)) -> 0
B59: =B42 -> SAÍDA FL. INVESTIMENTO | C59: =C42 -> 0 | D59: =D42 -> 0 | E59: =E42 -> 0 | F59: =F42 -> 0 | G59: =G42 -> 0 | H59: =H42 -> 0 | I59: =I42 -> 0 | ... O59: =O42 -> 0 | P59: =SUM(C59:O59) -> 0 | Q59: =IF(P59=0,0,AVERAGE(C59:O59)) -> 0
B60: =B46 -> ENTRADA FL. FINANCIAMENTO | C60: =C46 -> 0 | D60: =D46 -> 0 | E60: =E46 -> 0 | F60: =F46 -> 0 | G60: =G46 -> 0 | H60: =H46 -> 0 | I60: =I46 -> 0 | ... O60: =O46 -> 0 | P60: =SUM(C60:O60) -> 0 | Q60: =IF(P60=0,0,AVERAGE(C60:O60)) -> 0
B61: =B49 -> SAÍDA FL. FINANCIAMENTO | C61: =C49 -> -15516.8 | D61: =D49 -> -556.4 | E61: =E49 -> -19763.6 | F61: =F49 -> -5260.8 | G61: =G49 -> -15817.2 | H61: =H49 -> -32732.4 | I61: =I49 -> -28394.8 | ... O61: =O49 -> 0 | P61: =SUM(C61:O61) -> -118042 | Q61: =IF(P61=0,0,AVERAGE(C61:O61)) -> -9080.1538
B62: Saldos Finais | C62: =SUM(C54:C61) -> 23275.2 | D62: =SUM(D54:D61) -> 24109.8 | E62: =SUM(E54:E61) -> 53755.2 | F62: =SUM(F54:F61) -> 61646.4 | G62: =SUM(G54:G61) -> 85372.2 | H62: =SUM(H54:H61) -> 134470.8 | I62: =SUM(I54:I61) -> 177063 | J62: =SUM(J54:J61) -> 175708 | ... O62: =SUM(O54:O61) -> 175708 | P62: =SUM(C62:O62) -> 1613940.6 | Q62: =IF(P62=0,0,AVERAGE(C62:O62)) -> 124149.28
B64: Fluxo Operacional | C64: =SUM(C55:C57) -> 38792 | D64: =SUM(D55:D57) -> 1391 | E64: =SUM(E55:E57) -> 49409 | F64: =SUM(F55:F57) -> 13152 | G64: =SUM(G55:G57) -> 39543 | H64: =SUM(H55:H57) -> 81831 | I64: =SUM(I55:I57) -> 70987 | J64: =SUM(J55:J57) -> -1355 | ... Q64: =SUM(Q55:Q57) -> 22596.154
B65: Fluxo de Investimento | C65: =SUM(C58:C59) -> 0 | D65: =SUM(D58:D59) -> 0 | E65: =SUM(E58:E59) -> 0 | F65: =SUM(F58:F59) -> 0 | G65: =SUM(G58:G59) -> 0 | H65: =SUM(H58:H59) -> 0 | I65: =SUM(I58:I59) -> 0 | J65: =SUM(J58:J59) -> 0 | ... Q65: =SUM(Q58:Q59) -> 0
B66: Fluxo de Caixa Livre | C66: =SUM(C64:C65) -> 38792 | D66: =SUM(D64:D65) -> 1391 | E66: =SUM(E64:E65) -> 49409 | F66: =SUM(F64:F65) -> 13152 | G66: =SUM(G64:G65) -> 39543 | H66: =SUM(H64:H65) -> 81831 | I66: =SUM(I64:I65) -> 70987 | J66: =SUM(J64:J65) -> -1355 | ... Q66: =SUM(Q64:Q65) -> 22596.154
B67: Fluxo de Financiamento | C67: =SUM(C60:C61) -> -15516.8 | D67: =SUM(D60:D61) -> -556.4 | E67: =SUM(E60:E61) -> -19763.6 | F67: =SUM(F60:F61) -> -5260.8 | G67: =SUM(G60:G61) -> -15817.2 | H67: =SUM(H60:H61) -> -32732.4 | I67: =SUM(I60:I61) -> -28394.8 | J67: =SUM(J60:J61) -> 0 | ... Q67: =SUM(Q60:Q61) -> -9080.1538
B68: Despesa Fixa / Receita Operacional | C68: =IFERROR(-C56/C55,"") -> 0.26311585 | D68: =IFERROR(-D56/D55,"") -> 0.54135452 | E68: =IFERROR(-E56/E55,"") -> 0.17849937 | F68: =IFERROR(-F56/F55,"") -> 0.41218041 | G68: =IFERROR(-G56/G55,"") -> 0.2085278 | H68: =IFERROR(-H56/H55,"") -> 0.078196822 | I68: =IFERROR(-I56/I55,"") -> 0.08395597 | J68: =IFERROR(-J56/J55,"") | ... O68: =IFERROR(-O56/O55,"")
B69: Despesa Variável / Receita Operacional | C69: =-C57/C55 -> 0.048166889 | D69: =-D57/D55 -> 0.38870733 | E69: =-E57/E55 -> 0.036570448 | F69: =-F57/F55 -> 0.17472831 | G69: =-G57/G55 -> 0.053261397 | H69: =-H57/H55 -> 0.026222475 | I69: =-I57/I55 -> 0 | J69: =-J57/J55 -> #DIV/0! | ... O69: =-O57/O55 -> #DIV/0!
B70: Margem de Contribuição | C70: =1-C69 -> 0.95183311 | D70: =1-D69 -> 0.61129267 | E70: =1-E69 -> 0.96342955 | F70: =1-F69 -> 0.82527169 | G70: =1-G69 -> 0.9467386 | H70: =1-H69 -> 0.97377752 | I70: =1-I69 -> 1 | J70: =1-J69 -> #DIV/0! | ... O70: =1-O69 -> #DIV/0!
B71: Margem de Lucro | C71: =1-C70 -> 0.048166889 | D71: =1-D70 -> 0.38870733 | E71: =1-E70 -> 0.036570448 | F71: =1-F70 -> 0.17472831 | G71: =1-G70 -> 0.053261397 | H71: =1-H70 -> 0.026222475 | I71: =1-I70 -> 0 | J71: =1-J70 -> #DIV/0! | ... O71: =1-O70 -> #DIV/0!
B72: Ponto de Equilíbrio | C72: =-C56/C70 -> 15569.956 | D72: =-D56/D70 -> 17613.494 | E72: =-E56/E70 -> 11662.503 | F72: =-F56/F70 -> 15901.43 | G72: =-G56/G70 -> 11798.399 | H72: =-H56/H70 -> 7337.4049 | I72: =-I56/I70 -> 6506 | J72: =-J56/J70 -> #DIV/0! | ... O72: =-O56/O70 -> #DIV/0!

Sheet Relatório_RealxProj
B2: Relatório Financeiro Anual | I2: =Premissas!C4 -> 2020
B3: Protech do Brasil | I3: Ref.: Julho/ 2020
B6: Fluxo de Resultados | M6: =Fluxo_Diário_DB!J21 -> Margem de Contribuição
G7: Real Mil | H7: Análise Crítica | S7: Análise Crítica
H8: Queda na receita devido perda de renovação contratual do Cliente EFG. | S8: Margem de Contribuição muito acima do teto estabelecido. Não haverá margem de lucro para o mês de julho/20.
H13: Plano de Ação | S13: Plano de Ação
H14: Propor reunião com o Comercial para projeção de novos clientes dentro do período vigente. Prazo - 05/08/2020. | S14: Propor ação conjunta com as áreas de produção para implementação de projetos de redução de despesa fixa fixo.
H19: Análise do Período | S19: Análise do Período
H20: Projeção | J20: =MAX(Fluxo_Diário_DB!L4:W4) -> 335.6025 | S20: Projeção | U20: =AVERAGE(Fluxo_Diário_DB!L21:W21) -> 0.79455164
H21: Realizado | J21: =MAX(Fluxo_Diário_DB!L6:W6) -> 393.43 | S21: Realizado | U21: =AVERAGE(Fluxo_Diário_DB!L23:W23) -> 0.89604902
H22: Performance | J22: =J21/J20 -> 1.1723095 | S22: Performance | U22: =U21/U20 -> 1.1277417
G23: Real Mil | H23: Análise Crítica | M23: =Fluxo_Diário_DB!J26 -> Margem de Lucro
H24: Queda na despesa fixa devido a realocação dos recursos do cliente EFG. | S24: Análise Crítica
S25: Margem de Lucro abaixo do esperado, alavancado pelas recentes perdas de receita, principalmente por não renovação com clientes.
H29: Plano de Ação
H30: Aumento de Receita Operacional visando o alcance das despesas fixas propostas para o período. | S30: Plano de Ação
S31: Propor reunião com o Comercial para projeção de novos clientes.
H35: Análise do Período | S35: Análise do Período
H36: Projeção | J36: =MAX(Fluxo_Diário_DB!L10:W10) -> 134.28 | S36: Projeção | U36: =AVERAGE(Fluxo_Diário_DB!L26:W26) -> 0.20544836
H37: Realizado | J37: =MAX(Fluxo_Diário_DB!L12:W12) -> 76.122 | S37: Realizado | U37: =AVERAGE(Fluxo_Diário_DB!L28:W28) -> 0.10395098
H38: Performance | J38: =J37/J36 -> 0.56689008 | S38: Performance | U38: =U37/U36 -> 0.50597132
G39: Real Mil | H39: Análise Crítica | M39: =Fluxo_Diário_DB!J31 -> Ponto de Equilíbrio
H40: Redução do custo variável devido a perda de produção relacionada ao cliente EFG. | R40: Real Mil | S40: Análise Crítica
S41: Ponto de equilíbrio proporcional à queda de despesa fixa para o mesmo período.
H45: Plano de Ação
H46: Aumento de Receita Operacional visando o alcance das despesas variáveis propostas para o período. | S46: Plano de Ação
S47: Aumento de Receita Operacional visando a receita fixa proposta pro período.
H51: Análise do Período | S51: Análise do Período
H52: Projeção | J52: =MAX(Fluxo_Diário_DB!L16:W16) -> 70.416517 | S52: Projeção | U52: =AVERAGE(Fluxo_Diário_DB!L31:W31) -> 14.096191
H53: Realizado | J53: =MAX(Fluxo_Diário_DB!L18:W18) -> 23.558 | S53: Realizado | U53: =AVERAGE(Fluxo_Diário_DB!L33:W33) -> 12.341313
H54: Performance | J54: =J53/J52 -> 0.33455219 | S54: Performance | U54: =U53/U52 -> 0.87550689
